Workbook
Name TablaTasas: 'Tasas de Cambio'!$B$11:$E$15
Name NumPersonas: 'Tasas de Cambio'!$C$5

Sheet Resumen Comparativo
A1: COMPARATIVO DE PLANES — EUROPA 2027
A2: 3 personas
A4: Itinerario | B4: Crucero (11 días) | C4: Crucero y Zurich (16 días) | D4: Cotización (31 días, plan completo) | E4: Opción 4: Múnich (16 días, 100% cotizado)
A5: Ruta | B5: Barcelona → Crucero Mediterráneo → Venecia | C5: Zúrich → Barcelona → Crucero → Venecia | D5: Zúrich → París → Barcelona → Crucero → Venecia → Roma → Praga → Berlín → Múnich | E5: Múnich → Barcelona → Crucero → Venecia
A6: Fechas | B6: 5 – 16 mayo 2027 | C6: 1 – 16 mayo 2027 | D6: 29 abril – 30 mayo 2027 | E6: 1 – 16 mayo 2027
A7: Desglose por categoría (COP)
A8: Vuelos y Trenes | B8: 8840310 | C8: 12637329 | D8: 16266882 | E8: 10380005
A9: Traslados | B9: 1241448.6 | C9: 1606218.6 | D9: 2467285.8 | E9: 1804038.6
A10: Alojamiento | B10: 3450552 | C10: 7098252 | D10: 12743220 | E10: 5888442
A11: Crucero | B11: 6468682.5 | C11: 6468682.5 | D11: 6468682.5 | E11: 6468682.5
A12: Tours y Excursiones | B12: 2171956.5 | C12: 9876447 | D12: 12080007 | E12: 6322613.8
A13: Comidas | B13: 1800288 | C13: 4475268 | D13: 8377740 | E13: 3600576
A14: Seguro de Viaje | B14: 450000 | C14: 450000 | D14: 760054 | E14: 450000
A15: Otros y Extras | B15: 2400384 | C15: 2400384 | D15: 2400384 | E15: 2400384
A16: TOTAL GENERAL (COP) | B16: 26823622 | C16: 45012581 | D16: 61564256 | E16: 37314742
A17: TOTAL GENERAL (USD) | B17: 8334.85 | C17: 13986.66 | D17: 19129.731 | E17: 11594.73
A19: Por persona (COP)
A20: Costo por persona (COP) | B20: 8941207.2 | C20: 15004194 | D20: 20521419 | E20: 12438247
A21: Costo por persona (USD) | B21: 2778.28 | C21: 4662.22 | D21: 6376.5769 | E21: 3864.91
A22: Costo por persona/día (COP) | B22: 812837.02 | C22: 937762.11 | D22: 661981.24 | E22: 777390.46
E23: 740083.04
A25: Los 4 planes ya están completamente cotizados (sin pendientes). "Crucero" no incluye Zúrich; "Crucero y Zurich" agrega la estadía en Suiza; "Opción 4" reemplaza Zúrich por Múnich (misma duración); "Cotización" es el plan completo de un mes por 9 ciudades.

Sheet Instrucciones
B2: EUROPA 2027 — COTIZACIÓN DE VIAJE
B3: Itinerario completo · Del 30 de abril al 29 de mayo de 2027 (30 días / 29 noches) · 3 personas
B5: CÓMO USAR ESTA PLANTILLA
B6: 1. Tasas de Cambio | C6: Actualiza las tasas de cada moneda a COP (celdas amarillas). Trae valores de referencia de hoy; verifícalos antes de cotizar en firme.
B7: 2. Config. rápida | C7: En la misma hoja, ajusta el número de personas si cambia (por defecto 3) — todo el archivo se recalcula solo.
B8: 3. Cotización | C8: Registra cada costo en su MONEDA ORIGINAL (la que te cobra el proveedor: CHF, EUR, CZK, USD o COP). No conviertas manualmente: la hoja lo hace por ti.
B9: 4. Celdas amarillas | C9: Son las únicas que debes llenar: costo unitario, cantidad y moneda. Las demás columnas (totales, conversión) son fórmulas — no las edites.
B10: 5. Filas ya cargadas | C10: Contienen la estructura del itinerario (ciudad, fechas, concepto) para que solo agregues precios. Puedes insertar filas nuevas dentro de cada bloque si necesitas más líneas — copia el formato de una fila existente.
B11: 6. Resumen | C11: Muestra el total por categoría, el total general y el costo por persona, en COP y en USD, actualizados automáticamente.
B13: LEYENDA DE COLORES
C14: Celda para llenar (dato editable: costo, cantidad, moneda, tasa de cambio)
C15: Fórmula / cálculo automático — no editar
C16: Encabezados y títulos de sección
B18: ESTRUCTURA DEL ARCHIVO
B19: Tasas de Cambio | C19: Tipos de cambio y número de personas (parámetros del archivo).
B20: Cotización | C20: Detalle línea por línea de todo el itinerario: vuelos, trenes, alojamiento, crucero, tours, comidas, seguro y extras.
B21: Resumen | C21: Tablero con totales por categoría, total general y costo por persona (COP y USD).
B24: Nota: las tasas de cambio precargadas son referenciales (agosto 2026, fuente Xe.com). Los precios de vuelos, hoteles, crucero y tours NO están incluidos — debes cotizarlos con tus proveedores y digitarlos en la hoja 'Cotización'.

Sheet Tasas de Cambio
B2: TASAS DE CAMBIO Y CONFIGURACIÓN
B4: CONFIGURACIÓN DEL VIAJE
B5: Número de personas | C5: 3 | D5: ← editable, usado en toda la hoja Resumen
B6: Moneda base del reporte | C6: COP | D6: Todos los totales se consolidan en Pesos Colombianos
B7: Fecha de actualización de tasas | C7: 30/08/2026 | E7: 1.05
B9: TIPOS DE CAMBIO A PESO COLOMBIANO (COP)
B10: Código | C10: Moneda / País(es) donde se usa | D10: Símbolo | E10: Tasa (1 unidad = X COP) | F10: Fuente / Notas
B11: EUR | C11: Euro — Francia, España, Italia, Croacia, Alemania | D11: € | E11: =3608*$E$7 -> 3788.4 | F11: Xe.com, referencial 24-ago-2026
B12: CHF | C12: Franco suizo — Suiza | D12: CHF | E12: =3846*$E$7 -> 4038.3 | F12: Xe.com, referencial 24-ago-2026
B13: CZK | C13: Corona checa — República Checa | D13: Kč | E13: =149.5*$E$7 -> 156.97 | F13: Xe.com, referencial 24-ago-2026
B14: USD | C14: Dólar estadounidense — vuelos internacionales / referencia | D14: US$ | E14: =3108*$E$7 -> 3263.4 | F14: Xe.com, referencial 24-ago-2026
B15: COP | C15: Peso colombiano — Colombia (moneda base) | D15: $ | E15: 1 | F15: Moneda base — no requiere conversión
B17: ⚠ Actualiza estas 5 celdas amarillas con la tasa del día antes de enviar la cotización final al cliente. Toda la hoja 'Cotización' y 'Resumen' se recalcula automáticamente.

Sheet Cotización
A2: COTIZACIÓN DETALLADA — EUROPA 2027 (30 Abr – 29 May 2027) | O2: Vuelos y Trenes | P2: EUR
O3: Traslados | P3: CHF
A4: Categoría | B4: Ciudad / País | C4: Fechas | D4: Concepto / Descripción | E4: Moneda | F4: Costo Unitario (moneda original) | G4: Cantidad | H4: Costo Total (moneda original) | I4: Tasa de Cambio a COP | J4: Costo Total (COP) | K4: Costo por Persona (COP) | L4: Notas | M4: Fecha confirmación precio | O4: Alojamiento | P4: CZK
A5: Seguro de Viaje | B5: Internacional | C5: 7 – 31 May 2027 (25 días de cobertura) | D5: Asistencia médica internacional | E5: COP | F5: 443970 | G5: 3 | H5: =IFERROR(F5*G5,0) -> 1331910 | I5: {=IFERROR(INDEX('Tasas de Cambio'!$E$11:$E$15,MATCH(E5,'Tasas de Cambio'!$B$11:$B$15,0)),0)} -> 1 | J5: =IFERROR(H5*I5,0) -> 1331910 | K5: =IFERROR(J5/'Tasas de Cambio'!$C$5,0) -> 443970 | L5: Asistencia médica internacional, cobertura USD 60.000 (Cuponatic). https://www.cuponatic.com.co/descuento/asistencia-medica-internacional-cobertura-de-usd-60-000?m=tarjetas-de-asistencia&id_descuento=212587 | M5: 27 ago 2026
A6: Vuelos y Trenes | B6: Bogota / Barcelona | C6: 7 May 2027 | D6: Vuelo internacional Bogotá → Barcelona (ida y vuelta) | E6: COP | F6: 2740300 | G6: 3 | H6: =IFERROR(F6*G6,0) -> 8220900 | I6: {=IFERROR(INDEX('Tasas de Cambio'!$E$11:$E$15,MATCH(E6,'Tasas de Cambio'!$B$11:$B$15,0)),0)} -> 1 | J6: =IFERROR(H6*I6,0) -> 8220900 | K6: =IFERROR(J6/'Tasas de Cambio'!$C$5,0) -> 2740300 | L6: Iberia IB0156, BOG 12:35 (hora Colombia) → MAD 05:15 (+1, local); conexión → BCN 08:25 local. Incluye regreso. | M6: 11 sep 2026
A7: Traslados | B7: Alemania | C7: 31 May 2027 | D7: Traslado hotel → aeropuerto, Berlín | E7: EUR | F7: 65 | G7: 1 | H7: =IFERROR(F7*G7,0) -> 65 | I7: {=IFERROR(INDEX('Tasas de Cambio'!$E$11:$E$15,MATCH(E7,'Tasas de Cambio'!$B$11:$B$15,0)),0)} -> 3788.4 | J7: =IFERROR(H7*I7,0) -> 246246 | K7: =IFERROR(J7/'Tasas de Cambio'!$C$5,0) -> 82082 | L7: Estimado: Uber/taxi al aeropuerto BER desde Alexanderplatz/Mitte, ~35-45 min, €60-75. | M7: 11 sep 2026
A9: Otros y Extras | B9: — | C9: Contingencia | D9: Imprevistos / gastos varios (contingencia) | E9: EUR | F9: 200 | G9: 3 | H9: 600 | I9: {=IFERROR(INDEX('Tasas de Cambio'!$E$11:$E$15,MATCH(E9,'Tasas de Cambio'!$B$11:$B$15,0)),0)} -> 3788.4 | J9: 2273040 | K9: =IFERROR(J9/'Tasas de Cambio'!$C$5,0) -> 757680 | L9: Aplica solo al plan corto — revisar si alcanza para 30 días | O9: Otros y Extras
A10: Otros y Extras | B10: — | C10: Durante el viaje | D10: SIM card de viaje (datos internacionales) | E10: USD | F10: 54 | G10: 1 | H10: 54 | I10: {=IFERROR(INDEX('Tasas de Cambio'!$E$11:$E$15,MATCH(E10,'Tasas de Cambio'!$B$11:$B$15,0)),0)} -> 3263.4 | J10: 176223.6 | K10: =IFERROR(J10/'Tasas de Cambio'!$C$5,0) -> 58741.2 | L10: SIM compartida entre las 3 personas para 17 días del viaje. https://esim.holafly.com/es/esim-europa/?selectedDays=17&startDate=2027-04-30&endDate=2027-05-16 | M10: 27 ago 2026
A15: Vuelos y Trenes | B15: Francia / Rep. Checa | C15: 23 May 2027 | D15: Vuelo interno París → Praga | E15: EUR | F15: 85 | G15: 3 | H15: =IFERROR(F15*G15,0) -> 255 | I15: {=IFERROR(INDEX('Tasas de Cambio'!$E$11:$E$15,MATCH(E15,'Tasas de Cambio'!$B$11:$B$15,0)),0)} -> 3788.4 | J15: =IFERROR(H15*I15,0) -> 966042 | K15: =IFERROR(J15/'Tasas de Cambio'!$C$5,0) -> 322014 | L15: Vuelo low-cost, París → Praga, directo, ~1h50m. Maleta de mano incluida; facturada aparte. https://www.skyscanner.com/routes/pari/prg/paris-to-prague.html | M15: 11 sep 2026
A17: Traslados | B17: Francia | C17: 20 May 2027 | D17: Traslado aeropuerto → hotel, París | E17: EUR | F17: 50 | G17: 1 | H17: =IFERROR(F17*G17,0) -> 50 | I17: {=IFERROR(INDEX('Tasas de Cambio'!$E$11:$E$15,MATCH(E17,'Tasas de Cambio'!$B$11:$B$15,0)),0)} -> 3788.4 | J17: =IFERROR(H17*I17,0) -> 189420 | K17: =IFERROR(J17/'Tasas de Cambio'!$C$5,0) -> 63140 | L17: Estimado: Uber/taxi desde el aeropuerto (CDG/Orly) al hotel, ~45-60 min, €45-60. | M17: 11 sep 2026
A18: Alojamiento | B18: París, Francia | C18: 20 – 23 May (3 noches) | D18: Hotel París — costo por noche | E18: EUR | F18: 150 | G18: 3 | H18: 450 | I18: {=IFERROR(INDEX('Tasas de Cambio'!$E$11:$E$15,MATCH(E18,'Tasas de Cambio'!$B$11:$B$15,0)),0)} -> 3788.4 | J18: 1704780 | K18: =IFERROR(J18/'Tasas de Cambio'!$C$5,0) -> 568260 | L18: Recomendado: Hôtel Augustin - Astotel, boutique 4*, a 1 min de Boulevard Haussmann y 500m de Gare Saint-Lazare (zona Opéra/Grands Boulevards, muy céntrica y bien conectada). Cadena Astotel, buena calificación en Booking (~8.5+). https://www.booking.com/budget/city/fr/paris.en-gb.html
A19: Comidas | B19: París | C19: 20 May 2027 | D19: Comida del día (desayuno, almuerzo y cena) | E19: EUR | F19: 62 | G19: 3 | H19: =IFERROR(F19*G19,0) -> 186 | I19: {=IFERROR(INDEX('Tasas de Cambio'!$E$11:$E$15,MATCH(E19,'Tasas de Cambio'!$B$11:$B$15,0)),0)} -> 3788.4 | J19: =IFERROR(H19*I19,0) -> 704642.4 | K19: =IFERROR(J19/'Tasas de Cambio'!$C$5,0) -> 234880.8 | M19: 28 ago 2026
A20: Tours y Excursiones | B20: Francia | C20: 21 May 2027 | D20: Entrada Disneyland Paris — 1 día / 2 parques | E20: EUR | F20: 110 | G20: 3 | H20: 330 | I20: {=IFERROR(INDEX('Tasas de Cambio'!$E$11:$E$15,MATCH(E20,'Tasas de Cambio'!$B$11:$B$15,0)),0)} -> 3788.4 | J20: 1250172 | K20: =IFERROR(J20/'Tasas de Cambio'!$C$5,0) -> 416724 | L20: Recomendado: Ticket 1 día / 2 parques, tarifa media temporada. https://www.attractiontickets.com/en/paris-attraction-tickets/disneyland-paris-tickets/1-day-2-parks-disneyland-paris-hopper-ticket
A21: Comidas | B21: París | C21: 21 May 2027 | D21: Comida del día (desayuno, almuerzo y cena) | E21: EUR | F21: 62 | G21: 3 | H21: =IFERROR(F21*G21,0) -> 186 | I21: {=IFERROR(INDEX('Tasas de Cambio'!$E$11:$E$15,MATCH(E21,'Tasas de Cambio'!$B$11:$B$15,0)),0)} -> 3788.4 | J21: =IFERROR(H21*I21,0) -> 704642.4 | K21: =IFERROR(J21/'Tasas de Cambio'!$C$5,0) -> 234880.8 | M21: 28 ago 2026
A22: Tours y Excursiones | B22: Francia | C22: 22 May 2027 | D22: Crucero por el Sena | E22: EUR | F22: 19 | G22: 3 | H22: 57 | I22: {=IFERROR(INDEX('Tasas de Cambio'!$E$11:$E$15,MATCH(E22,'Tasas de Cambio'!$B$11:$B$15,0)),0)} -> 3788.4 | J22: 215938.8 | K22: =IFERROR(J22/'Tasas de Cambio'!$C$5,0) -> 71979.6 | L22: Recomendado: Crucero panorámico Bateaux Mouches, 1h10m. https://ryo.co/en/articles/france/paris/how-to-take-seine-cruise-paris/
A23: Comidas | B23: París | C23: 22 May 2027 | D23: Comida del día (desayuno, almuerzo y cena) | E23: EUR | F23: 62 | G23: 3 | H23: =IFERROR(F23*G23,0) -> 186 | I23: {=IFERROR(INDEX('Tasas de Cambio'!$E$11:$E$15,MATCH(E23,'Tasas de Cambio'!$B$11:$B$15,0)),0)} -> 3788.4 | J23: =IFERROR(H23*I23,0) -> 704642.4 | K23: =IFERROR(J23/'Tasas de Cambio'!$C$5,0) -> 234880.8 | M23: 28 ago 2026
A25: Traslados | B25: Francia | C25: 23 May 2027 | D25: Traslado hotel → aeropuerto, París | E25: EUR | F25: 50 | G25: 1 | H25: 50 | I25: {=IFERROR(INDEX('Tasas de Cambio'!$E$11:$E$15,MATCH(E25,'Tasas de Cambio'!$B$11:$B$15,0)),0)} -> 3788.4 | J25: 189420 | K25: =IFERROR(J25/'Tasas de Cambio'!$C$5,0) -> 63140 | L25: Estimado: Uber/taxi al aeropuerto (CDG/Orly), ~45-60 min, €45-60.
A26: Traslados | B26: España | C26: 7 May 2027 | D26: Traslado aeropuerto → hotel, Barcelona | E26: EUR | F26: 40 | G26: 1 | H26: 40 | I26: {=IFERROR(INDEX('Tasas de Cambio'!$E$11:$E$15,MATCH(E26,'Tasas de Cambio'!$B$11:$B$15,0)),0)} -> 3788.4 | J26: 151536 | K26: =IFERROR(J26/'Tasas de Cambio'!$C$5,0) -> 50512
A27: Alojamiento | B27: Barcelona, España | C27: 7 – 9 May (2 noches, pre-crucero) | D27: Hotel Barcelona — costo total (2 noches) | E27: COP | F27: 1900000 | G27: 1 | H27: =IFERROR(F27*G27,0) -> 1900000 | I27: {=IFERROR(INDEX('Tasas de Cambio'!$E$11:$E$15,MATCH(E27,'Tasas de Cambio'!$B$11:$B$15,0)),0)} -> 1 | J27: =IFERROR(H27*I27,0) -> 1900000 | K27: =IFERROR(J27/'Tasas de Cambio'!$C$5,0) -> 633333.33 | L27: Sagrada Familia, 2 noches (7-9 may). https://www.booking.com/hotel/es/sagradafamilia.es.html?aid=2311236&label=es-co-booking-desktop-vjGZbEFOhRc3a9njxeT3IwS652829002024%3Apl%3Ata%3Ap1%3Ap2%3Aac%3Aap%3Aneg%3Afi%3Atikwd-65526620%3Alp9246960%3Ali%3Adec%3Adm&sid=f6a1a9bb810c453f7b5f1225205f1f26&all_sr_blocks=9118812_91908190_0_2_0&checkin=2027-05-07&checkout=2027-05-09&dest_id=-372490&dest_type=city&dist=0&group_adults=3&group_children=0&hapos=1&highlighted_blocks=9118812_91908190_0_2_0&hpos=1&matching_block_id=9118812_91908190_0_2_0&no_rooms=1&req_adults=3&req_children=0&room1=A%2CA%2CA&sb_price_type=total&sr_order=popularity&sr_pri_blocks=9118812_91908190_0_2_0__37600&srepoch=1787875557&srpvid=a2d600b07c230149&type=total&ucfs=1 | M27: 27 ago 2026
A28: Comidas | B28: Barcelona | C28: 7 May 2027 | D28: cena | E28: EUR | F28: 15 | G28: 3 | H28: 45 | I28: {=IFERROR(INDEX('Tasas de Cambio'!$E$11:$E$15,MATCH(E28,'Tasas de Cambio'!$B$11:$B$15,0)),0)} -> 3788.4 | J28: 170478 | K28: =IFERROR(J28/'Tasas de Cambio'!$C$5,0) -> 56826
A29: Traslados | B29: Barcelona | C29: 8 May 2027 | D29: Bus, 4 trayectos | E29: EUR | F29: 12 | G29: 3 | H29: 36 | I29: {=IFERROR(INDEX('Tasas de Cambio'!$E$11:$E$15,MATCH(E29,'Tasas de Cambio'!$B$11:$B$15,0)),0)} -> 3788.4 | J29: 136382.4 | K29: =IFERROR(J29/'Tasas de Cambio'!$C$5,0) -> 45460.8
A30: Tours y Excursiones | B30: Barcelona | C30: 8 May 2027 | D30: Tour Barcelona Modernista | E30: USD | F30: 10 | G30: 3 | H30: =IFERROR(F30*G30,0) -> 30 | I30: {=IFERROR(INDEX('Tasas de Cambio'!$E$11:$E$15,MATCH(E30,'Tasas de Cambio'!$B$11:$B$15,0)),0)} -> 3263.4 | J30: =IFERROR(H30*I30,0) -> 97902 | K30: =IFERROR(J30/'Tasas de Cambio'!$C$5,0) -> 32634 | L30: Tour guiado por el Modernismo catalán en Barcelona. https://www.civitatis.com/es/barcelona/tour-barcelona-modernista/ | M30: 27 ago 2026
A31: Comidas | B31: Barcelona | C31: 8 May 2027 | D31: 3 comidas | E31: EUR | F31: 30 | G31: 3 | H31: 90 | I31: {=IFERROR(INDEX('Tasas de Cambio'!$E$11:$E$15,MATCH(E31,'Tasas de Cambio'!$B$11:$B$15,0)),0)} -> 3788.4 | J31: 340956 | K31: =IFERROR(J31/'Tasas de Cambio'!$C$5,0) -> 113652
A32: Traslados | B32: España | C32: 9 May 2027 | D32: Traslado hotel → puerto (embarque crucero), Barcelona | E32: EUR | F32: 30 | G32: 1 | H32: 30 | I32: {=IFERROR(INDEX('Tasas de Cambio'!$E$11:$E$15,MATCH(E32,'Tasas de Cambio'!$B$11:$B$15,0)),0)} -> 3788.4 | J32: 113652 | K32: =IFERROR(J32/'Tasas de Cambio'!$C$5,0) -> 37884
A33: Crucero | B33: Mediterráneo | C33: 9 – 16 May (7 noches) | D33: Crucero Barcelona → Ravena — tarifa por persona (cabina) | E33: USD | F33: 670 | G33: 3 | H33: =IFERROR(F33*G33,0) -> 2010 | I33: {=IFERROR(INDEX('Tasas de Cambio'!$E$11:$E$15,MATCH(E33,'Tasas de Cambio'!$B$11:$B$15,0)),0)} -> 3263.4 | J33: =IFERROR(H33*I33,0) -> 6559434 | K33: =IFERROR(J33/'Tasas de Cambio'!$C$5,0) -> 2186478 | L33: Crucero Barcelona-Ravena, 7 noches, incluye propinas. https://www.royalcaribbean.com/lac/es/itinerary/7-night-italy-croatia-cruise-from-barcelona-on-brilliance-BR07M885?sailDate=2027-05-08&packageCode=BR07M885&groupId=BR07BCN-1768961711&country=COL&search=startDate:2027-05-01~2027-05-31 | M33: 27 ago 2026
A34: Tours y Excursiones | B34: Barcelona | C34: 9 May 2027 | D34: N/A (día de embarque) | E34: EUR | F34: 0 | G34: 3 | H34: 0 | I34: {=IFERROR(INDEX('Tasas de Cambio'!$E$11:$E$15,MATCH(E34,'Tasas de Cambio'!$B$11:$B$15,0)),0)} -> 3788.4 | J34: 0 | K34: =IFERROR(J34/'Tasas de Cambio'!$C$5,0) -> 0
A35: Comidas | B35: Barcelona | C35: 9 May 2027 | D35: desayuno | E35: EUR | F35: 10 | G35: 3 | H35: 30 | I35: {=IFERROR(INDEX('Tasas de Cambio'!$E$11:$E$15,MATCH(E35,'Tasas de Cambio'!$B$11:$B$15,0)),0)} -> 3788.4 | J35: 113652 | K35: =IFERROR(J35/'Tasas de Cambio'!$C$5,0) -> 37884
A36: Traslados | B36: Venecia | C36: 16 May 2027 | D36: Vaporetti ACTV | E36: EUR | F36: 25 | G36: 3 | H36: =IFERROR(F36*G36,0) -> 75 | I36: {=IFERROR(INDEX('Tasas de Cambio'!$E$11:$E$15,MATCH(E36,'Tasas de Cambio'!$B$11:$B$15,0)),0)} -> 3788.4 | J36: =IFERROR(H36*I36,0) -> 284130 | K36: =IFERROR(J36/'Tasas de Cambio'!$C$5,0) -> 94710 | L36: Boletos de vaporetto (transporte acuático) por Venecia. https://book.tickets-venice.com/es/book/8748/select/?_gl=1%2A1073ils%2A_gcl_aw%2AR0NMLjE3ODc4NzgwODMuRUFJYUlRb2JDaE1JaFpPNjdZekNsZ01Wd1lSYUJSM2Y1U1JPRUFBWUF5QUFFZ0tjeFBEX0J3RQ..%2A_gcl_au%2ANzIxMTA1MTQ5LjE3ODc4NzgwODMuLS4tLjE3ODc4NzgwODMuMTE2MDU2ODc1MS4xNzg3ODc4MDg0LjE3ODc4NzgwODM.%2A_ga%2ANDcyOTU3MzYyLjE3ODc4NzgwODM.%2A_ga_Y45PC9R73C%2AczE3ODc4NzgwODMkbzEkZzAkdDE3ODc4NzgwODQkajU5JGwwJGgw&cookieBanner=false&date=2027-05-15&tourId=15560&variantId=15560 | M36: 27 ago 2026
A37: Tours y Excursiones | B37: La Spezia (Florencia/Pisa) | C37: 11 May 2027 | D37: Panoramic Pisa | E37: USD | F37: 70 | G37: 3 | H37: =IFERROR(F37*G37,0) -> 210 | I37: {=IFERROR(INDEX('Tasas de Cambio'!$E$11:$E$15,MATCH(E37,'Tasas de Cambio'!$B$11:$B$15,0)),0)} -> 3263.4 | J37: =IFERROR(H37*I37,0) -> 685314 | K37: =IFERROR(J37/'Tasas de Cambio'!$C$5,0) -> 228438 | L37: Excursión panorámica por Pisa desde el crucero. https://www.royalcaribbean.com/account/cruise-planner/category/shorex/product/Y8RO?bookingId=3113096&shipCode=BR&sailDate=20270508 | M37: 27 ago 2026
A38: Comidas | B38: La Spezia (Florencia/Pisa) | C38: 11 May 2027 | D38: Almuerzo en tierra | E38: EUR | F38: 25 | G38: 3 | H38: =IFERROR(F38*G38,0) -> 75 | I38: {=IFERROR(INDEX('Tasas de Cambio'!$E$11:$E$15,MATCH(E38,'Tasas de Cambio'!$B$11:$B$15,0)),0)} -> 3788.4 | J38: =IFERROR(H38*I38,0) -> 284130 | K38: =IFERROR(J38/'Tasas de Cambio'!$C$5,0) -> 94710 | L38: Desayuno y cena incluidos en el crucero, almuerzo en Pisa/Florencia | M38: 28 ago 2026
A39: Tours y Excursiones | B39: Civitavecchia (Roma) | C39: 12 May 2027 | D39: Visit to Rome | E39: USD | F39: 142 | G39: 3 | H39: =IFERROR(F39*G39,0) -> 426 | I39: {=IFERROR(INDEX('Tasas de Cambio'!$E$11:$E$15,MATCH(E39,'Tasas de Cambio'!$B$11:$B$15,0)),0)} -> 3263.4 | J39: =IFERROR(H39*I39,0) -> 1390208.4 | K39: =IFERROR(J39/'Tasas de Cambio'!$C$5,0) -> 463402.8 | L39: Excursión a Roma desde el crucero. https://www.royalcaribbean.com/account/cruise-planner/category/shorex/product/CV1F?bookingId=3113096&shipCode=BR&sailDate=20270508 | M39: 29 ago 2026
A40: Comidas | B40: Civitavecchia (Roma) | C40: 12 May 2027 | D40: Almuerzo en tierra | E40: EUR | F40: 25 | G40: 3 | H40: =IFERROR(F40*G40,0) -> 75 | I40: {=IFERROR(INDEX('Tasas de Cambio'!$E$11:$E$15,MATCH(E40,'Tasas de Cambio'!$B$11:$B$15,0)),0)} -> 3788.4 | J40: =IFERROR(H40*I40,0) -> 284130 | K40: =IFERROR(J40/'Tasas de Cambio'!$C$5,0) -> 94710 | L40: Desayuno y cena incluidos en el crucero, almuerzo en Roma | M40: 28 ago 2026
A41: Tours y Excursiones | B41: Salerno (Costa Amalfitana) | C41: 13 May 2027 | D41: Tour a pie gratis | E41: EUR | F41: 0 | G41: 3 | H41: 0 | I41: {=IFERROR(INDEX('Tasas de Cambio'!$E$11:$E$15,MATCH(E41,'Tasas de Cambio'!$B$11:$B$15,0)),0)} -> 3788.4 | J41: 0 | K41: =IFERROR(J41/'Tasas de Cambio'!$C$5,0) -> 0
A42: Comidas | B42: Salerno (Costa Amalfitana) | C42: 13 May 2027 | D42: Incluida en el crucero (come a bordo) | E42: EUR | F42: 0 | G42: 3 | H42: =IFERROR(F42*G42,0) -> 0 | I42: {=IFERROR(INDEX('Tasas de Cambio'!$E$11:$E$15,MATCH(E42,'Tasas de Cambio'!$B$11:$B$15,0)),0)} -> 3788.4 | J42: =IFERROR(H42*I42,0) -> 0 | K42: =IFERROR(J42/'Tasas de Cambio'!$C$5,0) -> 0 | L42: Comida incluida en el paquete del crucero, sin costo adicional | M42: 27 ago 2026
A43: Vuelos y Trenes | B43: Italia | C43: 16 May 2027 | D43: Tren Ravenna - Venecia St Lucia | E43: EUR | F43: 25 | G43: 3 | H43: =IFERROR(F43*G43,0) -> 75 | I43: {=IFERROR(INDEX('Tasas de Cambio'!$E$11:$E$15,MATCH(E43,'Tasas de Cambio'!$B$11:$B$15,0)),0)} -> 3788.4 | J43: =IFERROR(H43*I43,0) -> 284130 | K43: =IFERROR(J43/'Tasas de Cambio'!$C$5,0) -> 94710 | L43: Tren regional desde Ravenna hasta Venecia Santa Lucia. https://www.trenitalia.com/en.html | M43: 27 ago 2026
A44: Traslados | B44: Zadar, Croacia | C44: 15 May 2027 | D44: Transporte - Tour a pie gratis | E44: EUR | F44: 10 | G44: 3 | H44: =IFERROR(F44*G44,0) -> 30 | I44: {=IFERROR(INDEX('Tasas de Cambio'!$E$11:$E$15,MATCH(E44,'Tasas de Cambio'!$B$11:$B$15,0)),0)} -> 3788.4 | J44: =IFERROR(H44*I44,0) -> 113652 | K44: =IFERROR(J44/'Tasas de Cambio'!$C$5,0) -> 37884 | M44: 27 ago 2026
A45: Comidas | B45: Zadar, Croacia | C45: 15 May 2027 | D45: Incluida en el crucero (come a bordo) | E45: EUR | F45: 0 | G45: 3 | H45: =IFERROR(F45*G45,0) -> 0 | I45: {=IFERROR(INDEX('Tasas de Cambio'!$E$11:$E$15,MATCH(E45,'Tasas de Cambio'!$B$11:$B$15,0)),0)} -> 3788.4 | J45: =IFERROR(H45*I45,0) -> 0 | K45: =IFERROR(J45/'Tasas de Cambio'!$C$5,0) -> 0 | L45: Comida incluida en el paquete del crucero, sin costo adicional | M45: 27 ago 2026
A46: Traslados | B46: Italia | C46: 16 May 2027 | D46: Traslado puerto → Estación Ravenna | E46: EUR | F46: 12 | G46: 3 | H46: =IFERROR(F46*G46,0) -> 36 | I46: {=IFERROR(INDEX('Tasas de Cambio'!$E$11:$E$15,MATCH(E46,'Tasas de Cambio'!$B$11:$B$15,0)),0)} -> 3788.4 | J46: =IFERROR(H46*I46,0) -> 136382.4 | K46: =IFERROR(J46/'Tasas de Cambio'!$C$5,0) -> 45460.8 | M46: 27 ago 2026
A47: Alojamiento | B47: Venecia, Italia | C47: 16 – 17 May (1 noche, post-crucero) | D47: Hotel Venecia — costo total (1 noche) | E47: EUR | F47: 400 | G47: 1 | H47: =IFERROR(F47*G47,0) -> 400 | I47: {=IFERROR(INDEX('Tasas de Cambio'!$E$11:$E$15,MATCH(E47,'Tasas de Cambio'!$B$11:$B$15,0)),0)} -> 3788.4 | J47: =IFERROR(H47*I47,0) -> 1515360 | K47: =IFERROR(J47/'Tasas de Cambio'!$C$5,0) -> 505120 | M47: 28 ago 2026
A48: Comidas | B48: Rávena (Venecia) | C48: 16 May 2027 | D48: Almuerzo y cena | E48: EUR | F48: 30 | G48: 3 | H48: 90 | I48: {=IFERROR(INDEX('Tasas de Cambio'!$E$11:$E$15,MATCH(E48,'Tasas de Cambio'!$B$11:$B$15,0)),0)} -> 3788.4 | J48: 340956 | K48: =IFERROR(J48/'Tasas de Cambio'!$C$5,0) -> 113652
A49: Vuelos y Trenes | B49: Italia | C49: 17 May 2027 | D49: Tren Venecia → Milán, directo | E49: EUR | F49: 35 | G49: 3 | H49: =IFERROR(F49*G49,0) -> 105 | I49: {=IFERROR(INDEX('Tasas de Cambio'!$E$11:$E$15,MATCH(E49,'Tasas de Cambio'!$B$11:$B$15,0)),0)} -> 3788.4 | J49: =IFERROR(H49*I49,0) -> 397782 | K49: =IFERROR(J49/'Tasas de Cambio'!$C$5,0) -> 132594 | L49: Frecciarossa, Venezia Santa Lucia → Milano Centrale, directo, ~2h27m. https://www.thetrainline.com/en/train-times/venezia-santa-lucia-to-milan-central-station | M49: 11 sep 2026
A50: Traslados | B50: Italia | C50: 17 May 2027 | D50: Traslado hotel → estación (tren a Milán), Venecia | E50: EUR | F50: 20 | G50: 1 | H50: 20 | I50: {=IFERROR(INDEX('Tasas de Cambio'!$E$11:$E$15,MATCH(E50,'Tasas de Cambio'!$B$11:$B$15,0)),0)} -> 3788.4 | J50: 75768 | K50: =IFERROR(J50/'Tasas de Cambio'!$C$5,0) -> 25256 | L50: Estimado: vaporetto/water taxi compartido a la estación Santa Lucia (en Venecia no circulan autos), ~€20 total para el grupo con equipaje.
A51: Traslados | B51: Italia | C51: 17 May 2027 | D51: Traslado estación → hotel, Milán | E51: EUR | F51: 12 | G51: 1 | H51: =IFERROR(F51*G51,0) -> 12 | I51: {=IFERROR(INDEX('Tasas de Cambio'!$E$11:$E$15,MATCH(E51,'Tasas de Cambio'!$B$11:$B$15,0)),0)} -> 3788.4 | J51: =IFERROR(H51*I51,0) -> 45460.8 | K51: =IFERROR(J51/'Tasas de Cambio'!$C$5,0) -> 15153.6 | L51: Estimado: taxi corto desde Milano Centrale al hotel, ~10 min, €10-15. | M51: 11 sep 2026
A52: Alojamiento | B52: Milán, Italia | C52: 17 – 20 May (3 noches) | D52: Hotel Milán — costo por noche | E52: EUR | F52: 115 | G52: 3 | H52: =IFERROR(F52*G52,0) -> 345 | I52: {=IFERROR(INDEX('Tasas de Cambio'!$E$11:$E$15,MATCH(E52,'Tasas de Cambio'!$B$11:$B$15,0)),0)} -> 3788.4 | J52: =IFERROR(H52*I52,0) -> 1306998 | K52: =IFERROR(J52/'Tasas de Cambio'!$C$5,0) -> 435666 | L52: Recomendado: ibis Milano Centro, junto a Milano Centrale, 3 noches. https://www.booking.com/landmark/it/centrale-fs.html | M52: 11 sep 2026
A53: Tours y Excursiones | B53: Venecia | C53: 16 May 2027 | D53: Free tour Venecia | E53: EUR | F53: 10 | G53: 3 | H53: =IFERROR(F53*G53,0) -> 30 | I53: {=IFERROR(INDEX('Tasas de Cambio'!$E$11:$E$15,MATCH(E53,'Tasas de Cambio'!$B$11:$B$15,0)),0)} -> 3788.4 | J53: =IFERROR(H53*I53,0) -> 113652 | K53: =IFERROR(J53/'Tasas de Cambio'!$C$5,0) -> 37884 | L53: Free tour guiado por el centro histórico de Venecia. https://www.civitatis.com/es/venecia/free-tour-venecia/?_gl=1*1ijxuzi*_up*MQ..*_ga*ODU4MDQyNjAyLjE3ODc4Nzc2ODY.*_ga_QJQ54CTKPM*czE3ODc4Nzc2ODYkbzEkZzEkdDE3ODc4Nzc2OTEkajU1JGwwJGgxNTA2MDA0ODU0 | M53: 27 ago 2026
A54: Comidas | B54: Venecia | C54: 17 May 2027 | D54: Comida del día (desayuno, almuerzo y cena) | E54: EUR | F54: 40 | G54: 3 | H54: =IFERROR(F54*G54,0) -> 120 | I54: {=IFERROR(INDEX('Tasas de Cambio'!$E$11:$E$15,MATCH(E54,'Tasas de Cambio'!$B$11:$B$15,0)),0)} -> 3788.4 | J54: =IFERROR(H54*I54,0) -> 454608 | K54: =IFERROR(J54/'Tasas de Cambio'!$C$5,0) -> 151536 | M54: 28 ago 2026
A55: Tours y Excursiones | B55: Milán | C55: 18 May 2027 | D55: Duomo di Milano y terrazas (entrada) | E55: EUR | F55: 16 | G55: 3 | H55: =IFERROR(F55*G55,0) -> 48 | I55: {=IFERROR(INDEX('Tasas de Cambio'!$E$11:$E$15,MATCH(E55,'Tasas de Cambio'!$B$11:$B$15,0)),0)} -> 3788.4 | J55: =IFERROR(H55*I55,0) -> 181843.2 | K55: =IFERROR(J55/'Tasas de Cambio'!$C$5,0) -> 60614.4 | L55: Entrada terrazas con ascensor, precio oficial. https://ticket.duomomilano.it/en/categoria/terrazze/ | M55: 11 sep 2026
A56: Comidas | B56: Milán | C56: 18 May 2027 | D56: Comida del día (desayuno, almuerzo y cena) | E56: EUR | F56: 57 | G56: 3 | H56: =IFERROR(F56*G56,0) -> 171 | I56: {=IFERROR(INDEX('Tasas de Cambio'!$E$11:$E$15,MATCH(E56,'Tasas de Cambio'!$B$11:$B$15,0)),0)} -> 3788.4 | J56: =IFERROR(H56*I56,0) -> 647816.4 | K56: =IFERROR(J56/'Tasas de Cambio'!$C$5,0) -> 215938.8 | M56: 28 ago 2026
A57: Tours y Excursiones | B57: Milán | C57: 19 May 2027 | D57: Alpine Wonders: almuerzo en Diavolezza y tren Bernina | E57: USD | F57: 250 | G57: 3 | H57: =IFERROR(F57*G57,0) -> 750 | I57: {=IFERROR(INDEX('Tasas de Cambio'!$E$11:$E$15,MATCH(E57,'Tasas de Cambio'!$B$11:$B$15,0)),0)} -> 3263.4 | J57: =IFERROR(H57*I57,0) -> 2447550 | K57: =IFERROR(J57/'Tasas de Cambio'!$C$5,0) -> 815850 | L57: Excursión de día completo desde Milán, tren panorámico Bernina. https://www.tripadvisor.com/AttractionProductReview-g187849-d15090556-From_Milan_Alpine_Wonders_Lunch_at_Diavolezza_and_Bernina_Train-Milan_Lombardy.html | M57: 11 sep 2026
A58: Vuelos y Trenes | B58: Italia / Francia | C58: 20 May 2027 | D58: Vuelo interno Milán → París | E58: EUR | F58: 90 | G58: 3 | H58: =IFERROR(F58*G58,0) -> 270 | I58: {=IFERROR(INDEX('Tasas de Cambio'!$E$11:$E$15,MATCH(E58,'Tasas de Cambio'!$B$11:$B$15,0)),0)} -> 3788.4 | J58: =IFERROR(H58*I58,0) -> 1022868 | K58: =IFERROR(J58/'Tasas de Cambio'!$C$5,0) -> 340956 | L58: Vuelo low-cost (easyJet/Vueling), Milán → París, directo, ~1h35m. Maleta de mano incluida; facturada aparte. https://www.skyscanner.net/routes/mila/pari/milan-to-paris.html | M58: 11 sep 2026
A59: Traslados | B59: Italia | C59: 20 May 2027 | D59: Traslado hotel → aeropuerto, Milán | E59: EUR | F59: 30 | G59: 1 | H59: =IFERROR(F59*G59,0) -> 30 | I59: {=IFERROR(INDEX('Tasas de Cambio'!$E$11:$E$15,MATCH(E59,'Tasas de Cambio'!$B$11:$B$15,0)),0)} -> 3788.4 | J59: =IFERROR(H59*I59,0) -> 113652 | K59: =IFERROR(J59/'Tasas de Cambio'!$C$5,0) -> 37884 | L59: Estimado: taxi tarifa fija al aeropuerto (Linate/Malpensa), ~30-45 min, €30-45. | M59: 11 sep 2026
A60: Traslados | B60: Rep. Checa | C60: 23 May 2027 | D60: Traslado aeropuerto → hotel, Praga | E60: EUR | F60: 28 | G60: 1 | H60: 28 | I60: {=IFERROR(INDEX('Tasas de Cambio'!$E$11:$E$15,MATCH(E60,'Tasas de Cambio'!$B$11:$B$15,0)),0)} -> 3788.4 | J60: 106075.2 | K60: =IFERROR(J60/'Tasas de Cambio'!$C$5,0) -> 35358.4 | L60: Estimado: Uber/taxi desde el aeropuerto de Praga al hotel (Nové Město), ~20-25 min, €25-30.
A61: Alojamiento | B61: Praga, Rep. Checa | C61: 23 – 26 May (3 noches) | D61: Hotel Praga — costo por noche | E61: CZK | F61: 2000 | G61: 3 | H61: 6000 | I61: {=IFERROR(INDEX('Tasas de Cambio'!$E$11:$E$15,MATCH(E61,'Tasas de Cambio'!$B$11:$B$15,0)),0)} -> 156.97 | J61: 941820 | K61: =IFERROR(J61/'Tasas de Cambio'!$C$5,0) -> 313940 | L61: Recomendado: Mosaic House Design Hotel, Odborů 4, Praga 2 (Nové Město / Ciudad Nueva), a 10 min caminando de la Plaza de la Ciudad Vieja. Calificación ~8.5/10 en Booking, buena relación precio-ubicación. https://www.helloprague.net/budget-hotels-prague/
A62: Tours y Excursiones | B62: Rep. Checa | C62: 24 May 2027 | D62: Castillo de Praga + Puente de Carlos con guía | E62: CZK | F62: 1150 | G62: 3 | H62: 3450 | I62: {=IFERROR(INDEX('Tasas de Cambio'!$E$11:$E$15,MATCH(E62,'Tasas de Cambio'!$B$11:$B$15,0)),0)} -> 156.97 | J62: 541546.5 | K62: =IFERROR(J62/'Tasas de Cambio'!$C$5,0) -> 180515.5 | L62: Recomendado: Tour guiado interiores (Salón Dorado, Catedral San Vito, Basílica San Jorge, Palacio Real Viejo), incluye entradas. https://www.tours-prague.eu/tour-castleinter.phtml
A63: Comidas | B63: Praga | C63: 24 May 2027 | D63: Comida del día (desayuno, almuerzo y cena) | E63: CZK | F63: 700 | G63: 3 | H63: =IFERROR(F63*G63,0) -> 2100 | I63: {=IFERROR(INDEX('Tasas de Cambio'!$E$11:$E$15,MATCH(E63,'Tasas de Cambio'!$B$11:$B$15,0)),0)} -> 156.97 | J63: =IFERROR(H63*I63,0) -> 329637 | K63: =IFERROR(J63/'Tasas de Cambio'!$C$5,0) -> 109879 | M63: 28 ago 2026
A64: Tours y Excursiones | B64: Rep. Checa | C64: 25 May 2027 | D64: Crucero por el río Moldava | E64: CZK | F64: 500 | G64: 3 | H64: 1500 | I64: {=IFERROR(INDEX('Tasas de Cambio'!$E$11:$E$15,MATCH(E64,'Tasas de Cambio'!$B$11:$B$15,0)),0)} -> 156.97 | J64: 235455 | K64: =IFERROR(J64/'Tasas de Cambio'!$C$5,0) -> 78485 | L64: Recomendado: Crucero panorámico 1h por el Moldava. https://www.viator.com/tours/Prague/Panoramic-Vltava-River-Cruise/d462-10919P19
A65: Vuelos y Trenes | B65: Alemania | C65: 28 May 2027 | D65: Tren de alta velocidad Múnich → Berlín | E65: EUR | F65: 55 | G65: 3 | H65: =IFERROR(F65*G65,0) -> 165 | I65: {=IFERROR(INDEX('Tasas de Cambio'!$E$11:$E$15,MATCH(E65,'Tasas de Cambio'!$B$11:$B$15,0)),0)} -> 3788.4 | J65: =IFERROR(H65*I65,0) -> 625086 | K65: =IFERROR(J65/'Tasas de Cambio'!$C$5,0) -> 208362 | L65: Tren ICE (Intercity Express), Múnich Hbf → Berlín Hbf, directo, ~3h53m. Equipaje incluido sin cargo extra. https://rail.cc/train/berlin-to-munich | M65: 11 sep 2026
A66: Traslados | B66: Alemania | C66: 28 May 2027 | D66: Traslado estación → hotel, Berlín | E66: EUR | F66: 18 | G66: 1 | H66: 18 | I66: {=IFERROR(INDEX('Tasas de Cambio'!$E$11:$E$15,MATCH(E66,'Tasas de Cambio'!$B$11:$B$15,0)),0)} -> 3788.4 | J66: 68191.2 | K66: =IFERROR(J66/'Tasas de Cambio'!$C$5,0) -> 22730.4 | L66: Estimado: Uber/taxi desde Berlín Hbf al hotel (Alexanderplatz/Mitte), ~15 min, €15-20.
A67: Alojamiento | B67: Berlín, Alemania | C67: 28 – 31 May (3 noches) | D67: Hotel Berlín — costo por noche | E67: EUR | F67: 95 | G67: 3 | H67: 285 | I67: {=IFERROR(INDEX('Tasas de Cambio'!$E$11:$E$15,MATCH(E67,'Tasas de Cambio'!$B$11:$B$15,0)),0)} -> 3788.4 | J67: 1079694 | K67: =IFERROR(J67/'Tasas de Cambio'!$C$5,0) -> 359898 | L67: Recomendado: Motel One Berlin-Alexanderplatz, Mitte, muy cerca de Alexanderplatz y bien conectado en metro/tren. Calificación 9.2/10 en Booking - excelente para el precio. https://www.expedia.com/Mitte-Berlin-Hotels-Cheap-Hotels.0-n178779-0-tCheapHotels.Travel-Guide-Filter-Hotels
A68: Tours y Excursiones | B68: Alemania | C68: 29 May 2027 | D68: Tour histórico Berlín (Muro, Reichstag, East Side Gallery) | E68: USD | F68: 30 | G68: 3 | H68: 90 | I68: {=IFERROR(INDEX('Tasas de Cambio'!$E$11:$E$15,MATCH(E68,'Tasas de Cambio'!$B$11:$B$15,0)),0)} -> 3263.4 | J68: 293706 | K68: =IFERROR(J68/'Tasas de Cambio'!$C$5,0) -> 97902 | L68: Recomendado: Tour a pie medio día, Muro/Reichstag/East Side Gallery. https://www.viator.com/Berlin-attractions/Berlin-Wall/d488-a637
A69: Comidas | B69: Berlín | C69: 29 May 2027 | D69: Comida del día (desayuno, almuerzo y cena) | E69: EUR | F69: 40 | G69: 3 | H69: =IFERROR(F69*G69,0) -> 120 | I69: {=IFERROR(INDEX('Tasas de Cambio'!$E$11:$E$15,MATCH(E69,'Tasas de Cambio'!$B$11:$B$15,0)),0)} -> 3788.4 | J69: =IFERROR(H69*I69,0) -> 454608 | K69: =IFERROR(J69/'Tasas de Cambio'!$C$5,0) -> 151536 | M69: 28 ago 2026
A70: Tours y Excursiones | B70: Alemania | C70: 30 May 2027 | D70: Isla de los Museos - tour guiado (Pérgamo, Neues Museum, etc.) | E70: EUR | F70: 30 | G70: 3 | H70: 90 | I70: {=IFERROR(INDEX('Tasas de Cambio'!$E$11:$E$15,MATCH(E70,'Tasas de Cambio'!$B$11:$B$15,0)),0)} -> 3788.4 | J70: 340956 | K70: =IFERROR(J70/'Tasas de Cambio'!$C$5,0) -> 113652 | L70: Recomendado - día completo de 5 museos, mejor con guía | https://www.getyourguide.com/museum-island-l3075/
A71: Vuelos y Trenes | B71: Rep. Checa / Alemania | C71: 26 May 2027 | D71: Tren de alta velocidad Praga → Múnich | E71: EUR | F71: 50 | G71: 3 | H71: =IFERROR(F71*G71,0) -> 150 | I71: {=IFERROR(INDEX('Tasas de Cambio'!$E$11:$E$15,MATCH(E71,'Tasas de Cambio'!$B$11:$B$15,0)),0)} -> 3788.4 | J71: =IFERROR(H71*I71,0) -> 568260 | K71: =IFERROR(J71/'Tasas de Cambio'!$C$5,0) -> 189420 | L71: Tren EuroCity, Praga → Múnich Hbf, directo, ~5h43m. Equipaje incluido sin cargo extra. https://www.seat61.com/trains-and-routes/munich-to-prague-by-train.htm | M71: 11 sep 2026
A72: Traslados | B72: Alemania | C72: 26 May 2027 | D72: Traslado estación → hotel, Múnich | E72: EUR | F72: 10 | G72: 1 | H72: 10 | I72: {=IFERROR(INDEX('Tasas de Cambio'!$E$11:$E$15,MATCH(E72,'Tasas de Cambio'!$B$11:$B$15,0)),0)} -> 3788.4 | J72: 37884 | K72: =IFERROR(J72/'Tasas de Cambio'!$C$5,0) -> 12628 | L72: Estimado: el hotel está muy cerca de la Estación Central, Uber corto o caminando, €8-12.
A73: Alojamiento | B73: Múnich, Alemania | C73: 26 – 28 May (2 noches) | D73: Hotel Múnich — costo por noche | E73: EUR | F73: 130 | G73: 2 | H73: =IFERROR(F73*G73,0) -> 260 | I73: {=IFERROR(INDEX('Tasas de Cambio'!$E$11:$E$15,MATCH(E73,'Tasas de Cambio'!$B$11:$B$15,0)),0)} -> 3788.4 | J73: =IFERROR(H73*I73,0) -> 984984 | K73: =IFERROR(J73/'Tasas de Cambio'!$C$5,0) -> 328328 | L73: Recomendado: Eden Hotel Wolff, cerca de la Estación Central de Múnich (Hauptbahnhof), ~10-15 min a pie o en tranvía a Marienplatz. 4*, buena relación calidad-precio según reseñas. https://www.travelocity.com/Marienplatz-Hotels.0-l508534-0.Travel-Guide-Filter-Hotels | M73: 28 ago 2026
A74: Tours y Excursiones | B74: Alemania | C74: 26 May 2027 | D74: Tour a pie Múnich (Marienplatz, Jardín Inglés) | E74: USD | F74: 23 | G74: 3 | H74: =IFERROR(F74*G74,0) -> 69 | I74: {=IFERROR(INDEX('Tasas de Cambio'!$E$11:$E$15,MATCH(E74,'Tasas de Cambio'!$B$11:$B$15,0)),0)} -> 3263.4 | J74: =IFERROR(H74*I74,0) -> 225174.6 | K74: =IFERROR(J74/'Tasas de Cambio'!$C$5,0) -> 75058.2 | L74: Recomendado: Tour a pie 2h, Marienplatz + Jardín Inglés. https://www.travelersuniverse.com/munich-city-marienplatz-and-english-garden-walking-tour/ | M74: 28 ago 2026
A75: Comidas | B75: Múnich | C75: 27 May 2027 | D75: Comida del día (desayuno, almuerzo y cena) | E75: EUR | F75: 52 | G75: 3 | H75: =IFERROR(F75*G75,0) -> 156 | I75: {=IFERROR(INDEX('Tasas de Cambio'!$E$11:$E$15,MATCH(E75,'Tasas de Cambio'!$B$11:$B$15,0)),0)} -> 3788.4 | J75: =IFERROR(H75*I75,0) -> 590990.4 | K75: =IFERROR(J75/'Tasas de Cambio'!$C$5,0) -> 196996.8 | M75: 28 ago 2026
A76: Tours y Excursiones | B76: Alemania | C76: 27 May 2027 | D76: Excursión Castillo de Neuschwanstein | E76: EUR | F76: 80 | G76: 3 | H76: =IFERROR(F76*G76,0) -> 240 | I76: {=IFERROR(INDEX('Tasas de Cambio'!$E$11:$E$15,MATCH(E76,'Tasas de Cambio'!$B$11:$B$15,0)),0)} -> 3788.4 | J76: =IFERROR(H76*I76,0) -> 909216 | K76: =IFERROR(J76/'Tasas de Cambio'!$C$5,0) -> 303072 | L76: Recomendado: Excursión de día completo desde Múnich, incluye transporte + guía + entrada al castillo. https://www.machupicchu.org/best-neuschwanstein-castle-tours-2026-complete-guide.htm | M76: 28 ago 2026
A78: Vuelos y Trenes | B78: Alemania / Colombia | C78: 31 May 2027 | D78: Vuelo internacional Berlín → Bogotá (regreso) | E78: COP | F78: 0 | G78: 1 | H78: =IFERROR(F78*G78,0) -> 0 | I78: {=IFERROR(INDEX('Tasas de Cambio'!$E$11:$E$15,MATCH(E78,'Tasas de Cambio'!$B$11:$B$15,0)),0)} -> 1 | J78: =IFERROR(H78*I78,0) -> 0 | K78: =IFERROR(J78/'Tasas de Cambio'!$C$5,0) -> 0 | L78: Iberia IB0782, BER 11:35 local → MAD 14:50; conexión IB0153 → BOG 20:00 (hora Colombia). Incluido en ida. | M78: 11 sep 2026
A79: Traslados | B79: Alemania | C79: 26 May 2027 | D79: Traslado hotel → estación, Múnich | E79: EUR | F79: 10 | G79: 1 | H79: =IFERROR(F79*G79,0) -> 10 | I79: {=IFERROR(INDEX('Tasas de Cambio'!$E$11:$E$15,MATCH(E79,'Tasas de Cambio'!$B$11:$B$15,0)),0)} -> 3788.4 | J79: =IFERROR(H79*I79,0) -> 37884 | K79: =IFERROR(J79/'Tasas de Cambio'!$C$5,0) -> 12628 | L79: Estimado: el hotel está muy cerca de la Estación Central, Uber corto o caminando, €8-12. | M79: 11 sep 2026
A80: Tours y Excursiones | B80: Barcelona | C80: 8 May 2027 | D80: Free tour Sagrada Familia | E80: USD | F80: 10 | G80: 3 | H80: =IFERROR(F80*G80,0) -> 30 | I80: {=IFERROR(INDEX('Tasas de Cambio'!$E$11:$E$15,MATCH(E80,'Tasas de Cambio'!$B$11:$B$15,0)),0)} -> 3263.4 | J80: =IFERROR(H80*I80,0) -> 97902 | K80: =IFERROR(J80/'Tasas de Cambio'!$C$5,0) -> 32634 | L80: Free tour guiado por el exterior de la Sagrada Familia. https://www.civitatis.com/es/barcelona/free-tour-sagrada-familia/ | M80: 27 ago 2026
D81: TOTAL GENERAL | J81: =SUM(J5:J79) -> 61564256 | K81: =SUM(K5:K79) -> 20521419
A82: Otros y Extras | B82: Navegación | C82: 10 May 2027 | D82: Día de navegación | E82: COP | F82: 0 | G82: 1 | H82: =IFERROR(F82*G82,0) -> 0 | I82: {=IFERROR(INDEX('Tasas de Cambio'!$E$11:$E$15,MATCH(E82,'Tasas de Cambio'!$B$11:$B$15,0)),0)} -> 1 | J82: =IFERROR(H82*I82,0) -> 0 | K82: =IFERROR(J82/'Tasas de Cambio'!$C$5,0) -> 0 | L82: Día de navegación, incluido en la tarifa del crucero. https://www.royalcaribbean.com/lac/es/itinerary/7-night-italy-croatia-cruise-from-barcelona-on-brilliance-BR07M885?sailDate=2027-05-08&packageCode=BR07M885&groupId=BR07BCN-1768961711&country=COL&search=startDate:2027-05-01~2027-05-31 | M82: 27 ago 2026
A83: Otros y Extras | B83: Navegación | C83: 14 May 2027 | D83: Día de navegación | E83: COP | F83: 0 | G83: 1 | H83: =IFERROR(F83*G83,0) -> 0 | I83: {=IFERROR(INDEX('Tasas de Cambio'!$E$11:$E$15,MATCH(E83,'Tasas de Cambio'!$B$11:$B$15,0)),0)} -> 1 | J83: =IFERROR(H83*I83,0) -> 0 | K83: =IFERROR(J83/'Tasas de Cambio'!$C$5,0) -> 0 | L83: Día de navegación, incluido en la tarifa del crucero. https://www.royalcaribbean.com/lac/es/itinerary/7-night-italy-croatia-cruise-from-barcelona-on-brilliance-BR07M885?sailDate=2027-05-08&packageCode=BR07M885&groupId=BR07BCN-1768961711&country=COL&search=startDate:2027-05-01~2027-05-31 | M83: 27 ago 2026
A85: Comidas | B85: Praga | C85: 23 May 2027 | D85: Cena | E85: CZK | F85: 280 | G85: 3 | H85: =IFERROR(F85*G85,0) -> 840 | I85: {=IFERROR(INDEX('Tasas de Cambio'!$E$11:$E$15,MATCH(E85,'Tasas de Cambio'!$B$11:$B$15,0)),0)} -> 156.97 | J85: =IFERROR(H85*I85,0) -> 131854.8 | K85: =IFERROR(J85/'Tasas de Cambio'!$C$5,0) -> 43951.6 | L85: Cena de llegada | M85: 28 ago 2026
A86: Comidas | B86: Berlín | C86: 28 May 2027 | D86: Cena | E86: EUR | F86: 15 | G86: 3 | H86: =IFERROR(F86*G86,0) -> 45 | I86: {=IFERROR(INDEX('Tasas de Cambio'!$E$11:$E$15,MATCH(E86,'Tasas de Cambio'!$B$11:$B$15,0)),0)} -> 3788.4 | J86: =IFERROR(H86*I86,0) -> 170478 | K86: =IFERROR(J86/'Tasas de Cambio'!$C$5,0) -> 56826 | L86: Cena de llegada | M86: 28 ago 2026
A87: Comidas | B87: Múnich | C87: 26 May 2027 | D87: Cena | E87: EUR | F87: 20 | G87: 3 | H87: =IFERROR(F87*G87,0) -> 60 | I87: {=IFERROR(INDEX('Tasas de Cambio'!$E$11:$E$15,MATCH(E87,'Tasas de Cambio'!$B$11:$B$15,0)),0)} -> 3788.4 | J87: =IFERROR(H87*I87,0) -> 227304 | K87: =IFERROR(J87/'Tasas de Cambio'!$C$5,0) -> 75768 | L87: Cena de llegada | M87: 28 ago 2026
A88: Comidas | B88: Milán | C88: 19 May 2027 | D88: Comida del día (desayuno, almuerzo y cena) | E88: EUR | F88: 57 | G88: 3 | H88: =IFERROR(F88*G88,0) -> 171 | I88: {=IFERROR(INDEX('Tasas de Cambio'!$E$11:$E$15,MATCH(E88,'Tasas de Cambio'!$B$11:$B$15,0)),0)} -> 3788.4 | J88: =IFERROR(H88*I88,0) -> 647816.4 | K88: =IFERROR(J88/'Tasas de Cambio'!$C$5,0) -> 215938.8 | M88: 28 ago 2026
A89: Comidas | B89: Praga | C89: 25 May 2027 | D89: Comida del día (desayuno, almuerzo y cena) | E89: CZK | F89: 700 | G89: 3 | H89: =IFERROR(F89*G89,0) -> 2100 | I89: {=IFERROR(INDEX('Tasas de Cambio'!$E$11:$E$15,MATCH(E89,'Tasas de Cambio'!$B$11:$B$15,0)),0)} -> 156.97 | J89: =IFERROR(H89*I89,0) -> 329637 | K89: =IFERROR(J89/'Tasas de Cambio'!$C$5,0) -> 109879 | M89: 28 ago 2026
A90: Comidas | B90: Berlín | C90: 30 May 2027 | D90: Comida del día (desayuno, almuerzo y cena) | E90: EUR | F90: 40 | G90: 3 | H90: =IFERROR(F90*G90,0) -> 120 | I90: {=IFERROR(INDEX('Tasas de Cambio'!$E$11:$E$15,MATCH(E90,'Tasas de Cambio'!$B$11:$B$15,0)),0)} -> 3788.4 | J90: =IFERROR(H90*I90,0) -> 454608 | K90: =IFERROR(J90/'Tasas de Cambio'!$C$5,0) -> 151536 | M90: 28 ago 2026
A91: Comidas | B91: Berlín | C91: 31 May 2027 | D91: Comida del día (desayuno, almuerzo y cena) | E91: EUR | F91: 52 | G91: 3 | H91: =IFERROR(F91*G91,0) -> 156 | I91: {=IFERROR(INDEX('Tasas de Cambio'!$E$11:$E$15,MATCH(E91,'Tasas de Cambio'!$B$11:$B$15,0)),0)} -> 3788.4 | J91: =IFERROR(H91*I91,0) -> 590990.4 | K91: =IFERROR(J91/'Tasas de Cambio'!$C$5,0) -> 196996.8 | M91: 28 ago 2026
A92: Comidas | B92: — | C92: 7 May 2027 | D92: Comidas a bordo | E92: COP | F92: 0 | G92: 1 | H92: =IFERROR(F92*G92,0) -> 0 | I92: {=IFERROR(INDEX('Tasas de Cambio'!$E$11:$E$15,MATCH(E92,'Tasas de Cambio'!$B$11:$B$15,0)),0)} -> 1 | J92: =IFERROR(H92*I92,0) -> 0 | K92: =IFERROR(J92/'Tasas de Cambio'!$C$5,0) -> 0 | L92: Incluidas en el vuelo internacional | M92: 28 ago 2026
A93: Comidas | B93: Navegación | C93: 10 May 2027 | D93: Incluidas en el crucero (come a bordo) | E93: COP | F93: 0 | G93: 1 | H93: =IFERROR(F93*G93,0) -> 0 | I93: {=IFERROR(INDEX('Tasas de Cambio'!$E$11:$E$15,MATCH(E93,'Tasas de Cambio'!$B$11:$B$15,0)),0)} -> 1 | J93: =IFERROR(H93*I93,0) -> 0 | K93: =IFERROR(J93/'Tasas de Cambio'!$C$5,0) -> 0 | M93: 28 ago 2026
A94: Comidas | B94: Navegación | C94: 14 May 2027 | D94: Incluidas en el crucero (come a bordo) | E94: COP | F94: 0 | G94: 1 | H94: =IFERROR(F94*G94,0) -> 0 | I94: {=IFERROR(INDEX('Tasas de Cambio'!$E$11:$E$15,MATCH(E94,'Tasas de Cambio'!$B$11:$B$15,0)),0)} -> 1 | J94: =IFERROR(H94*I94,0) -> 0 | K94: =IFERROR(J94/'Tasas de Cambio'!$C$5,0) -> 0 | M94: 28 ago 2026

Sheet Resumen
B2: RESUMEN DE COTIZACIÓN — EUROPA 2027
B3: 30 de abril al 29 de mayo de 2027 · 30 días / 29 noches
B5: TOTAL POR CATEGORÍA
B6: Categoría | C6: Total (COP) | D6: Total (USD) | E6: % del total
B7: Vuelos y Trenes | C7: =SUMIF('Cotización'!$A:$A,B7,'Cotización'!$J:$J) -> 16266882 | D7: =IFERROR(C7/'Tasas de Cambio'!$E$14,0) -> 5054.5738 | E7: =IFERROR(C7/$C$15,0) -> 0.26422608
B8: Traslados | C8: =SUMIF('Cotización'!$A:$A,B8,'Cotización'!$J:$J) -> 2467285.8 | D8: =IFERROR(C8/'Tasas de Cambio'!$E$14,0) -> 766.65449 | E8: =IFERROR(C8/$C$15,0) -> 0.040076596
B9: Alojamiento | C9: =SUMIF('Cotización'!$A:$A,B9,'Cotización'!$J:$J) -> 12743220 | D9: =IFERROR(C9/'Tasas de Cambio'!$E$14,0) -> 3959.6737 | E9: =IFERROR(C9/$C$15,0) -> 0.20699056
B10: Crucero | C10: =SUMIF('Cotización'!$A:$A,B10,'Cotización'!$J:$J) -> 6468682.5 | D10: =IFERROR(C10/'Tasas de Cambio'!$E$14,0) -> 2010 | E10: =IFERROR(C10/$C$15,0) -> 0.10507205
B11: Tours y Excursiones | C11: =SUMIF('Cotización'!$A:$A,B11,'Cotización'!$J:$J) -> 12080007 | D11: =IFERROR(C11/'Tasas de Cambio'!$E$14,0) -> 3753.5951 | E11: =IFERROR(C11/$C$15,0) -> 0.19621788
B12: Comidas | C12: =SUMIF('Cotización'!$A:$A,B12,'Cotización'!$J:$J) -> 8377740 | D12: =IFERROR(C12/'Tasas de Cambio'!$E$14,0) -> 2603.1974 | E12: =IFERROR(C12/$C$15,0) -> 0.13608124
B13: Seguro de Viaje | C13: =SUMIF('Cotización'!$A:$A,B13,'Cotización'!$J:$J) -> 760054 | D13: =IFERROR(C13/'Tasas de Cambio'!$E$14,0) -> 236.16997 | E13: =IFERROR(C13/$C$15,0) -> 0.012345703
B14: Otros y Extras | C14: =SUMIF('Cotización'!$A:$A,B14,'Cotización'!$J:$J) -> 2400384 | D14: =IFERROR(C14/'Tasas de Cambio'!$E$14,0) -> 745.86623 | E14: =IFERROR(C14/$C$15,0) -> 0.038989897
B15: TOTAL GENERAL | C15: =SUM(C7:C14) -> 61564256 | D15: =SUM(D7:D14) -> 19129.731
B17: COSTO POR PERSONA
B18: Número de personas | C18: ='Tasas de Cambio'!$C$5 -> 3
B19: Costo por persona (COP) | C19: =IFERROR($C$15/'Tasas de Cambio'!$C$5,0) -> 20521419
B20: Costo por persona (USD) | C20: =IFERROR($D$15/'Tasas de Cambio'!$C$5,0) -> 6376.5769
B21: Costo promedio por persona / día (COP) | C21: =IFERROR(C19/30,0) -> 684047.29
B23: TASAS DE CAMBIO UTILIZADAS
B24: Moneda | C24: Tasa a COP
B25: ='Tasas de Cambio'!$B$11 -> EUR | C25: ='Tasas de Cambio'!$E$11 -> 3750.6
B26: ='Tasas de Cambio'!$B$12 -> CHF | C26: ='Tasas de Cambio'!$E$12 -> 4053
B27: ='Tasas de Cambio'!$B$13 -> CZK | C27: ='Tasas de Cambio'!$E$13 -> 155.82
B28: ='Tasas de Cambio'!$B$14 -> USD | C28: ='Tasas de Cambio'!$E$14 -> 3218.25
B29: ='Tasas de Cambio'!$B$15 -> COP | C29: ='Tasas de Cambio'!$E$15 -> 1
B31: Cifras referenciales — sujetas a disponibilidad, temporada y tasa de cambio del día de pago. Documento generado como herramienta de cotización, no constituye una tarifa garantizada.

Sheet Crucero y Zurich
A2: COTIZACIÓN DETALLADA — EUROPA 2027 (01 May – 16 May 2027) | O2: Vuelos y Trenes | P2: EUR
O3: Traslados | P3: CHF
A4: Categoría | B4: Ciudad / País | C4: Fechas | D4: Concepto / Descripción | E4: Moneda | F4: Costo Unitario (moneda original) | G4: Cantidad | H4: Costo Total (moneda original) | I4: Tasa de Cambio a COP | J4: Costo Total (COP) | K4: Costo por Persona (COP) | L4: Notas | M4: Fecha confirmación precio | O4: Alojamiento | P4: CZK
A5: Tours y Excursiones | B5: Barcelona | C5: 7 May 2027 | D5: Tour Barcelona Modernista | E5: USD | F5: 10 | G5: 3 | H5: =IFERROR(F5*G5,0) -> 30 | I5: {=IFERROR(INDEX('Tasas de Cambio'!$E$11:$E$15,MATCH(E5,'Tasas de Cambio'!$B$11:$B$15,0)),0)} -> 3263.4 | J5: =IFERROR(H5*I5,0) -> 97902 | K5: =IFERROR(J5/'Tasas de Cambio'!$C$5,0) -> 32634 | L5: Tour guiado por el Modernismo catalán en Barcelona. https://www.civitatis.com/es/barcelona/tour-barcelona-modernista/ | M5: 27 ago 2026
A6: Tours y Excursiones | B6: Barcelona | C6: 7 May 2027 | D6: Free tour Sagrada Familia | E6: USD | F6: 10 | G6: 3 | H6: =IFERROR(F6*G6,0) -> 30 | I6: {=IFERROR(INDEX('Tasas de Cambio'!$E$11:$E$15,MATCH(E6,'Tasas de Cambio'!$B$11:$B$15,0)),0)} -> 3263.4 | J6: =IFERROR(H6*I6,0) -> 97902 | K6: =IFERROR(J6/'Tasas de Cambio'!$C$5,0) -> 32634 | L6: Free tour guiado por el exterior de la Sagrada Familia. https://www.civitatis.com/es/barcelona/free-tour-sagrada-familia/ | M6: 27 ago 2026
A7: Otros y Extras | B7: Navegación | C7: 9 May 2027 | D7: Día de navegación | E7: COP | F7: 0 | G7: 1 | H7: =IFERROR(F7*G7,0) -> 0 | I7: {=IFERROR(INDEX('Tasas de Cambio'!$E$11:$E$15,MATCH(E7,'Tasas de Cambio'!$B$11:$B$15,0)),0)} -> 1 | J7: =IFERROR(H7*I7,0) -> 0 | K7: =IFERROR(J7/'Tasas de Cambio'!$C$5,0) -> 0 | L7: Día de navegación, incluido en la tarifa del crucero. https://www.royalcaribbean.com/lac/es/itinerary/7-night-italy-croatia-cruise-from-barcelona-on-brilliance-BR07M885?sailDate=2027-05-08&packageCode=BR07M885&groupId=BR07BCN-1768961711&country=COL&search=startDate:2027-05-01~2027-05-31 | M7: 27 ago 2026
A8: Otros y Extras | B8: Navegación | C8: 13 May 2027 | D8: Día de navegación | E8: COP | F8: 0 | G8: 1 | H8: =IFERROR(F8*G8,0) -> 0 | I8: {=IFERROR(INDEX('Tasas de Cambio'!$E$11:$E$15,MATCH(E8,'Tasas de Cambio'!$B$11:$B$15,0)),0)} -> 1 | J8: =IFERROR(H8*I8,0) -> 0 | K8: =IFERROR(J8/'Tasas de Cambio'!$C$5,0) -> 0 | L8: Día de navegación, incluido en la tarifa del crucero. https://www.royalcaribbean.com/lac/es/itinerary/7-night-italy-croatia-cruise-from-barcelona-on-brilliance-BR07M885?sailDate=2027-05-08&packageCode=BR07M885&groupId=BR07BCN-1768961711&country=COL&search=startDate:2027-05-01~2027-05-31 | M8: 27 ago 2026
A9: Traslados | B9: Venecia | C9: 15 May 2027 | D9: Vaporetti ACTV | E9: EUR | F9: 25 | G9: 3 | H9: =IFERROR(F9*G9,0) -> 75 | I9: {=IFERROR(INDEX('Tasas de Cambio'!$E$11:$E$15,MATCH(E9,'Tasas de Cambio'!$B$11:$B$15,0)),0)} -> 3788.4 | J9: =IFERROR(H9*I9,0) -> 284130 | K9: =IFERROR(J9/'Tasas de Cambio'!$C$5,0) -> 94710 | L9: Boletos de vaporetto (transporte acuático) por Venecia. https://book.tickets-venice.com/es/book/8748/select/?_gl=1%2A1073ils%2A_gcl_aw%2AR0NMLjE3ODc4NzgwODMuRUFJYUlRb2JDaE1JaFpPNjdZekNsZ01Wd1lSYUJSM2Y1U1JPRUFBWUF5QUFFZ0tjeFBEX0J3RQ..%2A_gcl_au%2ANzIxMTA1MTQ5LjE3ODc4NzgwODMuLS4tLjE3ODc4NzgwODMuMTE2MDU2ODc1MS4xNzg3ODc4MDg0LjE3ODc4NzgwODM.%2A_ga%2ANDcyOTU3MzYyLjE3ODc4NzgwODM.%2A_ga_Y45PC9R73C%2AczE3ODc4NzgwODMkbzEkZzAkdDE3ODc4NzgwODQkajU5JGwwJGgw&cookieBanner=false&date=2027-05-15&tourId=15560&variantId=15560 | M9: 27 ago 2026
A10: Otros y Extras | C10: Durante el viaje | D10: SIM card de viaje (datos internacionales) | E10: USD | F10: 52 | G10: 1 | H10: 52 | I10: {=IFERROR(INDEX('Tasas de Cambio'!$E$11:$E$15,MATCH(E10,'Tasas de Cambio'!$B$11:$B$15,0)),0)} -> 3263.4 | J10: 169696.8 | K10: =IFERROR(J10/'Tasas de Cambio'!$C$5,0) -> 56565.6 | L10: SIM compartida entre las 3 personas para los 16 días del viaje. https://esim.holafly.com/es/esim-europa/?selectedDays=16&startDate=2027-05-01&endDate=2027-05-16 | M10: 27 ago 2026
A11: Otros y Extras | C11: Contingencia | D11: Imprevistos / gastos varios (contingencia) | E11: EUR | F11: 200 | G11: 3 | H11: 600 | I11: {=IFERROR(INDEX('Tasas de Cambio'!$E$11:$E$15,MATCH(E11,'Tasas de Cambio'!$B$11:$B$15,0)),0)} -> 3788.4 | J11: 2273040 | K11: =IFERROR(J11/'Tasas de Cambio'!$C$5,0) -> 757680
A12: Vuelos y Trenes | B12: Bogota / Zúrich | C12: 46507 | D12: Vuelo internacional Bogotá → Zúrich (ida) | E12: COP | F12: 1557040 | G12: 3 | H12: 4671120 | I12: {=IFERROR(INDEX('Tasas de Cambio'!$E$11:$E$15,MATCH(E12,'Tasas de Cambio'!$B$11:$B$15,0)),0)} -> 1 | J12: 4671120 | K12: =IFERROR(J12/'Tasas de Cambio'!$C$5,0) -> 1557040 | L12: Lufthansa, sale vie 30 abr 23:30 BOG, llega sáb 1 may 19:15 ZRH (vía FRA), 12h45m, Economy Light. Total ida+regreso $3.114.080 COP/persona, dividido entre los 2 tramos.
A13: Traslados | B13: Suiza | C13: 46508 | D13: Traslado aeropuerto → hotel, Zúrich | E13: CHF | F13: 45 | G13: 1 | H13: 45 | I13: {=IFERROR(INDEX('Tasas de Cambio'!$E$11:$E$15,MATCH(E13,'Tasas de Cambio'!$B$11:$B$15,0)),0)} -> 4038.3 | J13: 181723.5 | K13: =IFERROR(J13/'Tasas de Cambio'!$C$5,0) -> 60574.5 | L13: Estimado: Uber X / taxi Zúrich, CHF 45 aprox. (aeropuerto-centro ~20-25 min, 1 carro para el grupo). Taxi normal: CHF 50-70.
A14: Alojamiento | B14: Zúrich, Suiza | C14: 1 May – 6 May (5 noches) | D14: Hotel Zúrich — costo total (5 noches) | E14: CHF | F14: 900 | G14: 1 | H14: =IFERROR(F14*G14,0) -> 900 | I14: {=IFERROR(INDEX('Tasas de Cambio'!$E$11:$E$15,MATCH(E14,'Tasas de Cambio'!$B$11:$B$15,0)),0)} -> 4038.3 | J14: =IFERROR(H14*I14,0) -> 3634470 | K14: =IFERROR(J14/'Tasas de Cambio'!$C$5,0) -> 1211490 | M14: 27 ago 2026
A15: Seguro de Viaje | B15: Internacional | C15: 1 – 16 may 2027 (16 días de cobertura) | D15: Asistencia médica internacional | E15: COP | F15: 295980 | G15: 3 | H15: =IFERROR(F15*G15,0) -> 887940 | I15: {=IFERROR(INDEX('Tasas de Cambio'!$E$11:$E$15,MATCH(E15,'Tasas de Cambio'!$B$11:$B$15,0)),0)} -> 1 | J15: =IFERROR(H15*I15,0) -> 887940 | K15: =IFERROR(J15/'Tasas de Cambio'!$C$5,0) -> 295980 | L15: Asistencia médica internacional, cobertura USD 60.000 (Cuponatic). https://www.cuponatic.com.co/descuento/asistencia-medica-internacional-cobertura-de-usd-60-000?m=tarjetas-de-asistencia&id_descuento=212587 | M15: 27 ago 2026
A16: Tours y Excursiones | B16: Zurich | C16: 1 May 2027 | D16: City Tour, Cruise en el lago y Lindt Home of Chocolate | E16: USD | F16: 90 | G16: 3 | H16: 270 | I16: {=IFERROR(INDEX('Tasas de Cambio'!$E$11:$E$15,MATCH(E16,'Tasas de Cambio'!$B$11:$B$15,0)),0)} -> 3263.4 | J16: 881118 | K16: =IFERROR(J16/'Tasas de Cambio'!$C$5,0) -> 293706 | L16: Recomendado (4.5★, +4600 reseñas) - tour de medio día | https://www.getyourguide.com/zurich-l55/zurich-city-tour-with-cruise-chocolate-t75865/
A17: Tours y Excursiones | B17: Zurich | C17: 46509.0 | D17: Excursión Jungfraujoch (tren panorámico, por persona) | E17: USD | F17: 362 | G17: 3 | H17: =IFERROR(F17*G17,0) -> 1086 | I17: {=IFERROR(INDEX('Tasas de Cambio'!$E$11:$E$15,MATCH(E17,'Tasas de Cambio'!$B$11:$B$15,0)),0)} -> 3263.4 | J17: =IFERROR(H17*I17,0) -> 3544052.4 | K17: =IFERROR(J17/'Tasas de Cambio'!$C$5,0) -> 1181350.8 | L17: Recomendado - tour guiado de día completo desde Zúrich (12h, incl. transporte y entrada Top of Europe). https://www.civitatis.com/es/zurich/excursion-jungfraujoch/ | M17: 28 ago 2026
A18: Comidas | B18: Zurich | C18: 46509.0 | D18: Comida del día (desayuno, almuerzo y cena) | E18: CHF | F18: 70 | G18: 3 | H18: =IFERROR(F18*G18,0) -> 210 | I18: {=IFERROR(INDEX('Tasas de Cambio'!$E$11:$E$15,MATCH(E18,'Tasas de Cambio'!$B$11:$B$15,0)),0)} -> 4038.3 | J18: =IFERROR(H18*I18,0) -> 848043 | K18: =IFERROR(J18/'Tasas de Cambio'!$C$5,0) -> 282681 | L18: Estimado: ~CHF 70/persona/día (desayuno+almuerzo+cena) | M18: 28 ago 2026
A19: Tours y Excursiones | B19: Zurich | C19: 46510 | D19: Mount Pilatus & Lucerne - excursión de un día (cogwheel + góndola + crucero lago) | E19: USD | F19: 150 | G19: 3 | H19: 450 | I19: {=IFERROR(INDEX('Tasas de Cambio'!$E$11:$E$15,MATCH(E19,'Tasas de Cambio'!$B$11:$B$15,0)),0)} -> 3263.4 | J19: 1468530 | K19: =IFERROR(J19/'Tasas de Cambio'!$C$5,0) -> 489510 | L19: Recomendado (Viator, 980+ reseñas) | https://www.viator.com/tours/Zurich/Mount-Pilatus-Summer-Day-Trip-from-Zurich/d577-3885SW304BS
A20: Comidas | B20: Zurich | C20: 46510.0 | D20: Comida del día (desayuno, almuerzo y cena) | E20: CHF | F20: 70 | G20: 3 | H20: =IFERROR(F20*G20,0) -> 210 | I20: {=IFERROR(INDEX('Tasas de Cambio'!$E$11:$E$15,MATCH(E20,'Tasas de Cambio'!$B$11:$B$15,0)),0)} -> 4038.3 | J20: =IFERROR(H20*I20,0) -> 848043 | K20: =IFERROR(J20/'Tasas de Cambio'!$C$5,0) -> 282681 | L20: Estimado: ~CHF 70/persona/día (desayuno+almuerzo+cena) | M20: 28 ago 2026
A21: Tours y Excursiones | B21: Zurich | C21: 46511 | D21: Grindelwald, Interlaken y Lauterbrunnen - excursión de un día | E21: USD | F21: 138 | G21: 3 | H21: 414 | I21: {=IFERROR(INDEX('Tasas de Cambio'!$E$11:$E$15,MATCH(E21,'Tasas de Cambio'!$B$11:$B$15,0)),0)} -> 3263.4 | J21: 1351047.6 | K21: =IFERROR(J21/'Tasas de Cambio'!$C$5,0) -> 450349.2 | L21: Recomendado (4.5★, 152 reseñas) | https://www.getyourguide.com/zurich-l55/zurich-day-trip-to-grindelwald-interlaken-lauterbrunnen-t42647/
A22: Comidas | B22: Zurich | C22: 46511.0 | D22: Comida del día (desayuno, almuerzo y cena) | E22: CHF | F22: 70 | G22: 3 | H22: =IFERROR(F22*G22,0) -> 210 | I22: {=IFERROR(INDEX('Tasas de Cambio'!$E$11:$E$15,MATCH(E22,'Tasas de Cambio'!$B$11:$B$15,0)),0)} -> 4038.3 | J22: =IFERROR(H22*I22,0) -> 848043 | K22: =IFERROR(J22/'Tasas de Cambio'!$C$5,0) -> 282681 | L22: Estimado: ~CHF 70/persona/día (desayuno+almuerzo+cena) | M22: 28 ago 2026
A23: Tours y Excursiones | B23: Zurich | C23: 46512 | D23: Cataratas del Rin (Schaffhausen) - excursión de medio día | E23: USD | F23: 70 | G23: 3 | H23: 210 | I23: {=IFERROR(INDEX('Tasas de Cambio'!$E$11:$E$15,MATCH(E23,'Tasas de Cambio'!$B$11:$B$15,0)),0)} -> 3263.4 | J23: 685314 | K23: =IFERROR(J23/'Tasas de Cambio'!$C$5,0) -> 228438 | L23: Recomendado - las cataratas más grandes de Europa | https://www.viator.com/tours/Zurich/Rhine-Falls-and-Stein-am-Rhein-Half-Day-Tour-from-Zurich/d577-3885RHINESTEIN
A24: Comidas | B24: Zurich | C24: 46512.0 | D24: Comida del día (desayuno, almuerzo y cena) | E24: CHF | F24: 70 | G24: 3 | H24: =IFERROR(F24*G24,0) -> 210 | I24: {=IFERROR(INDEX('Tasas de Cambio'!$E$11:$E$15,MATCH(E24,'Tasas de Cambio'!$B$11:$B$15,0)),0)} -> 4038.3 | J24: =IFERROR(H24*I24,0) -> 848043 | K24: =IFERROR(J24/'Tasas de Cambio'!$C$5,0) -> 282681 | L24: Estimado: ~CHF 70/persona/día (desayuno+almuerzo+cena) | M24: 28 ago 2026
A25: Alojamiento | B25: Barcelona, España | C25: 6 – 8 May (2 noches, pre-crucero) | D25: Hotel Barcelona — costo total (2 noches) | E25: COP | F25: 1900000 | G25: 1 | H25: =IFERROR(F25*G25,0) -> 1900000 | I25: {=IFERROR(INDEX('Tasas de Cambio'!$E$11:$E$15,MATCH(E25,'Tasas de Cambio'!$B$11:$B$15,0)),0)} -> 1 | J25: =IFERROR(H25*I25,0) -> 1900000 | K25: =IFERROR(J25/'Tasas de Cambio'!$C$5,0) -> 633333.33 | L25: Sagrada Familia, 2 noches (6-8 may). https://www.booking.com/hotel/es/sagradafamilia.es.html?aid=2311236&label=es-co-booking-desktop-vjGZbEFOhRc3a9njxeT3IwS652829002024%3Apl%3Ata%3Ap1%3Ap2%3Aac%3Aap%3Aneg%3Afi%3Atikwd-65526620%3Alp9246960%3Ali%3Adec%3Adm&sid=f6a1a9bb810c453f7b5f1225205f1f26&all_sr_blocks=9118812_91908190_0_2_0&checkin=2027-05-06&checkout=2027-05-08&dest_id=-372490&dest_type=city&dist=0&group_adults=3&group_children=0&hapos=1&highlighted_blocks=9118812_91908190_0_2_0&hpos=1&matching_block_id=9118812_91908190_0_2_0&no_rooms=1&req_adults=3&req_children=0&room1=A%2CA%2CA&sb_price_type=total&sr_order=popularity&sr_pri_blocks=9118812_91908190_0_2_0__37600&srepoch=1787875557&srpvid=a2d600b07c230149&type=total&ucfs=1 | M25: 27 ago 2026
A26: Vuelos y Trenes | B26: Zúrich / Barcelona | C26: 46513 | D26: Vuelo Swiss Int. Air Lines Zúrich → Barcelona, directo | E26: CHF | F26: 271 | G26: 3 | H26: 813 | I26: {=IFERROR(INDEX('Tasas de Cambio'!$E$11:$E$15,MATCH(E26,'Tasas de Cambio'!$B$11:$B$15,0)),0)} -> 4038.3 | J26: 3283137.9 | K26: =IFERROR(J26/'Tasas de Cambio'!$C$5,0) -> 1094379.3 | L26: Jue 6 may, sale 07:10 ZRH, llega 08:50 BCN, directo (1h40m), Economy Light
A27: Traslados | B27: Suiza | C27: 46513 | D27: Traslado hotel → aeropuerto, Zúrich | E27: CHF | F27: 45 | G27: 1 | H27: 45 | I27: {=IFERROR(INDEX('Tasas de Cambio'!$E$11:$E$15,MATCH(E27,'Tasas de Cambio'!$B$11:$B$15,0)),0)} -> 4038.3 | J27: 181723.5 | K27: =IFERROR(J27/'Tasas de Cambio'!$C$5,0) -> 60574.5 | L27: Estimado: Uber X / taxi Zúrich, CHF 45 aprox. (aeropuerto-centro ~20-25 min, 1 carro para el grupo). Taxi normal: CHF 50-70.
A28: Traslados | B28: España | C28: 46513.0 | D28: Traslado aeropuerto → hotel, Barcelona | E28: EUR | F28: 40 | G28: 1 | H28: =IFERROR(F28*G28,0) -> 40 | I28: {=IFERROR(INDEX('Tasas de Cambio'!$E$11:$E$15,MATCH(E28,'Tasas de Cambio'!$B$11:$B$15,0)),0)} -> 3788.4 | J28: =IFERROR(H28*I28,0) -> 151536 | K28: =IFERROR(J28/'Tasas de Cambio'!$C$5,0) -> 50512 | M28: 27 ago 2026
A29: Comidas | B29: Barcelona | C29: 46513 | D29: cena | E29: EUR | F29: 15 | G29: 3 | H29: 45 | I29: {=IFERROR(INDEX('Tasas de Cambio'!$E$11:$E$15,MATCH(E29,'Tasas de Cambio'!$B$11:$B$15,0)),0)} -> 3788.4 | J29: 170478 | K29: =IFERROR(J29/'Tasas de Cambio'!$C$5,0) -> 56826
A30: Vuelos y Trenes | B30: Italia | C30: 15 May 2027 | D30: Tren Ravenna - Venecia St Lucia | E30: EUR | F30: 25 | G30: 3 | H30: =IFERROR(F30*G30,0) -> 75 | I30: {=IFERROR(INDEX('Tasas de Cambio'!$E$11:$E$15,MATCH(E30,'Tasas de Cambio'!$B$11:$B$15,0)),0)} -> 3788.4 | J30: =IFERROR(H30*I30,0) -> 284130 | K30: =IFERROR(J30/'Tasas de Cambio'!$C$5,0) -> 94710 | L30: Tren regional desde Ravenna hasta Venecia Santa Lucia. https://www.trenitalia.com/en.html | M30: 27 ago 2026
A31: Comidas | B31: Barcelona | C31: 46514 | D31: 3 comidas | E31: EUR | F31: 30 | G31: 3 | H31: 90 | I31: {=IFERROR(INDEX('Tasas de Cambio'!$E$11:$E$15,MATCH(E31,'Tasas de Cambio'!$B$11:$B$15,0)),0)} -> 3788.4 | J31: 340956 | K31: =IFERROR(J31/'Tasas de Cambio'!$C$5,0) -> 113652
A32: Traslados | B32: Barcelona | C32: 46514.0 | D32: Bus, 4 trayectos | E32: EUR | F32: 12 | G32: 3 | H32: =IFERROR(F32*G32,0) -> 36 | I32: {=IFERROR(INDEX('Tasas de Cambio'!$E$11:$E$15,MATCH(E32,'Tasas de Cambio'!$B$11:$B$15,0)),0)} -> 3788.4 | J32: =IFERROR(H32*I32,0) -> 136382.4 | K32: =IFERROR(J32/'Tasas de Cambio'!$C$5,0) -> 45460.8 | M32: 27 ago 2026
A33: Crucero | B33: Mediterráneo | C33: 8 – 15 May (7 noches) | D33: Crucero Barcelona → Ravena — tarifa por persona (cabina) | E33: USD | F33: 670 | G33: 3 | H33: =IFERROR(F33*G33,0) -> 2010 | I33: {=IFERROR(INDEX('Tasas de Cambio'!$E$11:$E$15,MATCH(E33,'Tasas de Cambio'!$B$11:$B$15,0)),0)} -> 3263.4 | J33: =IFERROR(H33*I33,0) -> 6559434 | K33: =IFERROR(J33/'Tasas de Cambio'!$C$5,0) -> 2186478 | L33: Crucero Barcelona-Ravena, 7 noches, incluye propinas. https://www.royalcaribbean.com/lac/es/itinerary/7-night-italy-croatia-cruise-from-barcelona-on-brilliance-BR07M885?sailDate=2027-05-08&packageCode=BR07M885&groupId=BR07BCN-1768961711&country=COL&search=startDate:2027-05-01~2027-05-31 | M33: 27 ago 2026
A34: Traslados | B34: España | C34: 46515 | D34: Traslado hotel → puerto (embarque crucero), Barcelona | E34: EUR | F34: 30 | G34: 1 | H34: 30 | I34: {=IFERROR(INDEX('Tasas de Cambio'!$E$11:$E$15,MATCH(E34,'Tasas de Cambio'!$B$11:$B$15,0)),0)} -> 3788.4 | J34: 113652 | K34: =IFERROR(J34/'Tasas de Cambio'!$C$5,0) -> 37884
A35: Tours y Excursiones | B35: Barcelona | C35: 46515 | D35: N/A | E35: EUR | F35: 0 | G35: 3 | H35: 0 | I35: {=IFERROR(INDEX('Tasas de Cambio'!$E$11:$E$15,MATCH(E35,'Tasas de Cambio'!$B$11:$B$15,0)),0)} -> 3788.4 | J35: 0 | K35: =IFERROR(J35/'Tasas de Cambio'!$C$5,0) -> 0
A36: Comidas | B36: Barcelona | C36: 46515 | D36: desayuno | E36: EUR | F36: 10 | G36: 3 | H36: 30 | I36: {=IFERROR(INDEX('Tasas de Cambio'!$E$11:$E$15,MATCH(E36,'Tasas de Cambio'!$B$11:$B$15,0)),0)} -> 3788.4 | J36: 113652 | K36: =IFERROR(J36/'Tasas de Cambio'!$C$5,0) -> 37884
A37: Tours y Excursiones | B37: Navegacion | C37: 46516 | D37: N/A | E37: EUR | F37: 0 | G37: 3 | H37: 0 | I37: {=IFERROR(INDEX('Tasas de Cambio'!$E$11:$E$15,MATCH(E37,'Tasas de Cambio'!$B$11:$B$15,0)),0)} -> 3788.4 | J37: 0 | K37: =IFERROR(J37/'Tasas de Cambio'!$C$5,0) -> 0
A38: Tours y Excursiones | B38: La Spezia (Florencia/Pisa) | C38: 46517.0 | D38: Panoramic Pisa | E38: USD | F38: 70 | G38: 3 | H38: =IFERROR(F38*G38,0) -> 210 | I38: {=IFERROR(INDEX('Tasas de Cambio'!$E$11:$E$15,MATCH(E38,'Tasas de Cambio'!$B$11:$B$15,0)),0)} -> 3263.4 | J38: =IFERROR(H38*I38,0) -> 685314 | K38: =IFERROR(J38/'Tasas de Cambio'!$C$5,0) -> 228438 | L38: Excursión panorámica por Pisa desde el crucero. https://www.royalcaribbean.com/account/cruise-planner/category/shorex/product/Y8RO?bookingId=3113096&shipCode=BR&sailDate=20270508 | M38: 27 ago 2026
A39: Comidas | B39: La Spezia (Florencia/Pisa) | C39: 46517.0 | D39: Almuerzo en tierra | E39: EUR | F39: 25 | G39: 3 | H39: =IFERROR(F39*G39,0) -> 75 | I39: {=IFERROR(INDEX('Tasas de Cambio'!$E$11:$E$15,MATCH(E39,'Tasas de Cambio'!$B$11:$B$15,0)),0)} -> 3788.4 | J39: =IFERROR(H39*I39,0) -> 284130 | K39: =IFERROR(J39/'Tasas de Cambio'!$C$5,0) -> 94710 | L39: Desayuno y cena incluidos en el crucero, almuerzo en Pisa/Florencia | M39: 28 ago 2026
A40: Tours y Excursiones | B40: Civitavecchia (Roma) | C40: 46518.0 | D40: Visit to Rome | E40: USD | F40: 142 | G40: 3 | H40: =IFERROR(F40*G40,0) -> 426 | I40: {=IFERROR(INDEX('Tasas de Cambio'!$E$11:$E$15,MATCH(E40,'Tasas de Cambio'!$B$11:$B$15,0)),0)} -> 3263.4 | J40: =IFERROR(H40*I40,0) -> 1390208.4 | K40: =IFERROR(J40/'Tasas de Cambio'!$C$5,0) -> 463402.8 | L40: Excursión a Roma desde el crucero. https://www.royalcaribbean.com/account/cruise-planner/category/shorex/product/CV1F?bookingId=3113096&shipCode=BR&sailDate=20270508 | M40: 29 ago 2026
A41: Comidas | B41: Civitavecchia (Roma) | C41: 46518.0 | D41: Almuerzo en tierra | E41: EUR | F41: 25 | G41: 3 | H41: =IFERROR(F41*G41,0) -> 75 | I41: {=IFERROR(INDEX('Tasas de Cambio'!$E$11:$E$15,MATCH(E41,'Tasas de Cambio'!$B$11:$B$15,0)),0)} -> 3788.4 | J41: =IFERROR(H41*I41,0) -> 284130 | K41: =IFERROR(J41/'Tasas de Cambio'!$C$5,0) -> 94710 | L41: Desayuno y cena incluidos en el crucero, almuerzo en Roma | M41: 28 ago 2026
A42: Tours y Excursiones | B42: Salerno (Costa Amalfitana) | C42: 46519.0 | D42: Tour a pie gratis | E42: EUR | F42: 0 | G42: 3 | H42: =IFERROR(F42*G42,0) -> 0 | I42: {=IFERROR(INDEX('Tasas de Cambio'!$E$11:$E$15,MATCH(E42,'Tasas de Cambio'!$B$11:$B$15,0)),0)} -> 3788.4 | J42: =IFERROR(H42*I42,0) -> 0 | K42: =IFERROR(J42/'Tasas de Cambio'!$C$5,0) -> 0 | M42: 27 ago 2026
A43: Comidas | B43: Salerno (Costa Amalfitana) | C43: 46519.0 | D43: Incluida en el crucero (come a bordo) | E43: EUR | F43: 0 | G43: 3 | H43: =IFERROR(F43*G43,0) -> 0 | I43: {=IFERROR(INDEX('Tasas de Cambio'!$E$11:$E$15,MATCH(E43,'Tasas de Cambio'!$B$11:$B$15,0)),0)} -> 3788.4 | J43: =IFERROR(H43*I43,0) -> 0 | K43: =IFERROR(J43/'Tasas de Cambio'!$C$5,0) -> 0 | L43: Comida incluida en el paquete del crucero, sin costo adicional | M43: 27 ago 2026
A44: Tours y Excursiones | B44: Navegacion | C44: 46520 | D44: N/A | E44: CZK | F44: 0 | G44: 3 | H44: 0 | I44: {=IFERROR(INDEX('Tasas de Cambio'!$E$11:$E$15,MATCH(E44,'Tasas de Cambio'!$B$11:$B$15,0)),0)} -> 156.97 | J44: 0 | K44: =IFERROR(J44/'Tasas de Cambio'!$C$5,0) -> 0
A45: Traslados | B45: Zadar, Croacia | C45: 46521 | D45: Transporte - Tour a pie gratis | E45: EUR | F45: 10 | G45: 3 | H45: 30 | I45: {=IFERROR(INDEX('Tasas de Cambio'!$E$11:$E$15,MATCH(E45,'Tasas de Cambio'!$B$11:$B$15,0)),0)} -> 3788.4 | J45: 113652 | K45: =IFERROR(J45/'Tasas de Cambio'!$C$5,0) -> 37884
A46: Comidas | B46: Zadar, Croacia | C46: 46521.0 | D46: Incluida en el crucero (come a bordo) | E46: EUR | F46: 0 | G46: 3 | H46: =IFERROR(F46*G46,0) -> 0 | I46: {=IFERROR(INDEX('Tasas de Cambio'!$E$11:$E$15,MATCH(E46,'Tasas de Cambio'!$B$11:$B$15,0)),0)} -> 3788.4 | J46: =IFERROR(H46*I46,0) -> 0 | K46: =IFERROR(J46/'Tasas de Cambio'!$C$5,0) -> 0 | L46: Comida incluida en el paquete del crucero, sin costo adicional | M46: 27 ago 2026
A47: Alojamiento | B47: Venecia, Italia | C47: 15 – 16 May (1 noche, post-crucero) | D47: Hotel Venecia — costo total (1 noche) | E47: EUR | F47: 400 | G47: 1 | H47: =IFERROR(F47*G47,0) -> 400 | I47: {=IFERROR(INDEX('Tasas de Cambio'!$E$11:$E$15,MATCH(E47,'Tasas de Cambio'!$B$11:$B$15,0)),0)} -> 3788.4 | J47: =IFERROR(H47*I47,0) -> 1515360 | K47: =IFERROR(J47/'Tasas de Cambio'!$C$5,0) -> 505120 | M47: 28 ago 2026
A48: Traslados | B48: Italia | C48: 46522.0 | D48: Traslado puerto → Estación Ravenna | E48: EUR | F48: 12 | G48: 3 | H48: =IFERROR(F48*G48,0) -> 36 | I48: {=IFERROR(INDEX('Tasas de Cambio'!$E$11:$E$15,MATCH(E48,'Tasas de Cambio'!$B$11:$B$15,0)),0)} -> 3788.4 | J48: =IFERROR(H48*I48,0) -> 136382.4 | K48: =IFERROR(J48/'Tasas de Cambio'!$C$5,0) -> 45460.8 | M48: 27 ago 2026
A49: Comidas | B49: Rávena (Venecia) | C49: 46522 | D49: Almuerzo y cena | E49: EUR | F49: 30 | G49: 3 | H49: 90 | I49: {=IFERROR(INDEX('Tasas de Cambio'!$E$11:$E$15,MATCH(E49,'Tasas de Cambio'!$B$11:$B$15,0)),0)} -> 3788.4 | J49: 340956 | K49: =IFERROR(J49/'Tasas de Cambio'!$C$5,0) -> 113652
A50: Vuelos y Trenes | B50: Venecia / Bogota | C50: 46523 | D50: Vuelo internacional Venecia → Bogotá (regreso) | E50: COP | F50: 1557040 | G50: 3 | H50: 4671120 | I50: {=IFERROR(INDEX('Tasas de Cambio'!$E$11:$E$15,MATCH(E50,'Tasas de Cambio'!$B$11:$B$15,0)),0)} -> 1 | J50: 4671120 | K50: =IFERROR(J50/'Tasas de Cambio'!$C$5,0) -> 1557040 | L50: Lufthansa, sale dom 16 may 10:55 VCE, llega 18:55 BOG (vía FRA), 15h00m, Economy Light. Total ida+regreso $3.114.080 COP/persona, dividido entre los 2 tramos.
A51: Traslados | B51: Italia | C51: 46523 | D51: Traslado hotel → aeropuerto, Venecia | E51: EUR | F51: 30 | G51: 1 | H51: 30 | I51: {=IFERROR(INDEX('Tasas de Cambio'!$E$11:$E$15,MATCH(E51,'Tasas de Cambio'!$B$11:$B$15,0)),0)} -> 3788.4 | J51: 113652 | K51: =IFERROR(J51/'Tasas de Cambio'!$C$5,0) -> 37884
A52: Tours y Excursiones | B52: Venecia | C52: 15 May 2027 | D52: Free tour Venecia | E52: EUR | F52: 10 | G52: 3 | H52: =IFERROR(F52*G52,0) -> 30 | I52: {=IFERROR(INDEX('Tasas de Cambio'!$E$11:$E$15,MATCH(E52,'Tasas de Cambio'!$B$11:$B$15,0)),0)} -> 3788.4 | J52: =IFERROR(H52*I52,0) -> 113652 | K52: =IFERROR(J52/'Tasas de Cambio'!$C$5,0) -> 37884 | L52: Free tour guiado por el centro histórico de Venecia. https://www.civitatis.com/es/venecia/free-tour-venecia/?_gl=1*1ijxuzi*_up*MQ..*_ga*ODU4MDQyNjAyLjE3ODc4Nzc2ODY.*_ga_QJQ54CTKPM*czE3ODc4Nzc2ODYkbzEkZzEkdDE3ODc4Nzc2OTEkajU1JGwwJGgxNTA2MDA0ODU0 | M52: 27 ago 2026
A53: Comidas | B53: Venecia | C53: 46523.0 | D53: Desayuno | E53: EUR | F53: 12 | G53: 3 | H53: =IFERROR(F53*G53,0) -> 36 | I53: {=IFERROR(INDEX('Tasas de Cambio'!$E$11:$E$15,MATCH(E53,'Tasas de Cambio'!$B$11:$B$15,0)),0)} -> 3788.4 | J53: =IFERROR(H53*I53,0) -> 136382.4 | K53: =IFERROR(J53/'Tasas de Cambio'!$C$5,0) -> 45460.8 | L53: Almuerzo y cena incluidos en el vuelo de regreso (15h, sale 10:55am) | M53: 28 ago 2026
A54: Comidas | B54: — | C54: 30 Abr 2027 | D54: Comidas a bordo | E54: COP | F54: 0 | G54: 1 | H54: =IFERROR(F54*G54,0) -> 0 | I54: {=IFERROR(INDEX('Tasas de Cambio'!$E$11:$E$15,MATCH(E54,'Tasas de Cambio'!$B$11:$B$15,0)),0)} -> 1 | J54: =IFERROR(H54*I54,0) -> 0 | K54: =IFERROR(J54/'Tasas de Cambio'!$C$5,0) -> 0 | L54: Incluidas en el vuelo internacional | M54: 28 ago 2026
D55: TOTAL GENERAL | J55: =SUM(J5:J53) -> 45012581 | K55: =SUM(K5:K53) -> 15004194
A56: Comidas | B56: Navegación | C56: 9 May 2027 | D56: Incluidas en el crucero (come a bordo) | E56: COP | F56: 0 | G56: 1 | H56: =IFERROR(F56*G56,0) -> 0 | I56: {=IFERROR(INDEX('Tasas de Cambio'!$E$11:$E$15,MATCH(E56,'Tasas de Cambio'!$B$11:$B$15,0)),0)} -> 1 | J56: =IFERROR(H56*I56,0) -> 0 | K56: =IFERROR(J56/'Tasas de Cambio'!$C$5,0) -> 0 | M56: 28 ago 2026
A57: Comidas | B57: Navegación | C57: 13 May 2027 | D57: Incluidas en el crucero (come a bordo) | E57: COP | F57: 0 | G57: 1 | H57: =IFERROR(F57*G57,0) -> 0 | I57: {=IFERROR(INDEX('Tasas de Cambio'!$E$11:$E$15,MATCH(E57,'Tasas de Cambio'!$B$11:$B$15,0)),0)} -> 1 | J57: =IFERROR(H57*I57,0) -> 0 | K57: =IFERROR(J57/'Tasas de Cambio'!$C$5,0) -> 0 | M57: 28 ago 2026
A58: Comidas | B58: Zurich | C58: 1 May 2027 | D58: Cena | E58: CHF | F58: 28 | G58: 3 | H58: =IFERROR(F58*G58,0) -> 84 | I58: {=IFERROR(INDEX('Tasas de Cambio'!$E$11:$E$15,MATCH(E58,'Tasas de Cambio'!$B$11:$B$15,0)),0)} -> 4038.3 | J58: =IFERROR(H58*I58,0) -> 339217.2 | K58: =IFERROR(J58/'Tasas de Cambio'!$C$5,0) -> 113072.4 | L58: Cena de llegada | M58: 28 ago 2026

Sheet Resumen CZ
B2: RESUMEN DE COTIZACIÓN — EUROPA 2027
B3: 1 de mayo al 16 de mayo de 2027 · 16 días
B5: TOTAL POR CATEGORÍA
B6: Categoría | C6: Total (COP) | D6: Total (USD) | E6: % del total
B7: Vuelos y Trenes | C7: =SUMIF('Crucero y Zurich'!$A:$A,B7,'Crucero y Zurich'!$J:$J) -> 12637329 | D7: =IFERROR(C7/'Tasas de Cambio'!$E$14,0) -> 3926.7704 | E7: =IFERROR(C7/$C$15,0) -> 0.28075104
B8: Traslados | C8: =SUMIF('Crucero y Zurich'!$A:$A,B8,'Crucero y Zurich'!$J:$J) -> 1606218.6 | D8: =IFERROR(C8/'Tasas de Cambio'!$E$14,0) -> 499.0969 | E8: =IFERROR(C8/$C$15,0) -> 0.03568377
B9: Alojamiento | C9: =SUMIF('Crucero y Zurich'!$A:$A,B9,'Crucero y Zurich'!$J:$J) -> 7098252 | D9: =IFERROR(C9/'Tasas de Cambio'!$E$14,0) -> 2205.6248 | E9: =IFERROR(C9/$C$15,0) -> 0.15769485
B10: Crucero | C10: =SUMIF('Crucero y Zurich'!$A:$A,B10,'Crucero y Zurich'!$J:$J) -> 6468682.5 | D10: =IFERROR(C10/'Tasas de Cambio'!$E$14,0) -> 2010 | E10: =IFERROR(C10/$C$15,0) -> 0.14370832
B11: Tours y Excursiones | C11: =SUMIF('Crucero y Zurich'!$A:$A,B11,'Crucero y Zurich'!$J:$J) -> 9876447 | D11: =IFERROR(C11/'Tasas de Cambio'!$E$14,0) -> 3068.8874 | E11: =IFERROR(C11/$C$15,0) -> 0.21941526
B12: Comidas | C12: =SUMIF('Crucero y Zurich'!$A:$A,B12,'Crucero y Zurich'!$J:$J) -> 4475268 | D12: =IFERROR(C12/'Tasas de Cambio'!$E$14,0) -> 1390.5905 | E12: =IFERROR(C12/$C$15,0) -> 0.099422603
B13: Seguro de Viaje | C13: =SUMIF('Crucero y Zurich'!$A:$A,B13,'Crucero y Zurich'!$J:$J) -> 450000 | D13: =IFERROR(C13/'Tasas de Cambio'!$E$14,0) -> 139.82755 | E13: =IFERROR(C13/$C$15,0) -> 0.009997205
B14: Otros y Extras | C14: =SUMIF('Crucero y Zurich'!$A:$A,B14,'Crucero y Zurich'!$J:$J) -> 2400384 | D14: =IFERROR(C14/'Tasas de Cambio'!$E$14,0) -> 745.86623 | E14: =IFERROR(C14/$C$15,0) -> 0.053326958
B15: TOTAL GENERAL | C15: =SUM(C7:C14) -> 45012581 | D15: =SUM(D7:D14) -> 13986.664
B17: COSTO POR PERSONA
B18: Número de personas | C18: ='Tasas de Cambio'!$C$5 -> 3
B19: Costo por persona (COP) | C19: =IFERROR($C$15/'Tasas de Cambio'!$C$5,0) -> 15004194
B20: Costo por persona (USD) | C20: =IFERROR($D$15/'Tasas de Cambio'!$C$5,0) -> 4662.2213
B21: Costo promedio por persona / día (COP) | C21: =IFERROR(C19/16,0) -> 937762.11
B23: TASAS DE CAMBIO UTILIZADAS
B24: Moneda | C24: Tasa a COP
B25: ='Tasas de Cambio'!$B$11 -> EUR | C25: ='Tasas de Cambio'!$E$11 -> 3750.6
B26: ='Tasas de Cambio'!$B$12 -> CHF | C26: ='Tasas de Cambio'!$E$12 -> 4053
B27: ='Tasas de Cambio'!$B$13 -> CZK | C27: ='Tasas de Cambio'!$E$13 -> 155.82
B28: ='Tasas de Cambio'!$B$14 -> USD | C28: ='Tasas de Cambio'!$E$14 -> 3218.25
B29: ='Tasas de Cambio'!$B$15 -> COP | C29: ='Tasas de Cambio'!$E$15 -> 1
B31: Cifras referenciales — sujetas a disponibilidad, temporada y tasa de cambio del día de pago. Documento generado como herramienta de cotización, no constituye una tarifa garantizada.

Sheet Opción 4 (Múnich)
A2: COTIZACIÓN DETALLADA — EUROPA 2027 (01 May – 16 May 2027) — OPCIÓN 4: MÚNICH en vez de ZÚRICH | O2: Vuelos y Trenes | P2: EUR
O3: Traslados | P3: CHF
A4: Categoría | B4: Ciudad / País | C4: Fechas | D4: Concepto / Descripción | E4: Moneda | F4: Costo Unitario (moneda original) | G4: Cantidad | H4: Costo Total (moneda original) | I4: Tasa de Cambio a COP | J4: Costo Total (COP) | K4: Costo por Persona (COP) | L4: Notas | M4: Fecha confirmación precio | O4: Alojamiento | P4: CZK
A5: Tours y Excursiones | B5: Barcelona | C5: 7 May 2027 | D5: Tour Barcelona Modernista | E5: USD | F5: 10 | G5: 3 | H5: =IFERROR(F5*G5,0) -> 30 | I5: {=IFERROR(INDEX('Tasas de Cambio'!$E$11:$E$15,MATCH(E5,'Tasas de Cambio'!$B$11:$B$15,0)),0)} -> 3263.4 | J5: =IFERROR(H5*I5,0) -> 97902 | K5: =IFERROR(J5/'Tasas de Cambio'!$C$5,0) -> 32634 | L5: Tour guiado por el Modernismo catalán en Barcelona. https://www.civitatis.com/es/barcelona/tour-barcelona-modernista/ | M5: 27 ago 2026
A6: Tours y Excursiones | B6: Barcelona | C6: 7 May 2027 | D6: Free tour Sagrada Familia | E6: USD | F6: 10 | G6: 3 | H6: =IFERROR(F6*G6,0) -> 30 | I6: {=IFERROR(INDEX('Tasas de Cambio'!$E$11:$E$15,MATCH(E6,'Tasas de Cambio'!$B$11:$B$15,0)),0)} -> 3263.4 | J6: =IFERROR(H6*I6,0) -> 97902 | K6: =IFERROR(J6/'Tasas de Cambio'!$C$5,0) -> 32634 | L6: Free tour guiado por el exterior de la Sagrada Familia. https://www.civitatis.com/es/barcelona/free-tour-sagrada-familia/ | M6: 27 ago 2026
A7: Otros y Extras | B7: Navegación | C7: 9 May 2027 | D7: Día de navegación | E7: COP | F7: 0 | G7: 1 | H7: =IFERROR(F7*G7,0) -> 0 | I7: {=IFERROR(INDEX('Tasas de Cambio'!$E$11:$E$15,MATCH(E7,'Tasas de Cambio'!$B$11:$B$15,0)),0)} -> 1 | J7: =IFERROR(H7*I7,0) -> 0 | K7: =IFERROR(J7/'Tasas de Cambio'!$C$5,0) -> 0 | L7: Día de navegación, incluido en la tarifa del crucero. https://www.royalcaribbean.com/lac/es/itinerary/7-night-italy-croatia-cruise-from-barcelona-on-brilliance-BR07M885?sailDate=2027-05-08&packageCode=BR07M885&groupId=BR07BCN-1768961711&country=COL&search=startDate:2027-05-01~2027-05-31 | M7: 27 ago 2026
A8: Otros y Extras | B8: Navegación | C8: 13 May 2027 | D8: Día de navegación | E8: COP | F8: 0 | G8: 1 | H8: =IFERROR(F8*G8,0) -> 0 | I8: {=IFERROR(INDEX('Tasas de Cambio'!$E$11:$E$15,MATCH(E8,'Tasas de Cambio'!$B$11:$B$15,0)),0)} -> 1 | J8: =IFERROR(H8*I8,0) -> 0 | K8: =IFERROR(J8/'Tasas de Cambio'!$C$5,0) -> 0 | L8: Día de navegación, incluido en la tarifa del crucero. https://www.royalcaribbean.com/lac/es/itinerary/7-night-italy-croatia-cruise-from-barcelona-on-brilliance-BR07M885?sailDate=2027-05-08&packageCode=BR07M885&groupId=BR07BCN-1768961711&country=COL&search=startDate:2027-05-01~2027-05-31 | M8: 27 ago 2026
A9: Traslados | B9: Venecia | C9: 15 May 2027 | D9: Vaporetti ACTV | E9: EUR | F9: 25 | G9: 3 | H9: =IFERROR(F9*G9,0) -> 75 | I9: {=IFERROR(INDEX('Tasas de Cambio'!$E$11:$E$15,MATCH(E9,'Tasas de Cambio'!$B$11:$B$15,0)),0)} -> 3788.4 | J9: =IFERROR(H9*I9,0) -> 284130 | K9: =IFERROR(J9/'Tasas de Cambio'!$C$5,0) -> 94710 | L9: Boletos de vaporetto (transporte acuático) por Venecia. https://book.tickets-venice.com/es/book/8748/select/?_gl=1%2A1073ils%2A_gcl_aw%2AR0NMLjE3ODc4NzgwODMuRUFJYUlRb2JDaE1JaFpPNjdZekNsZ01Wd1lSYUJSM2Y1U1JPRUFBWUF5QUFFZ0tjeFBEX0J3RQ..%2A_gcl_au%2ANzIxMTA1MTQ5LjE3ODc4NzgwODMuLS4tLjE3ODc4NzgwODMuMTE2MDU2ODc1MS4xNzg3ODc4MDg0LjE3ODc4NzgwODM.%2A_ga%2ANDcyOTU3MzYyLjE3ODc4NzgwODM.%2A_ga_Y45PC9R73C%2AczE3ODc4NzgwODMkbzEkZzAkdDE3ODc4NzgwODQkajU5JGwwJGgw&cookieBanner=false&date=2027-05-15&tourId=15560&variantId=15560 | M9: 27 ago 2026
A10: Otros y Extras | C10: Durante el viaje | D10: SIM card de viaje (datos internacionales) | E10: USD | F10: 52 | G10: 1 | H10: 52 | I10: {=IFERROR(INDEX('Tasas de Cambio'!$E$11:$E$15,MATCH(E10,'Tasas de Cambio'!$B$11:$B$15,0)),0)} -> 3263.4 | J10: 169696.8 | K10: =IFERROR(J10/'Tasas de Cambio'!$C$5,0) -> 56565.6 | L10: SIM compartida entre las 3 personas para los 16 días del viaje. https://esim.holafly.com/es/esim-europa/?selectedDays=16&startDate=2027-05-01&endDate=2027-05-16 | M10: 27 ago 2026
A11: Otros y Extras | C11: Contingencia | D11: Imprevistos / gastos varios (contingencia) | E11: EUR | F11: 200 | G11: 3 | H11: 600 | I11: {=IFERROR(INDEX('Tasas de Cambio'!$E$11:$E$15,MATCH(E11,'Tasas de Cambio'!$B$11:$B$15,0)),0)} -> 3788.4 | J11: 2273040 | K11: =IFERROR(J11/'Tasas de Cambio'!$C$5,0) -> 757680
A12: Vuelos y Trenes | B12: Bogota / Múnich | C12: 46507 | D12: Vuelo internacional Bogotá → Múnich (ida) | E12: COP | F12: 1435635 | G12: 3 | H12: 4306905 | I12: {=IFERROR(INDEX('Tasas de Cambio'!$E$11:$E$15,MATCH(E12,'Tasas de Cambio'!$B$11:$B$15,0)),0)} -> 1 | J12: 4306905 | K12: =IFERROR(J12/'Tasas de Cambio'!$C$5,0) -> 1435635 | L12: Lufthansa, sale vie 30 abr 23:30 BOG, llega sáb 1 may 20:10 MUC (+1 día, vía FRA, 2h05m), 13h40m total, Economy Light. Total ida+regreso $2.871.270 COP/persona, dividido entre los 2 tramos.
A13: Traslados | B13: Alemania | C13: 46508 | D13: Traslado aeropuerto → hotel, Múnich | E13: EUR | F13: 75 | G13: 1 | H13: 75 | I13: {=IFERROR(INDEX('Tasas de Cambio'!$E$11:$E$15,MATCH(E13,'Tasas de Cambio'!$B$11:$B$15,0)),0)} -> 3788.4 | J13: 284130 | K13: =IFERROR(J13/'Tasas de Cambio'!$C$5,0) -> 94710 | L13: Estimado: Uber X/taxi, aeropuerto MUC → centro, ~45 min, €70-90 (1 carro para el grupo).
A14: Alojamiento | B14: Múnich, Alemania | C14: 1 May – 6 May (5 noches) | D14: Hotel Múnich — costo por noche | E14: EUR | F14: 130 | G14: 5 | H14: =IFERROR(F14*G14,0) -> 650 | I14: {=IFERROR(INDEX('Tasas de Cambio'!$E$11:$E$15,MATCH(E14,'Tasas de Cambio'!$B$11:$B$15,0)),0)} -> 3788.4 | J14: =IFERROR(H14*I14,0) -> 2462460 | K14: =IFERROR(J14/'Tasas de Cambio'!$C$5,0) -> 820820 | L14: Recomendado: Eden Hotel Wolff, cerca de la Estación Central, ~10-15 min a Marienplatz. €130/noche aprox. | M14: 27 ago 2026
A15: Seguro de Viaje | B15: Internacional | C15: 1 – 16 may 2027 (16 días de cobertura) | D15: Asistencia médica internacional | E15: COP | F15: 295980 | G15: 3 | H15: =IFERROR(F15*G15,0) -> 887940 | I15: {=IFERROR(INDEX('Tasas de Cambio'!$E$11:$E$15,MATCH(E15,'Tasas de Cambio'!$B$11:$B$15,0)),0)} -> 1 | J15: =IFERROR(H15*I15,0) -> 887940 | K15: =IFERROR(J15/'Tasas de Cambio'!$C$5,0) -> 295980 | L15: Asistencia médica internacional, cobertura USD 60.000 (Cuponatic). https://www.cuponatic.com.co/descuento/asistencia-medica-internacional-cobertura-de-usd-60-000?m=tarjetas-de-asistencia&id_descuento=212587 | M15: 27 ago 2026
A16: Tours y Excursiones | B16: Múnich | C16: 1 May 2027 | D16: Zugspitze, Eibsee, Highline179 & Neuschwanstein Tour (privado) | E16: COP | F16: 2690900 | G16: 1 | H16: 2690900 | I16: {=IFERROR(INDEX('Tasas de Cambio'!$E$11:$E$15,MATCH(E16,'Tasas de Cambio'!$B$11:$B$15,0)),0)} -> 1 | J16: 2690900 | K16: =IFERROR(J16/'Tasas de Cambio'!$C$5,0) -> 896966.67 | L16: Tour privado 12h, guía en inglés, dom 2 may 8:00am, para el grupo de 3. Incluye Zugspitze, lago Eibsee, puente Highline179 y Castillo de Neuschwanstein. Col$2.690.900 total (3 participantes).
A18: Comidas | B18: Múnich | C18: 46509.0 | D18: Comida del día (desayuno, almuerzo y cena) | E18: EUR | F18: 52 | G18: 3 | H18: =IFERROR(F18*G18,0) -> 156 | I18: {=IFERROR(INDEX('Tasas de Cambio'!$E$11:$E$15,MATCH(E18,'Tasas de Cambio'!$B$11:$B$15,0)),0)} -> 3788.4 | J18: =IFERROR(H18*I18,0) -> 590990.4 | K18: =IFERROR(J18/'Tasas de Cambio'!$C$5,0) -> 196996.8 | L18: Estimado: ~€52/persona/día (desayuno+almuerzo+cena) | M18: 28 ago 2026
A19: Tours y Excursiones | B19: Múnich | C19: 46510 | D19: Excursión de un día a Salzburgo, Austria | E19: EUR | F19: 85 | G19: 3 | H19: 255 | I19: {=IFERROR(INDEX('Tasas de Cambio'!$E$11:$E$15,MATCH(E19,'Tasas de Cambio'!$B$11:$B$15,0)),0)} -> 3788.4 | J19: 966042 | K19: =IFERROR(J19/'Tasas de Cambio'!$C$5,0) -> 322014 | L19: Recomendado: tour guiado en tren, incluye transporte + guía. https://www.getyourguide.com/munich-l26/salzburg-day-trip-from-munich-by-train-t24230/
A20: Comidas | B20: Múnich | C20: 46510.0 | D20: Comida del día (desayuno, almuerzo y cena) | E20: EUR | F20: 52 | G20: 3 | H20: =IFERROR(F20*G20,0) -> 156 | I20: {=IFERROR(INDEX('Tasas de Cambio'!$E$11:$E$15,MATCH(E20,'Tasas de Cambio'!$B$11:$B$15,0)),0)} -> 3788.4 | J20: =IFERROR(H20*I20,0) -> 590990.4 | K20: =IFERROR(J20/'Tasas de Cambio'!$C$5,0) -> 196996.8 | L20: Estimado: ~€52/persona/día (desayuno+almuerzo+cena) | M20: 28 ago 2026
A21: Tours y Excursiones | B21: Múnich | C21: 46511 | D21: Museo BMW + Parque Olímpico | E21: EUR | F21: 25 | G21: 3 | H21: 75 | I21: {=IFERROR(INDEX('Tasas de Cambio'!$E$11:$E$15,MATCH(E21,'Tasas de Cambio'!$B$11:$B$15,0)),0)} -> 3788.4 | J21: 284130 | K21: =IFERROR(J21/'Tasas de Cambio'!$C$5,0) -> 94710 | L21: Recomendado: entrada museo + parque. https://www.getyourguide.com/bmw-museum-l3579/
A22: Comidas | B22: Múnich | C22: 46511.0 | D22: Comida del día (desayuno, almuerzo y cena) | E22: EUR | F22: 52 | G22: 3 | H22: =IFERROR(F22*G22,0) -> 156 | I22: {=IFERROR(INDEX('Tasas de Cambio'!$E$11:$E$15,MATCH(E22,'Tasas de Cambio'!$B$11:$B$15,0)),0)} -> 3788.4 | J22: =IFERROR(H22*I22,0) -> 590990.4 | K22: =IFERROR(J22/'Tasas de Cambio'!$C$5,0) -> 196996.8 | L22: Estimado: ~€52/persona/día (desayuno+almuerzo+cena) | M22: 28 ago 2026
A23: Comidas | B23: Múnich | C23: 46512.0 | D23: Comida del día (desayuno, almuerzo y cena) | E23: EUR | F23: 52 | G23: 3 | H23: =IFERROR(F23*G23,0) -> 156 | I23: {=IFERROR(INDEX('Tasas de Cambio'!$E$11:$E$15,MATCH(E23,'Tasas de Cambio'!$B$11:$B$15,0)),0)} -> 3788.4 | J23: =IFERROR(H23*I23,0) -> 590990.4 | K23: =IFERROR(J23/'Tasas de Cambio'!$C$5,0) -> 196996.8 | L23: Estimado: ~€52/persona/día (desayuno+almuerzo+cena) | M23: 28 ago 2026
A24: Alojamiento | B24: Barcelona, España | C24: 6 – 8 May (2 noches, pre-crucero) | D24: Hotel Barcelona — costo total (2 noches) | E24: COP | F24: 1900000 | G24: 1 | H24: =IFERROR(F24*G24,0) -> 1900000 | I24: {=IFERROR(INDEX('Tasas de Cambio'!$E$11:$E$15,MATCH(E24,'Tasas de Cambio'!$B$11:$B$15,0)),0)} -> 1 | J24: =IFERROR(H24*I24,0) -> 1900000 | K24: =IFERROR(J24/'Tasas de Cambio'!$C$5,0) -> 633333.33 | L24: Sagrada Familia, 2 noches (6-8 may). https://www.booking.com/hotel/es/sagradafamilia.es.html?aid=2311236&label=es-co-booking-desktop-vjGZbEFOhRc3a9njxeT3IwS652829002024%3Apl%3Ata%3Ap1%3Ap2%3Aac%3Aap%3Aneg%3Afi%3Atikwd-65526620%3Alp9246960%3Ali%3Adec%3Adm&sid=f6a1a9bb810c453f7b5f1225205f1f26&all_sr_blocks=9118812_91908190_0_2_0&checkin=2027-05-06&checkout=2027-05-08&dest_id=-372490&dest_type=city&dist=0&group_adults=3&group_children=0&hapos=1&highlighted_blocks=9118812_91908190_0_2_0&hpos=1&matching_block_id=9118812_91908190_0_2_0&no_rooms=1&req_adults=3&req_children=0&room1=A%2CA%2CA&sb_price_type=total&sr_order=popularity&sr_pri_blocks=9118812_91908190_0_2_0__37600&srepoch=1787875557&srpvid=a2d600b07c230149&type=total&ucfs=1 | M24: 27 ago 2026
A25: Vuelos y Trenes | B25: Múnich / Barcelona | C25: 46513 | D25: Vuelo Múnich → Barcelona, directo | E25: EUR | F25: 156.97 | G25: 3 | H25: 470.91 | I25: {=IFERROR(INDEX('Tasas de Cambio'!$E$11:$E$15,MATCH(E25,'Tasas de Cambio'!$B$11:$B$15,0)),0)} -> 3788.4 | J25: 1783995.4 | K25: =IFERROR(J25/'Tasas de Cambio'!$C$5,0) -> 594665.15 | L25: Lufthansa City Airlines, jue 6 may 06:15 MUC → 08:25 BCN, directo, 2h10m, Economy Basic. Asumido por persona (confirmar si es total).
A26: Traslados | B26: Alemania | C26: 46513 | D26: Traslado hotel → aeropuerto, Múnich | E26: EUR | F26: 75 | G26: 1 | H26: 75 | I26: {=IFERROR(INDEX('Tasas de Cambio'!$E$11:$E$15,MATCH(E26,'Tasas de Cambio'!$B$11:$B$15,0)),0)} -> 3788.4 | J26: 284130 | K26: =IFERROR(J26/'Tasas de Cambio'!$C$5,0) -> 94710 | L26: Estimado: Uber X/taxi, centro → aeropuerto MUC, ~45 min, €70-90 (1 carro para el grupo).
A27: Traslados | B27: España | C27: 46513.0 | D27: Traslado aeropuerto → hotel, Barcelona | E27: EUR | F27: 40 | G27: 1 | H27: =IFERROR(F27*G27,0) -> 40 | I27: {=IFERROR(INDEX('Tasas de Cambio'!$E$11:$E$15,MATCH(E27,'Tasas de Cambio'!$B$11:$B$15,0)),0)} -> 3788.4 | J27: =IFERROR(H27*I27,0) -> 151536 | K27: =IFERROR(J27/'Tasas de Cambio'!$C$5,0) -> 50512 | M27: 27 ago 2026
A28: Comidas | B28: Barcelona | C28: 46513 | D28: cena | E28: EUR | F28: 15 | G28: 3 | H28: 45 | I28: {=IFERROR(INDEX('Tasas de Cambio'!$E$11:$E$15,MATCH(E28,'Tasas de Cambio'!$B$11:$B$15,0)),0)} -> 3788.4 | J28: 170478 | K28: =IFERROR(J28/'Tasas de Cambio'!$C$5,0) -> 56826
A29: Vuelos y Trenes | B29: Italia | C29: 15 May 2027 | D29: Tren Ravenna - Venecia St Lucia | E29: EUR | F29: 25 | G29: 3 | H29: =IFERROR(F29*G29,0) -> 75 | I29: {=IFERROR(INDEX('Tasas de Cambio'!$E$11:$E$15,MATCH(E29,'Tasas de Cambio'!$B$11:$B$15,0)),0)} -> 3788.4 | J29: =IFERROR(H29*I29,0) -> 284130 | K29: =IFERROR(J29/'Tasas de Cambio'!$C$5,0) -> 94710 | L29: Tren regional desde Ravenna hasta Venecia Santa Lucia. https://www.trenitalia.com/en.html | M29: 27 ago 2026
A30: Comidas | B30: Barcelona | C30: 46514 | D30: 3 comidas | E30: EUR | F30: 30 | G30: 3 | H30: 90 | I30: {=IFERROR(INDEX('Tasas de Cambio'!$E$11:$E$15,MATCH(E30,'Tasas de Cambio'!$B$11:$B$15,0)),0)} -> 3788.4 | J30: 340956 | K30: =IFERROR(J30/'Tasas de Cambio'!$C$5,0) -> 113652
A31: Traslados | B31: Barcelona | C31: 46514.0 | D31: Bus, 4 trayectos | E31: EUR | F31: 12 | G31: 3 | H31: =IFERROR(F31*G31,0) -> 36 | I31: {=IFERROR(INDEX('Tasas de Cambio'!$E$11:$E$15,MATCH(E31,'Tasas de Cambio'!$B$11:$B$15,0)),0)} -> 3788.4 | J31: =IFERROR(H31*I31,0) -> 136382.4 | K31: =IFERROR(J31/'Tasas de Cambio'!$C$5,0) -> 45460.8 | M31: 27 ago 2026
A32: Crucero | B32: Mediterráneo | C32: 8 – 15 May (7 noches) | D32: Crucero Barcelona → Ravena — tarifa por persona (cabina) | E32: USD | F32: 670 | G32: 3 | H32: =IFERROR(F32*G32,0) -> 2010 | I32: {=IFERROR(INDEX('Tasas de Cambio'!$E$11:$E$15,MATCH(E32,'Tasas de Cambio'!$B$11:$B$15,0)),0)} -> 3263.4 | J32: =IFERROR(H32*I32,0) -> 6559434 | K32: =IFERROR(J32/'Tasas de Cambio'!$C$5,0) -> 2186478 | L32: Crucero Barcelona-Ravena, 7 noches, incluye propinas. https://www.royalcaribbean.com/lac/es/itinerary/7-night-italy-croatia-cruise-from-barcelona-on-brilliance-BR07M885?sailDate=2027-05-08&packageCode=BR07M885&groupId=BR07BCN-1768961711&country=COL&search=startDate:2027-05-01~2027-05-31 | M32: 27 ago 2026
A33: Traslados | B33: España | C33: 46515 | D33: Traslado hotel → puerto (embarque crucero), Barcelona | E33: EUR | F33: 30 | G33: 1 | H33: 30 | I33: {=IFERROR(INDEX('Tasas de Cambio'!$E$11:$E$15,MATCH(E33,'Tasas de Cambio'!$B$11:$B$15,0)),0)} -> 3788.4 | J33: 113652 | K33: =IFERROR(J33/'Tasas de Cambio'!$C$5,0) -> 37884
A34: Tours y Excursiones | B34: Barcelona | C34: 46515 | D34: N/A | E34: EUR | F34: 0 | G34: 3 | H34: 0 | I34: {=IFERROR(INDEX('Tasas de Cambio'!$E$11:$E$15,MATCH(E34,'Tasas de Cambio'!$B$11:$B$15,0)),0)} -> 3788.4 | J34: 0 | K34: =IFERROR(J34/'Tasas de Cambio'!$C$5,0) -> 0
A35: Comidas | B35: Barcelona | C35: 46515 | D35: desayuno | E35: EUR | F35: 10 | G35: 3 | H35: 30 | I35: {=IFERROR(INDEX('Tasas de Cambio'!$E$11:$E$15,MATCH(E35,'Tasas de Cambio'!$B$11:$B$15,0)),0)} -> 3788.4 | J35: 113652 | K35: =IFERROR(J35/'Tasas de Cambio'!$C$5,0) -> 37884
A36: Tours y Excursiones | B36: Navegacion | C36: 46516 | D36: N/A | E36: EUR | F36: 0 | G36: 3 | H36: 0 | I36: {=IFERROR(INDEX('Tasas de Cambio'!$E$11:$E$15,MATCH(E36,'Tasas de Cambio'!$B$11:$B$15,0)),0)} -> 3788.4 | J36: 0 | K36: =IFERROR(J36/'Tasas de Cambio'!$C$5,0) -> 0
A37: Tours y Excursiones | B37: La Spezia (Florencia/Pisa) | C37: 46517.0 | D37: Panoramic Pisa | E37: USD | F37: 70 | G37: 3 | H37: =IFERROR(F37*G37,0) -> 210 | I37: {=IFERROR(INDEX('Tasas de Cambio'!$E$11:$E$15,MATCH(E37,'Tasas de Cambio'!$B$11:$B$15,0)),0)} -> 3263.4 | J37: =IFERROR(H37*I37,0) -> 685314 | K37: =IFERROR(J37/'Tasas de Cambio'!$C$5,0) -> 228438 | L37: Excursión panorámica por Pisa desde el crucero. https://www.royalcaribbean.com/account/cruise-planner/category/shorex/product/Y8RO?bookingId=3113096&shipCode=BR&sailDate=20270508 | M37: 27 ago 2026
A38: Comidas | B38: La Spezia (Florencia/Pisa) | C38: 46517.0 | D38: Almuerzo en tierra | E38: EUR | F38: 25 | G38: 3 | H38: =IFERROR(F38*G38,0) -> 75 | I38: {=IFERROR(INDEX('Tasas de Cambio'!$E$11:$E$15,MATCH(E38,'Tasas de Cambio'!$B$11:$B$15,0)),0)} -> 3788.4 | J38: =IFERROR(H38*I38,0) -> 284130 | K38: =IFERROR(J38/'Tasas de Cambio'!$C$5,0) -> 94710 | L38: Desayuno y cena incluidos en el crucero, almuerzo en Pisa/Florencia | M38: 28 ago 2026
A39: Tours y Excursiones | B39: Civitavecchia (Roma) | C39: 46518.0 | D39: Visit to Rome | E39: USD | F39: 142 | G39: 3 | H39: =IFERROR(F39*G39,0) -> 426 | I39: {=IFERROR(INDEX('Tasas de Cambio'!$E$11:$E$15,MATCH(E39,'Tasas de Cambio'!$B$11:$B$15,0)),0)} -> 3263.4 | J39: =IFERROR(H39*I39,0) -> 1390208.4 | K39: =IFERROR(J39/'Tasas de Cambio'!$C$5,0) -> 463402.8 | L39: Excursión a Roma desde el crucero. https://www.royalcaribbean.com/account/cruise-planner/category/shorex/product/CV1F?bookingId=3113096&shipCode=BR&sailDate=20270508 | M39: 29 ago 2026
A40: Comidas | B40: Civitavecchia (Roma) | C40: 46518.0 | D40: Almuerzo en tierra | E40: EUR | F40: 25 | G40: 3 | H40: =IFERROR(F40*G40,0) -> 75 | I40: {=IFERROR(INDEX('Tasas de Cambio'!$E$11:$E$15,MATCH(E40,'Tasas de Cambio'!$B$11:$B$15,0)),0)} -> 3788.4 | J40: =IFERROR(H40*I40,0) -> 284130 | K40: =IFERROR(J40/'Tasas de Cambio'!$C$5,0) -> 94710 | L40: Desayuno y cena incluidos en el crucero, almuerzo en Roma | M40: 28 ago 2026
A41: Tours y Excursiones | B41: Salerno (Costa Amalfitana) | C41: 46519.0 | D41: Tour a pie gratis | E41: EUR | F41: 0 | G41: 3 | H41: =IFERROR(F41*G41,0) -> 0 | I41: {=IFERROR(INDEX('Tasas de Cambio'!$E$11:$E$15,MATCH(E41,'Tasas de Cambio'!$B$11:$B$15,0)),0)} -> 3788.4 | J41: =IFERROR(H41*I41,0) -> 0 | K41: =IFERROR(J41/'Tasas de Cambio'!$C$5,0) -> 0 | M41: 27 ago 2026
A42: Comidas | B42: Salerno (Costa Amalfitana) | C42: 46519.0 | D42: Incluida en el crucero (come a bordo) | E42: EUR | F42: 0 | G42: 3 | H42: =IFERROR(F42*G42,0) -> 0 | I42: {=IFERROR(INDEX('Tasas de Cambio'!$E$11:$E$15,MATCH(E42,'Tasas de Cambio'!$B$11:$B$15,0)),0)} -> 3788.4 | J42: =IFERROR(H42*I42,0) -> 0 | K42: =IFERROR(J42/'Tasas de Cambio'!$C$5,0) -> 0 | L42: Comida incluida en el paquete del crucero, sin costo adicional | M42: 27 ago 2026
A43: Tours y Excursiones | B43: Navegacion | C43: 46520 | D43: N/A | E43: CZK | F43: 0 | G43: 3 | H43: 0 | I43: {=IFERROR(INDEX('Tasas de Cambio'!$E$11:$E$15,MATCH(E43,'Tasas de Cambio'!$B$11:$B$15,0)),0)} -> 156.97 | J43: 0 | K43: =IFERROR(J43/'Tasas de Cambio'!$C$5,0) -> 0
A44: Traslados | B44: Zadar, Croacia | C44: 46521 | D44: Transporte - Tour a pie gratis | E44: EUR | F44: 10 | G44: 3 | H44: 30 | I44: {=IFERROR(INDEX('Tasas de Cambio'!$E$11:$E$15,MATCH(E44,'Tasas de Cambio'!$B$11:$B$15,0)),0)} -> 3788.4 | J44: 113652 | K44: =IFERROR(J44/'Tasas de Cambio'!$C$5,0) -> 37884
A45: Comidas | B45: Zadar, Croacia | C45: 46521.0 | D45: Incluida en el crucero (come a bordo) | E45: EUR | F45: 0 | G45: 3 | H45: =IFERROR(F45*G45,0) -> 0 | I45: {=IFERROR(INDEX('Tasas de Cambio'!$E$11:$E$15,MATCH(E45,'Tasas de Cambio'!$B$11:$B$15,0)),0)} -> 3788.4 | J45: =IFERROR(H45*I45,0) -> 0 | K45: =IFERROR(J45/'Tasas de Cambio'!$C$5,0) -> 0 | L45: Comida incluida en el paquete del crucero, sin costo adicional | M45: 27 ago 2026
A46: Alojamiento | B46: Venecia, Italia | C46: 15 – 16 May (1 noche, post-crucero) | D46: Hotel Venecia — costo total (1 noche) | E46: EUR | F46: 400 | G46: 1 | H46: =IFERROR(F46*G46,0) -> 400 | I46: {=IFERROR(INDEX('Tasas de Cambio'!$E$11:$E$15,MATCH(E46,'Tasas de Cambio'!$B$11:$B$15,0)),0)} -> 3788.4 | J46: =IFERROR(H46*I46,0) -> 1515360 | K46: =IFERROR(J46/'Tasas de Cambio'!$C$5,0) -> 505120 | M46: 28 ago 2026
A47: Traslados | B47: Italia | C47: 46522.0 | D47: Traslado puerto → Estación Ravenna | E47: EUR | F47: 12 | G47: 3 | H47: =IFERROR(F47*G47,0) -> 36 | I47: {=IFERROR(INDEX('Tasas de Cambio'!$E$11:$E$15,MATCH(E47,'Tasas de Cambio'!$B$11:$B$15,0)),0)} -> 3788.4 | J47: =IFERROR(H47*I47,0) -> 136382.4 | K47: =IFERROR(J47/'Tasas de Cambio'!$C$5,0) -> 45460.8 | M47: 27 ago 2026
A48: Comidas | B48: Rávena (Venecia) | C48: 46522 | D48: Almuerzo y cena | E48: EUR | F48: 30 | G48: 3 | H48: 90 | I48: {=IFERROR(INDEX('Tasas de Cambio'!$E$11:$E$15,MATCH(E48,'Tasas de Cambio'!$B$11:$B$15,0)),0)} -> 3788.4 | J48: 340956 | K48: =IFERROR(J48/'Tasas de Cambio'!$C$5,0) -> 113652
A49: Vuelos y Trenes | B49: Venecia / Bogota | C49: 46523 | D49: Vuelo internacional Venecia → Bogotá (regreso) | E49: COP | F49: 1435635 | G49: 3 | H49: 4306905 | I49: {=IFERROR(INDEX('Tasas de Cambio'!$E$11:$E$15,MATCH(E49,'Tasas de Cambio'!$B$11:$B$15,0)),0)} -> 1 | J49: 4306905 | K49: =IFERROR(J49/'Tasas de Cambio'!$C$5,0) -> 1435635 | L49: Lufthansa, sale dom 16 may 10:55 VCE, llega 18:55 BOG (vía FRA, 2h20m), 15h00m total, Economy Light. Total ida+regreso $2.871.270 COP/persona, dividido entre los 2 tramos.
A50: Traslados | B50: Italia | C50: 46523 | D50: Traslado hotel → aeropuerto, Venecia | E50: EUR | F50: 30 | G50: 1 | H50: 30 | I50: {=IFERROR(INDEX('Tasas de Cambio'!$E$11:$E$15,MATCH(E50,'Tasas de Cambio'!$B$11:$B$15,0)),0)} -> 3788.4 | J50: 113652 | K50: =IFERROR(J50/'Tasas de Cambio'!$C$5,0) -> 37884
A51: Tours y Excursiones | B51: Venecia | C51: 15 May 2027 | D51: Free tour Venecia | E51: EUR | F51: 10 | G51: 3 | H51: =IFERROR(F51*G51,0) -> 30 | I51: {=IFERROR(INDEX('Tasas de Cambio'!$E$11:$E$15,MATCH(E51,'Tasas de Cambio'!$B$11:$B$15,0)),0)} -> 3788.4 | J51: =IFERROR(H51*I51,0) -> 113652 | K51: =IFERROR(J51/'Tasas de Cambio'!$C$5,0) -> 37884 | L51: Free tour guiado por el centro histórico de Venecia. https://www.civitatis.com/es/venecia/free-tour-venecia/?_gl=1*1ijxuzi*_up*MQ..*_ga*ODU4MDQyNjAyLjE3ODc4Nzc2ODY.*_ga_QJQ54CTKPM*czE3ODc4Nzc2ODYkbzEkZzEkdDE3ODc4Nzc2OTEkajU1JGwwJGgxNTA2MDA0ODU0 | M51: 27 ago 2026
A52: Comidas | B52: Venecia | C52: 46523.0 | D52: Desayuno | E52: EUR | F52: 12 | G52: 3 | H52: =IFERROR(F52*G52,0) -> 36 | I52: {=IFERROR(INDEX('Tasas de Cambio'!$E$11:$E$15,MATCH(E52,'Tasas de Cambio'!$B$11:$B$15,0)),0)} -> 3788.4 | J52: =IFERROR(H52*I52,0) -> 136382.4 | K52: =IFERROR(J52/'Tasas de Cambio'!$C$5,0) -> 45460.8 | L52: Almuerzo y cena incluidos en el vuelo de regreso (15h, sale 10:55am) | M52: 28 ago 2026
A53: Comidas | B53: — | C53: 30 Abr 2027 | D53: Comidas a bordo | E53: COP | F53: 0 | G53: 1 | H53: =IFERROR(F53*G53,0) -> 0 | I53: {=IFERROR(INDEX('Tasas de Cambio'!$E$11:$E$15,MATCH(E53,'Tasas de Cambio'!$B$11:$B$15,0)),0)} -> 1 | J53: =IFERROR(H53*I53,0) -> 0 | K53: =IFERROR(J53/'Tasas de Cambio'!$C$5,0) -> 0 | L53: Incluidas en el vuelo internacional | M53: 28 ago 2026
D54: TOTAL GENERAL | J54: =SUM(J5:J52) -> 37314742 | K54: =SUM(K5:K52) -> 12438247
A55: Comidas | B55: Navegación | C55: 9 May 2027 | D55: Incluidas en el crucero (come a bordo) | E55: COP | F55: 0 | G55: 1 | H55: =IFERROR(F55*G55,0) -> 0 | I55: {=IFERROR(INDEX('Tasas de Cambio'!$E$11:$E$15,MATCH(E55,'Tasas de Cambio'!$B$11:$B$15,0)),0)} -> 1 | J55: =IFERROR(H55*I55,0) -> 0 | K55: =IFERROR(J55/'Tasas de Cambio'!$C$5,0) -> 0 | M55: 28 ago 2026
A56: Comidas | B56: Navegación | C56: 13 May 2027 | D56: Incluidas en el crucero (come a bordo) | E56: COP | F56: 0 | G56: 1 | H56: =IFERROR(F56*G56,0) -> 0 | I56: {=IFERROR(INDEX('Tasas de Cambio'!$E$11:$E$15,MATCH(E56,'Tasas de Cambio'!$B$11:$B$15,0)),0)} -> 1 | J56: =IFERROR(H56*I56,0) -> 0 | K56: =IFERROR(J56/'Tasas de Cambio'!$C$5,0) -> 0 | M56: 28 ago 2026
A57: Comidas | B57: Múnich | C57: 1 May 2027 | D57: Cena | E57: EUR | F57: 20 | G57: 3 | H57: =IFERROR(F57*G57,0) -> 60 | I57: {=IFERROR(INDEX('Tasas de Cambio'!$E$11:$E$15,MATCH(E57,'Tasas de Cambio'!$B$11:$B$15,0)),0)} -> 3788.4 | J57: =IFERROR(H57*I57,0) -> 227304 | K57: =IFERROR(J57/'Tasas de Cambio'!$C$5,0) -> 75768 | L57: Cena de llegada | M57: 28 ago 2026
A58: Tours y Excursiones | B58: Múnich | C58: 2 May 2027 | D58: Tour a Zugspitze, Eibsee, Highline179 y Neuschwanstein | E58: COP | F58: 2752900 | G58: 1 | H58: =IFERROR(F58*G58,0) -> 2752900 | I58: {=IFERROR(INDEX('Tasas de Cambio'!$E$11:$E$15,MATCH(E58,'Tasas de Cambio'!$B$11:$B$15,0)),0)} -> 1 | J58: =IFERROR(H58*I58,0) -> 2752900 | K58: =IFERROR(J58/'Tasas de Cambio'!$C$5,0) -> 917633.33 | L58: Excursión de día completo a los Alpes bávaros desde Múnich. https://www.getyourguide.com/munich-l26/tour-a-zugspitze-eibsee-highline179-y-neuschwanstein-t1320693/ | M58: 30 ago 2026

Sheet Resumen Opción 4
B2: RESUMEN DE COTIZACIÓN — EUROPA 2027
B3: 1 de mayo al 16 de mayo de 2027 · 16 días (Opción Múnich en vez de Zúrich)
B5: TOTAL POR CATEGORÍA
B6: Categoría | C6: Total (COP) | D6: Total (USD) | E6: % del total
B7: Vuelos y Trenes | C7: =SUMIF('Opción 4 (Múnich)'!$A:$A,B7,'Opción 4 (Múnich)'!$J:$J) -> 10380005 | D7: =IFERROR(C7/'Tasas de Cambio'!$E$14,0) -> 3225.357 | E7: =IFERROR(C7/$C$15,0) -> 0.27817438
B8: Traslados | C8: =SUMIF('Opción 4 (Múnich)'!$A:$A,B8,'Opción 4 (Múnich)'!$J:$J) -> 1804038.6 | D8: =IFERROR(C8/'Tasas de Cambio'!$E$14,0) -> 560.56509 | E8: =IFERROR(C8/$C$15,0) -> 0.048346538
B9: Alojamiento | C9: =SUMIF('Opción 4 (Múnich)'!$A:$A,B9,'Opción 4 (Múnich)'!$J:$J) -> 5888442 | D9: =IFERROR(C9/'Tasas de Cambio'!$E$14,0) -> 1829.7031 | E9: =IFERROR(C9/$C$15,0) -> 0.15780471
B10: Crucero | C10: =SUMIF('Opción 4 (Múnich)'!$A:$A,B10,'Opción 4 (Múnich)'!$J:$J) -> 6468682.5 | D10: =IFERROR(C10/'Tasas de Cambio'!$E$14,0) -> 2010 | E10: =IFERROR(C10/$C$15,0) -> 0.17335461
B11: Tours y Excursiones | C11: =SUMIF('Opción 4 (Múnich)'!$A:$A,B11,'Opción 4 (Múnich)'!$J:$J) -> 6322613.8 | D11: =IFERROR(C11/'Tasas de Cambio'!$E$14,0) -> 1964.6124 | E11: =IFERROR(C11/$C$15,0) -> 0.1694401
B12: Comidas | C12: =SUMIF('Opción 4 (Múnich)'!$A:$A,B12,'Opción 4 (Múnich)'!$J:$J) -> 3600576 | D12: =IFERROR(C12/'Tasas de Cambio'!$E$14,0) -> 1118.7993 | E12: =IFERROR(C12/$C$15,0) -> 0.096492052
B13: Seguro de Viaje | C13: =SUMIF('Opción 4 (Múnich)'!$A:$A,B13,'Opción 4 (Múnich)'!$J:$J) -> 450000 | D13: =IFERROR(C13/'Tasas de Cambio'!$E$14,0) -> 139.82755 | E13: =IFERROR(C13/$C$15,0) -> 0.012059577
B14: Otros y Extras | C14: =SUMIF('Opción 4 (Múnich)'!$A:$A,B14,'Opción 4 (Múnich)'!$J:$J) -> 2400384 | D14: =IFERROR(C14/'Tasas de Cambio'!$E$14,0) -> 745.86623 | E14: =IFERROR(C14/$C$15,0) -> 0.064328034
B15: TOTAL GENERAL | C15: =SUM(C7:C14) -> 37314742 | D15: =SUM(D7:D14) -> 11594.731
B17: COSTO POR PERSONA
B18: Número de personas | C18: ='Tasas de Cambio'!$C$5 -> 3
B19: Costo por persona (COP) | C19: =IFERROR($C$15/'Tasas de Cambio'!$C$5,0) -> 12438247
B20: Costo por persona (USD) | C20: =IFERROR($D$15/'Tasas de Cambio'!$C$5,0) -> 3864.9102
B21: Costo promedio por persona / día (COP) | C21: =IFERROR(C19/16,0) -> 777390.46
B23: TASAS DE CAMBIO UTILIZADAS
B24: Moneda | C24: Tasa a COP
B25: ='Tasas de Cambio'!$B$11 -> EUR | C25: ='Tasas de Cambio'!$E$11 -> 3750.6
B26: ='Tasas de Cambio'!$B$12 -> CHF | C26: ='Tasas de Cambio'!$E$12 -> 4053
B27: ='Tasas de Cambio'!$B$13 -> CZK | C27: ='Tasas de Cambio'!$E$13 -> 155.82
B28: ='Tasas de Cambio'!$B$14 -> USD | C28: ='Tasas de Cambio'!$E$14 -> 3218.25
B29: ='Tasas de Cambio'!$B$15 -> COP | C29: ='Tasas de Cambio'!$E$15 -> 1
B31: Cifras referenciales — sujetas a disponibilidad, temporada y tasa de cambio del día de pago. Documento generado como herramienta de cotización, no constituye una tarifa garantizada.

Sheet Crucero
A2: COTIZACIÓN DETALLADA — EUROPA 2027 (05 May – 16 May 2027) | O2: Vuelos y Trenes | P2: EUR
O3: Traslados | P3: CHF
A4: Categoría | B4: Ciudad / País | C4: Fechas | D4: Concepto / Descripción | E4: Moneda | F4: Costo Unitario (moneda original) | G4: Cantidad | H4: Costo Total (moneda original) | I4: Tasa de Cambio a COP | J4: Costo Total (COP) | K4: Costo por Persona (COP) | L4: Notas | M4: Fecha confirmación precio | O4: Alojamiento | P4: CZK
A5: Otros y Extras | B5: — | C5: Durante el viaje | D5: SIM card de viaje (datos internacionales) | E5: USD | F5: 40 | G5: 1 | H5: =IFERROR(F5*G5,0) -> 40 | I5: {=IFERROR(INDEX('Tasas de Cambio'!$E$11:$E$15,MATCH(E5,'Tasas de Cambio'!$B$11:$B$15,0)),0)} -> 3263.4 | J5: =IFERROR(H5*I5,0) -> 130536 | K5: =IFERROR(J5/'Tasas de Cambio'!$C$5,0) -> 43512 | L5: SIM compartida entre las 3 personas para los 11 días del crucero. https://esim.holafly.com/es/esim-europa/?selectedDays=11&startDate=2027-05-06&endDate=2027-05-16 | M5: 27 ago 2026 | O5: Crucero | P5: USD
A6: Otros y Extras | B6: — | C6: Contingencia | D6: Imprevistos / gastos varios (contingencia) | E6: EUR | F6: 200 | G6: 3 | H6: =IFERROR(F6*G6,0) -> 600 | I6: {=IFERROR(INDEX('Tasas de Cambio'!$E$11:$E$15,MATCH(E6,'Tasas de Cambio'!$B$11:$B$15,0)),0)} -> 3788.4 | J6: =IFERROR(H6*I6,0) -> 2273040 | K6: =IFERROR(J6/'Tasas de Cambio'!$C$5,0) -> 757680 | O6: Tours y Excursiones | P6: COP
A7: Seguro de Viaje | B7: Internacional | C7: 5 – 16 may 2027 (12 días de cobertura) | D7: Asistencia médica internacional | E7: COP | F7: 221985 | G7: 3 | H7: =IFERROR(F7*G7,0) -> 665955 | I7: {=IFERROR(INDEX('Tasas de Cambio'!$E$11:$E$15,MATCH(E7,'Tasas de Cambio'!$B$11:$B$15,0)),0)} -> 1 | J7: =IFERROR(H7*I7,0) -> 665955 | K7: =IFERROR(J7/'Tasas de Cambio'!$C$5,0) -> 221985 | L7: Asistencia médica internacional, cobertura USD 60.000 (Cuponatic). https://www.cuponatic.com.co/descuento/asistencia-medica-internacional-cobertura-de-usd-60-000?m=tarjetas-de-asistencia&id_descuento=212587 | M7: 27 ago 2026
A8: Vuelos y Trenes | B8: Bogota / Barcelona | C8: 46512 | D8: Vuelo Lufthansa Bogotá → Barcelona (vía FRA), ida | E8: COP | F8: 1491070 | G8: 3 | H8: =IFERROR(F8*G8,0) -> 4473210 | I8: {=IFERROR(INDEX('Tasas de Cambio'!$E$11:$E$15,MATCH(E8,'Tasas de Cambio'!$B$11:$B$15,0)),0)} -> 1 | J8: =IFERROR(H8*I8,0) -> 4473210 | K8: =IFERROR(J8/'Tasas de Cambio'!$C$5,0) -> 1491070 | L8: Lufthansa · BOG 23:30 → BCN 23:05 (+1 día) · 1 escala (FRA) · Duración 16h35m · Economy Light. https://shop.lufthansa.com/booking/cart?cartId=1EA66RSYEOGDFEB1&type=cart&shared=true&origin=BOG&utm_source=sharedcart&utm_medium=referral&consent=true | M8: 27 ago 2026
A9: Alojamiento | B9: Barcelona, España | C9: 6 – 8 May (2 noches, pre-crucero) | D9: Hotel Barcelona — costo total (2 noches) | E9: COP | F9: 1900000 | G9: 1 | H9: =IFERROR(F9*G9,0) -> 1900000 | I9: {=IFERROR(INDEX('Tasas de Cambio'!$E$11:$E$15,MATCH(E9,'Tasas de Cambio'!$B$11:$B$15,0)),0)} -> 1 | J9: =IFERROR(H9*I9,0) -> 1900000 | K9: =IFERROR(J9/'Tasas de Cambio'!$C$5,0) -> 633333.33 | L9: Sagrada Familia, 2 noches (6-8 may). https://www.booking.com/hotel/es/sagradafamilia.es.html?aid=2311236&label=es-co-booking-desktop-vjGZbEFOhRc3a9njxeT3IwS652829002024%3Apl%3Ata%3Ap1%3Ap2%3Aac%3Aap%3Aneg%3Afi%3Atikwd-65526620%3Alp9246960%3Ali%3Adec%3Adm&sid=f6a1a9bb810c453f7b5f1225205f1f26&all_sr_blocks=9118812_91908190_0_2_0&checkin=2027-05-06&checkout=2027-05-08&dest_id=-372490&dest_type=city&dist=0&group_adults=3&group_children=0&hapos=1&highlighted_blocks=9118812_91908190_0_2_0&hpos=1&matching_block_id=9118812_91908190_0_2_0&no_rooms=1&req_adults=3&req_children=0&room1=A%2CA%2CA&sb_price_type=total&sr_order=popularity&sr_pri_blocks=9118812_91908190_0_2_0__37600&srepoch=1787875557&srpvid=a2d600b07c230149&type=total&ucfs=1 | M9: 27 ago 2026
A10: Traslados | B10: España | C10: 46513.0 | D10: Traslado aeropuerto → hotel, Barcelona | E10: EUR | F10: 40 | G10: 1 | H10: =IFERROR(F10*G10,0) -> 40 | I10: {=IFERROR(INDEX('Tasas de Cambio'!$E$11:$E$15,MATCH(E10,'Tasas de Cambio'!$B$11:$B$15,0)),0)} -> 3788.4 | J10: =IFERROR(H10*I10,0) -> 151536 | K10: =IFERROR(J10/'Tasas de Cambio'!$C$5,0) -> 50512 | M10: 27 ago 2026
A11: Comidas | B11: Barcelona | C11: 46513 | D11: cena | E11: EUR | F11: 15 | G11: 3 | H11: =IFERROR(F11*G11,0) -> 45 | I11: {=IFERROR(INDEX('Tasas de Cambio'!$E$11:$E$15,MATCH(E11,'Tasas de Cambio'!$B$11:$B$15,0)),0)} -> 3788.4 | J11: =IFERROR(H11*I11,0) -> 170478 | K11: =IFERROR(J11/'Tasas de Cambio'!$C$5,0) -> 56826
A12: Tours y Excursiones | B12: Barcelona | C12: 7 May 2027 | D12: Tour Barcelona Modernista | E12: USD | F12: 10 | G12: 3 | H12: =IFERROR(F12*G12,0) -> 30 | I12: {=IFERROR(INDEX('Tasas de Cambio'!$E$11:$E$15,MATCH(E12,'Tasas de Cambio'!$B$11:$B$15,0)),0)} -> 3263.4 | J12: =IFERROR(H12*I12,0) -> 97902 | K12: =IFERROR(J12/'Tasas de Cambio'!$C$5,0) -> 32634 | L12: Tour guiado por el Modernismo catalán en Barcelona. https://www.civitatis.com/es/barcelona/tour-barcelona-modernista/ | M12: 27 ago 2026
A13: Comidas | B13: Barcelona | C13: 46514 | D13: 3 comidas | E13: EUR | F13: 30 | G13: 3 | H13: =IFERROR(F13*G13,0) -> 90 | I13: {=IFERROR(INDEX('Tasas de Cambio'!$E$11:$E$15,MATCH(E13,'Tasas de Cambio'!$B$11:$B$15,0)),0)} -> 3788.4 | J13: =IFERROR(H13*I13,0) -> 340956 | K13: =IFERROR(J13/'Tasas de Cambio'!$C$5,0) -> 113652
A14: Traslados | B14: Barcelona | C14: 46514.0 | D14: Bus, 4 trayectos | E14: EUR | F14: 12 | G14: 3 | H14: =IFERROR(F14*G14,0) -> 36 | I14: {=IFERROR(INDEX('Tasas de Cambio'!$E$11:$E$15,MATCH(E14,'Tasas de Cambio'!$B$11:$B$15,0)),0)} -> 3788.4 | J14: =IFERROR(H14*I14,0) -> 136382.4 | K14: =IFERROR(J14/'Tasas de Cambio'!$C$5,0) -> 45460.8 | M14: 27 ago 2026
A15: Crucero | B15: Mediterráneo | C15: 8 – 15 May (7 noches) | D15: Crucero Barcelona → Ravena — tarifa por persona (cabina) | E15: USD | F15: 670 | G15: 3 | H15: =IFERROR(F15*G15,0) -> 2010 | I15: {=IFERROR(INDEX('Tasas de Cambio'!$E$11:$E$15,MATCH(E15,'Tasas de Cambio'!$B$11:$B$15,0)),0)} -> 3263.4 | J15: =IFERROR(H15*I15,0) -> 6559434 | K15: =IFERROR(J15/'Tasas de Cambio'!$C$5,0) -> 2186478 | L15: Crucero Barcelona-Ravena, 7 noches, incluye propinas. https://www.royalcaribbean.com/lac/es/itinerary/7-night-italy-croatia-cruise-from-barcelona-on-brilliance-BR07M885?sailDate=2027-05-08&packageCode=BR07M885&groupId=BR07BCN-1768961711&country=COL&search=startDate:2027-05-01~2027-05-31 | M15: 27 ago 2026
A16: Traslados | B16: España | C16: 46515 | D16: Traslado hotel → puerto (embarque crucero), Barcelona | E16: EUR | F16: 30 | G16: 1 | H16: =IFERROR(F16*G16,0) -> 30 | I16: {=IFERROR(INDEX('Tasas de Cambio'!$E$11:$E$15,MATCH(E16,'Tasas de Cambio'!$B$11:$B$15,0)),0)} -> 3788.4 | J16: =IFERROR(H16*I16,0) -> 113652 | K16: =IFERROR(J16/'Tasas de Cambio'!$C$5,0) -> 37884
A17: Tours y Excursiones | B17: Barcelona | C17: 46515 | D17: N/A | E17: EUR | F17: 0 | G17: 3 | H17: =IFERROR(F17*G17,0) -> 0 | I17: {=IFERROR(INDEX('Tasas de Cambio'!$E$11:$E$15,MATCH(E17,'Tasas de Cambio'!$B$11:$B$15,0)),0)} -> 3788.4 | J17: =IFERROR(H17*I17,0) -> 0 | K17: =IFERROR(J17/'Tasas de Cambio'!$C$5,0) -> 0
A18: Comidas | B18: Barcelona | C18: 46515 | D18: desayuno | E18: EUR | F18: 10 | G18: 3 | H18: =IFERROR(F18*G18,0) -> 30 | I18: {=IFERROR(INDEX('Tasas de Cambio'!$E$11:$E$15,MATCH(E18,'Tasas de Cambio'!$B$11:$B$15,0)),0)} -> 3788.4 | J18: =IFERROR(H18*I18,0) -> 113652 | K18: =IFERROR(J18/'Tasas de Cambio'!$C$5,0) -> 37884
A19: Tours y Excursiones | B19: Navegacion | C19: 46516 | D19: N/A | E19: EUR | F19: 0 | G19: 3 | H19: =IFERROR(F19*G19,0) -> 0 | I19: {=IFERROR(INDEX('Tasas de Cambio'!$E$11:$E$15,MATCH(E19,'Tasas de Cambio'!$B$11:$B$15,0)),0)} -> 3788.4 | J19: =IFERROR(H19*I19,0) -> 0 | K19: =IFERROR(J19/'Tasas de Cambio'!$C$5,0) -> 0
A20: Tours y Excursiones | B20: La Spezia (Florencia/Pisa) | C20: 46517.0 | D20: Panoramic Pisa | E20: USD | F20: 70 | G20: 3 | H20: =IFERROR(F20*G20,0) -> 210 | I20: {=IFERROR(INDEX('Tasas de Cambio'!$E$11:$E$15,MATCH(E20,'Tasas de Cambio'!$B$11:$B$15,0)),0)} -> 3263.4 | J20: =IFERROR(H20*I20,0) -> 685314 | K20: =IFERROR(J20/'Tasas de Cambio'!$C$5,0) -> 228438 | L20: Excursión panorámica por Pisa desde el crucero. https://www.royalcaribbean.com/account/cruise-planner/category/shorex/product/Y8RO?bookingId=3113096&shipCode=BR&sailDate=20270508 | M20: 27 ago 2026
A21: Comidas | B21: La Spezia (Florencia/Pisa) | C21: 46517 | D21: Comida | E21: EUR | F21: 25 | G21: 3 | H21: =IFERROR(F21*G21,0) -> 75 | I21: {=IFERROR(INDEX('Tasas de Cambio'!$E$11:$E$15,MATCH(E21,'Tasas de Cambio'!$B$11:$B$15,0)),0)} -> 3788.4 | J21: =IFERROR(H21*I21,0) -> 284130 | K21: =IFERROR(J21/'Tasas de Cambio'!$C$5,0) -> 94710
A22: Tours y Excursiones | B22: Civitavecchia (Roma) | C22: 46518.0 | D22: Visit to Rome | E22: USD | F22: 142 | G22: 3 | H22: =IFERROR(F22*G22,0) -> 426 | I22: {=IFERROR(INDEX('Tasas de Cambio'!$E$11:$E$15,MATCH(E22,'Tasas de Cambio'!$B$11:$B$15,0)),0)} -> 3263.4 | J22: =IFERROR(H22*I22,0) -> 1390208.4 | K22: =IFERROR(J22/'Tasas de Cambio'!$C$5,0) -> 463402.8 | L22: Excursión a Roma desde el crucero. https://www.royalcaribbean.com/account/cruise-planner/category/shorex/product/CV1F?bookingId=3113096&shipCode=BR&sailDate=20270508 | M22: 29 ago 2026
A23: Comidas | B23: Civitavecchia (Roma) | C23: 46518 | D23: Comida | E23: EUR | F23: 25 | G23: 3 | H23: =IFERROR(F23*G23,0) -> 75 | I23: {=IFERROR(INDEX('Tasas de Cambio'!$E$11:$E$15,MATCH(E23,'Tasas de Cambio'!$B$11:$B$15,0)),0)} -> 3788.4 | J23: =IFERROR(H23*I23,0) -> 284130 | K23: =IFERROR(J23/'Tasas de Cambio'!$C$5,0) -> 94710
A24: Tours y Excursiones | B24: Salerno (Costa Amalfitana) | C24: 46519.0 | D24: Tour a pie gratis | E24: EUR | F24: 0 | G24: 3 | H24: =IFERROR(F24*G24,0) -> 0 | I24: {=IFERROR(INDEX('Tasas de Cambio'!$E$11:$E$15,MATCH(E24,'Tasas de Cambio'!$B$11:$B$15,0)),0)} -> 3788.4 | J24: =IFERROR(H24*I24,0) -> 0 | K24: =IFERROR(J24/'Tasas de Cambio'!$C$5,0) -> 0 | M24: 27 ago 2026
A25: Tours y Excursiones | B25: Navegacion | C25: 46520 | D25: N/A | E25: CZK | F25: 0 | G25: 3 | H25: =IFERROR(F25*G25,0) -> 0 | I25: {=IFERROR(INDEX('Tasas de Cambio'!$E$11:$E$15,MATCH(E25,'Tasas de Cambio'!$B$11:$B$15,0)),0)} -> 156.97 | J25: =IFERROR(H25*I25,0) -> 0 | K25: =IFERROR(J25/'Tasas de Cambio'!$C$5,0) -> 0
A26: Traslados | B26: Zadar, Croacia | C26: 46521 | D26: Transporte - Tour a pie gratis | E26: EUR | F26: 10 | G26: 3 | H26: =IFERROR(F26*G26,0) -> 30 | I26: {=IFERROR(INDEX('Tasas de Cambio'!$E$11:$E$15,MATCH(E26,'Tasas de Cambio'!$B$11:$B$15,0)),0)} -> 3788.4 | J26: =IFERROR(H26*I26,0) -> 113652 | K26: =IFERROR(J26/'Tasas de Cambio'!$C$5,0) -> 37884
A27: Alojamiento | B27: Venecia, Italia | C27: 15 – 16 May (1 noche, post-crucero) | D27: Hotel Venecia — costo total (1 noche) | E27: EUR | F27: 400 | G27: 1 | H27: =IFERROR(F27*G27,0) -> 400 | I27: {=IFERROR(INDEX('Tasas de Cambio'!$E$11:$E$15,MATCH(E27,'Tasas de Cambio'!$B$11:$B$15,0)),0)} -> 3788.4 | J27: =IFERROR(H27*I27,0) -> 1515360 | K27: =IFERROR(J27/'Tasas de Cambio'!$C$5,0) -> 505120 | M27: 28 ago 2026
A28: Traslados | B28: Italia | C28: 46522.0 | D28: Traslado puerto → Estación Ravenna | E28: EUR | F28: 12 | G28: 3 | H28: =IFERROR(F28*G28,0) -> 36 | I28: {=IFERROR(INDEX('Tasas de Cambio'!$E$11:$E$15,MATCH(E28,'Tasas de Cambio'!$B$11:$B$15,0)),0)} -> 3788.4 | J28: =IFERROR(H28*I28,0) -> 136382.4 | K28: =IFERROR(J28/'Tasas de Cambio'!$C$5,0) -> 45460.8 | M28: 27 ago 2026
A29: Comidas | B29: Rávena (Venecia) | C29: 46522 | D29: Almuerzo y cena | E29: EUR | F29: 30 | G29: 3 | H29: =IFERROR(F29*G29,0) -> 90 | I29: {=IFERROR(INDEX('Tasas de Cambio'!$E$11:$E$15,MATCH(E29,'Tasas de Cambio'!$B$11:$B$15,0)),0)} -> 3788.4 | J29: =IFERROR(H29*I29,0) -> 340956 | K29: =IFERROR(J29/'Tasas de Cambio'!$C$5,0) -> 113652
A30: Vuelos y Trenes | B30: Venecia / Bogota | C30: 46523 | D30: Vuelo Lufthansa Venecia → Bogotá (vía FRA), regreso | E30: COP | F30: 1491070 | G30: 3 | H30: =IFERROR(F30*G30,0) -> 4473210 | I30: {=IFERROR(INDEX('Tasas de Cambio'!$E$11:$E$15,MATCH(E30,'Tasas de Cambio'!$B$11:$B$15,0)),0)} -> 1 | J30: =IFERROR(H30*I30,0) -> 4473210 | K30: =IFERROR(J30/'Tasas de Cambio'!$C$5,0) -> 1491070 | L30: Lufthansa · VCE 10:55 → BOG 18:55 · 1 escala (FRA) · Duración 15h00m · Economy Light. https://shop.lufthansa.com/booking/cart?cartId=1EA66RSYEOGDFEB1&type=cart&shared=true&origin=BOG&utm_source=sharedcart&utm_medium=referral&consent=true | M30: 27 ago 2026
A31: Traslados | B31: Italia | C31: 46523 | D31: Traslado hotel → aeropuerto, Venecia | E31: EUR | F31: 30 | G31: 1 | H31: =IFERROR(F31*G31,0) -> 30 | I31: {=IFERROR(INDEX('Tasas de Cambio'!$E$11:$E$15,MATCH(E31,'Tasas de Cambio'!$B$11:$B$15,0)),0)} -> 3788.4 | J31: =IFERROR(H31*I31,0) -> 113652 | K31: =IFERROR(J31/'Tasas de Cambio'!$C$5,0) -> 37884
A32: Tours y Excursiones | B32: Venecia | C32: 15 May 2027 | D32: Free tour Venecia | E32: EUR | F32: 10 | G32: 3 | H32: =IFERROR(F32*G32,0) -> 30 | I32: {=IFERROR(INDEX('Tasas de Cambio'!$E$11:$E$15,MATCH(E32,'Tasas de Cambio'!$B$11:$B$15,0)),0)} -> 3788.4 | J32: =IFERROR(H32*I32,0) -> 113652 | K32: =IFERROR(J32/'Tasas de Cambio'!$C$5,0) -> 37884 | L32: Free tour guiado por el centro histórico de Venecia. https://www.civitatis.com/es/venecia/free-tour-venecia/?_gl=1*1ijxuzi*_up*MQ..*_ga*ODU4MDQyNjAyLjE3ODc4Nzc2ODY.*_ga_QJQ54CTKPM*czE3ODc4Nzc2ODYkbzEkZzEkdDE3ODc4Nzc2OTEkajU1JGwwJGgxNTA2MDA0ODU0 | M32: 27 ago 2026
A33: Comidas | B33: Venecia | C33: 46523.0 | D33: Desayuno | E33: EUR | F33: 12 | G33: 3 | H33: =IFERROR(F33*G33,0) -> 36 | I33: {=IFERROR(INDEX('Tasas de Cambio'!$E$11:$E$15,MATCH(E33,'Tasas de Cambio'!$B$11:$B$15,0)),0)} -> 3788.4 | J33: =IFERROR(H33*I33,0) -> 136382.4 | K33: =IFERROR(J33/'Tasas de Cambio'!$C$5,0) -> 45460.8 | L33: Almuerzo y cena incluidos en el vuelo de regreso (15h, sale 10:55am) | M33: 28 ago 2026
A34: Tours y Excursiones | B34: Barcelona | C34: 7 May 2027 | D34: Free tour Sagrada Familia | E34: USD | F34: 10 | G34: 3 | H34: =IFERROR(F34*G34,0) -> 30 | I34: {=IFERROR(INDEX('Tasas de Cambio'!$E$11:$E$15,MATCH(E34,'Tasas de Cambio'!$B$11:$B$15,0)),0)} -> 3263.4 | J34: =IFERROR(H34*I34,0) -> 97902 | K34: =IFERROR(J34/'Tasas de Cambio'!$C$5,0) -> 32634 | L34: Free tour guiado por el exterior de la Sagrada Familia. https://www.civitatis.com/es/barcelona/free-tour-sagrada-familia/ | M34: 27 ago 2026
D35: TOTAL GENERAL | J35: =SUM(J5:J33) -> 26823622 | K35: =SUM(K5:K33) -> 8941207.2
A36: Otros y Extras | B36: Navegación | C36: 9 May 2027 | D36: Día de navegación | E36: COP | F36: 0 | G36: 1 | H36: =IFERROR(F36*G36,0) -> 0 | I36: {=IFERROR(INDEX('Tasas de Cambio'!$E$11:$E$15,MATCH(E36,'Tasas de Cambio'!$B$11:$B$15,0)),0)} -> 1 | J36: =IFERROR(H36*I36,0) -> 0 | K36: =IFERROR(J36/'Tasas de Cambio'!$C$5,0) -> 0 | L36: Día de navegación, incluido en la tarifa del crucero. https://www.royalcaribbean.com/lac/es/itinerary/7-night-italy-croatia-cruise-from-barcelona-on-brilliance-BR07M885?sailDate=2027-05-08&packageCode=BR07M885&groupId=BR07BCN-1768961711&country=COL&search=startDate:2027-05-01~2027-05-31 | M36: 27 ago 2026
A37: Otros y Extras | B37: Navegación | C37: 13 May 2027 | D37: Día de navegación | E37: COP | F37: 0 | G37: 1 | H37: =IFERROR(F37*G37,0) -> 0 | I37: {=IFERROR(INDEX('Tasas de Cambio'!$E$11:$E$15,MATCH(E37,'Tasas de Cambio'!$B$11:$B$15,0)),0)} -> 1 | J37: =IFERROR(H37*I37,0) -> 0 | K37: =IFERROR(J37/'Tasas de Cambio'!$C$5,0) -> 0 | L37: Día de navegación, incluido en la tarifa del crucero. https://www.royalcaribbean.com/lac/es/itinerary/7-night-italy-croatia-cruise-from-barcelona-on-brilliance-BR07M885?sailDate=2027-05-08&packageCode=BR07M885&groupId=BR07BCN-1768961711&country=COL&search=startDate:2027-05-01~2027-05-31 | M37: 27 ago 2026
A38: Traslados | B38: Venecia | C38: 15 May 2027 | D38: Vaporetti ACTV | E38: EUR | F38: 25 | G38: 3 | H38: =IFERROR(F38*G38,0) -> 75 | I38: {=IFERROR(INDEX('Tasas de Cambio'!$E$11:$E$15,MATCH(E38,'Tasas de Cambio'!$B$11:$B$15,0)),0)} -> 3788.4 | J38: =IFERROR(H38*I38,0) -> 284130 | K38: =IFERROR(J38/'Tasas de Cambio'!$C$5,0) -> 94710 | L38: Boletos de vaporetto (transporte acuático) por Venecia. https://book.tickets-venice.com/es/book/8748/select/?_gl=1%2A1073ils%2A_gcl_aw%2AR0NMLjE3ODc4NzgwODMuRUFJYUlRb2JDaE1JaFpPNjdZekNsZ01Wd1lSYUJSM2Y1U1JPRUFBWUF5QUFFZ0tjeFBEX0J3RQ..%2A_gcl_au%2ANzIxMTA1MTQ5LjE3ODc4NzgwODMuLS4tLjE3ODc4NzgwODMuMTE2MDU2ODc1MS4xNzg3ODc4MDg0LjE3ODc4NzgwODM.%2A_ga%2ANDcyOTU3MzYyLjE3ODc4NzgwODM.%2A_ga_Y45PC9R73C%2AczE3ODc4NzgwODMkbzEkZzAkdDE3ODc4NzgwODQkajU5JGwwJGgw&cookieBanner=false&date=2027-05-15&tourId=15560&variantId=15560 | M38: 27 ago 2026
A39: Vuelos y Trenes | B39: Italia | C39: 15 May 2027 | D39: Tren Ravenna - Venecia St Lucia | E39: EUR | F39: 25 | G39: 3 | H39: =IFERROR(F39*G39,0) -> 75 | I39: {=IFERROR(INDEX('Tasas de Cambio'!$E$11:$E$15,MATCH(E39,'Tasas de Cambio'!$B$11:$B$15,0)),0)} -> 3788.4 | J39: =IFERROR(H39*I39,0) -> 284130 | K39: =IFERROR(J39/'Tasas de Cambio'!$C$5,0) -> 94710 | L39: Tren regional desde Ravenna hasta Venecia Santa Lucia. https://www.trenitalia.com/en.html | M39: 27 ago 2026
A40: Comidas | B40: Salerno (Costa Amalfitana) | C40: 12 May 2027 | D40: Incluida en el crucero (come a bordo) | E40: EUR | F40: 0 | G40: 3 | H40: =IFERROR(F40*G40,0) -> 0 | I40: {=IFERROR(INDEX('Tasas de Cambio'!$E$11:$E$15,MATCH(E40,'Tasas de Cambio'!$B$11:$B$15,0)),0)} -> 3788.4 | J40: =IFERROR(H40*I40,0) -> 0 | K40: =IFERROR(J40/'Tasas de Cambio'!$C$5,0) -> 0 | L40: Comida incluida en el paquete del crucero, sin costo adicional | M40: 27 ago 2026
A41: Comidas | B41: Zadar, Croacia | C41: 14 May 2027 | D41: Incluida en el crucero (come a bordo) | E41: EUR | F41: 0 | G41: 3 | H41: =IFERROR(F41*G41,0) -> 0 | I41: {=IFERROR(INDEX('Tasas de Cambio'!$E$11:$E$15,MATCH(E41,'Tasas de Cambio'!$B$11:$B$15,0)),0)} -> 3788.4 | J41: =IFERROR(H41*I41,0) -> 0 | K41: =IFERROR(J41/'Tasas de Cambio'!$C$5,0) -> 0 | L41: Comida incluida en el paquete del crucero, sin costo adicional | M41: 27 ago 2026

Sheet Crucero 2P
A2: COTIZACIÓN DETALLADA — EUROPA 2027 (05 May – 16 May 2027) | O2: Vuelos y Trenes | P2: EUR
O3: Traslados | P3: CHF
A4: Categoría | B4: Ciudad / País | C4: Fechas | D4: Concepto / Descripción | E4: Moneda | F4: Costo Unitario (moneda original) | G4: Cantidad | H4: Costo Total (moneda original) | I4: Tasa de Cambio a COP | J4: Costo Total (COP) | K4: Costo por Persona (COP) | L4: Notas | M4: Fecha confirmación precio | O4: Alojamiento | P4: CZK
A5: Otros y Extras | B5: — | C5: Durante el viaje | D5: SIM card de viaje (datos internacionales) | E5: USD | F5: 40 | G5: 1 | H5: =IFERROR(F5*G5,0) -> 40 | I5: {=IFERROR(INDEX('Tasas de Cambio'!$E$11:$E$15,MATCH(E5,'Tasas de Cambio'!$B$11:$B$15,0)),0)} -> 3263.4 | J5: =IFERROR(H5*I5,0) -> 130536 | K5: =IFERROR(J5/2,0) -> 65268 | L5: SIM compartida entre las 2 personas para los 11 días del crucero. https://esim.holafly.com/es/esim-europa/?selectedDays=11&startDate=2027-05-06&endDate=2027-05-16 | M5: 28 ago 2026
A6: Otros y Extras | B6: — | C6: Contingencia | D6: Imprevistos / gastos varios (contingencia) | E6: EUR | F6: 200 | G6: 2 | H6: 400 | I6: {=IFERROR(INDEX('Tasas de Cambio'!$E$11:$E$15,MATCH(E6,'Tasas de Cambio'!$B$11:$B$15,0)),0)} -> 3788.4 | J6: 1515360 | K6: =IFERROR(J6/2,0) -> 757680 | O6: Tours y Excursiones | P6: COP
A7: Seguro de Viaje | B7: Internacional | C7: 5 – 16 may 2027 (12 días de cobertura) | D7: Asistencia médica internacional | E7: COP | F7: 221985 | G7: 2 | H7: =IFERROR(F7*G7,0) -> 443970 | I7: {=IFERROR(INDEX('Tasas de Cambio'!$E$11:$E$15,MATCH(E7,'Tasas de Cambio'!$B$11:$B$15,0)),0)} -> 1 | J7: =IFERROR(H7*I7,0) -> 443970 | K7: =IFERROR(J7/2,0) -> 221985 | L7: Asistencia médica internacional, cobertura USD 60.000 (Cuponatic). https://www.cuponatic.com.co/descuento/asistencia-medica-internacional-cobertura-de-usd-60-000?m=tarjetas-de-asistencia&id_descuento=212587 | M7: 27 ago 2026
A8: Vuelos y Trenes | B8: Bogota / Barcelona | C8: 46512.0 | D8: Vuelo Lufthansa Bogotá → Barcelona (vía FRA), ida | E8: COP | F8: 1491070 | G8: 2 | H8: =IFERROR(F8*G8,0) -> 2982140 | I8: {=IFERROR(INDEX('Tasas de Cambio'!$E$11:$E$15,MATCH(E8,'Tasas de Cambio'!$B$11:$B$15,0)),0)} -> 1 | J8: =IFERROR(H8*I8,0) -> 2982140 | K8: =IFERROR(J8/2,0) -> 1491070 | L8: Lufthansa, BOG 23:30 (hora Colombia) → FRA (escala) → BCN 23:05 +1 día, local España. https://shop.lufthansa.com/booking/cart?cartId=1EA66RSYEOGDFEB1&type=cart&shared=true&origin=BOG&utm_source=sharedcart&utm_medium=referral&consent=true | M8: 11 sep 2026
A9: Alojamiento | B9: Barcelona, España | C9: 6 – 8 May (2 noches, pre-crucero) | D9: Hotel Barcelona — costo total (2 noches) | E9: COP | F9: 1615000 | G9: 1 | H9: =IFERROR(F9*G9,0) -> 1615000 | I9: {=IFERROR(INDEX('Tasas de Cambio'!$E$11:$E$15,MATCH(E9,'Tasas de Cambio'!$B$11:$B$15,0)),0)} -> 1 | J9: =IFERROR(H9*I9,0) -> 1615000 | K9: =IFERROR(J9/2,0) -> 807500 | L9: Sagrada Familia, 2 noches (6-8 may). https://www.booking.com/hotel/es/sagradafamilia.es.html?aid=2311236&label=es-co-booking-desktop-vjGZbEFOhRc3a9njxeT3IwS652829002024%3Apl%3Ata%3Ap1%3Ap2%3Aac%3Aap%3Aneg%3Afi%3Atikwd-65526620%3Alp9246960%3Ali%3Adec%3Adm&sid=f6a1a9bb810c453f7b5f1225205f1f26&all_sr_blocks=9118810_91908190_0_2_0&checkin=2027-05-06&checkout=2027-05-08&dest_id=-372490&dest_type=city&dist=0&group_adults=2&group_children=0&hapos=1&highlighted_blocks=9118810_91908190_0_2_0&hpos=1&matching_block_id=9118810_91908190_0_2_0&no_rooms=1&req_adults=2&req_children=0&room1=A%2CA&sb_price_type=total&sr_order=popularity&sr_pri_blocks=9118810_91908190_0_2_0__32800&srepoch=1787920765&srpvid=c13758fcde590c7a&type=total&ucfs=1 | M9: 28 ago 2026
A10: Traslados | B10: España | C10: 46513.0 | D10: Traslado aeropuerto → hotel, Barcelona | E10: EUR | F10: 40 | G10: 1 | H10: =IFERROR(F10*G10,0) -> 40 | I10: {=IFERROR(INDEX('Tasas de Cambio'!$E$11:$E$15,MATCH(E10,'Tasas de Cambio'!$B$11:$B$15,0)),0)} -> 3788.4 | J10: =IFERROR(H10*I10,0) -> 151536 | K10: =IFERROR(J10/2,0) -> 75768 | M10: 28 ago 2026
A11: Comidas | B11: Barcelona | C11: 46513 | D11: cena | E11: EUR | F11: 15 | G11: 2 | H11: 30 | I11: {=IFERROR(INDEX('Tasas de Cambio'!$E$11:$E$15,MATCH(E11,'Tasas de Cambio'!$B$11:$B$15,0)),0)} -> 3788.4 | J11: 113652 | K11: =IFERROR(J11/2,0) -> 56826
A12: Tours y Excursiones | B12: Barcelona | C12: 7 May 2027 | D12: Tour Barcelona Modernista | E12: USD | F12: 10 | G12: 2 | H12: =IFERROR(F12*G12,0) -> 20 | I12: {=IFERROR(INDEX('Tasas de Cambio'!$E$11:$E$15,MATCH(E12,'Tasas de Cambio'!$B$11:$B$15,0)),0)} -> 3263.4 | J12: =IFERROR(H12*I12,0) -> 65268 | K12: =IFERROR(J12/2,0) -> 32634 | L12: Tour guiado por el Modernismo catalán en Barcelona. https://www.civitatis.com/es/barcelona/tour-barcelona-modernista/ | M12: 27 ago 2026
A13: Comidas | B13: Barcelona | C13: 46514 | D13: 3 comidas | E13: EUR | F13: 30 | G13: 2 | H13: 60 | I13: {=IFERROR(INDEX('Tasas de Cambio'!$E$11:$E$15,MATCH(E13,'Tasas de Cambio'!$B$11:$B$15,0)),0)} -> 3788.4 | J13: 227304 | K13: =IFERROR(J13/2,0) -> 113652
A14: Traslados | B14: Barcelona | C14: 46514.0 | D14: Bus, 4 trayectos | E14: EUR | F14: 12 | G14: 2 | H14: =IFERROR(F14*G14,0) -> 24 | I14: {=IFERROR(INDEX('Tasas de Cambio'!$E$11:$E$15,MATCH(E14,'Tasas de Cambio'!$B$11:$B$15,0)),0)} -> 3788.4 | J14: =IFERROR(H14*I14,0) -> 90921.6 | K14: =IFERROR(J14/2,0) -> 45460.8 | M14: 27 ago 2026
A15: Crucero | B15: Mediterráneo | C15: 8 – 15 May (7 noches) | D15: Crucero Barcelona → Ravena — tarifa por persona (cabina) | E15: USD | F15: 1650 | G15: 1 | H15: =IFERROR(F15*G15,0) -> 1650 | I15: {=IFERROR(INDEX('Tasas de Cambio'!$E$11:$E$15,MATCH(E15,'Tasas de Cambio'!$B$11:$B$15,0)),0)} -> 3263.4 | J15: =IFERROR(H15*I15,0) -> 5384610 | K15: =IFERROR(J15/2,0) -> 2692305 | L15: Crucero Barcelona-Ravena, 7 noches, incluye propinas. https://www.royalcaribbean.com/lac/es/itinerary/7-night-italy-croatia-cruise-from-barcelona-on-brilliance-BR07M885?sailDate=2027-05-08&packageCode=BR07M885&groupId=BR07BCN-1768961711&country=COL&search=startDate:2027-05-01~2027-05-31 | M15: 28 ago 2026
A16: Traslados | B16: España | C16: 46515.0 | D16: Traslado hotel → puerto (embarque crucero), Barcelona | E16: USD | F16: 15 | G16: 1 | H16: =IFERROR(F16*G16,0) -> 15 | I16: {=IFERROR(INDEX('Tasas de Cambio'!$E$11:$E$15,MATCH(E16,'Tasas de Cambio'!$B$11:$B$15,0)),0)} -> 3263.4 | J16: =IFERROR(H16*I16,0) -> 48951 | K16: =IFERROR(J16/2,0) -> 24475.5 | M16: 28 ago 2026
A17: Tours y Excursiones | B17: Barcelona | C17: 46515 | D17: N/A | E17: EUR | F17: 0 | G17: 3 | H17: 0 | I17: {=IFERROR(INDEX('Tasas de Cambio'!$E$11:$E$15,MATCH(E17,'Tasas de Cambio'!$B$11:$B$15,0)),0)} -> 3788.4 | J17: 0 | K17: =IFERROR(J17/'Tasas de Cambio'!$C$5,0) -> 0
A18: Comidas | B18: Barcelona | C18: 46515 | D18: desayuno | E18: EUR | F18: 10 | G18: 2 | H18: 20 | I18: {=IFERROR(INDEX('Tasas de Cambio'!$E$11:$E$15,MATCH(E18,'Tasas de Cambio'!$B$11:$B$15,0)),0)} -> 3788.4 | J18: 75768 | K18: =IFERROR(J18/2,0) -> 37884
A19: Tours y Excursiones | B19: Navegacion | C19: 46516 | D19: N/A | E19: EUR | F19: 0 | G19: 3 | H19: 0 | I19: {=IFERROR(INDEX('Tasas de Cambio'!$E$11:$E$15,MATCH(E19,'Tasas de Cambio'!$B$11:$B$15,0)),0)} -> 3788.4 | J19: 0 | K19: =IFERROR(J19/'Tasas de Cambio'!$C$5,0) -> 0
A20: Tours y Excursiones | B20: La Spezia (Florencia/Pisa) | C20: 46517.0 | D20: Panoramic Pisa | E20: USD | F20: 70 | G20: 2 | H20: =IFERROR(F20*G20,0) -> 140 | I20: {=IFERROR(INDEX('Tasas de Cambio'!$E$11:$E$15,MATCH(E20,'Tasas de Cambio'!$B$11:$B$15,0)),0)} -> 3263.4 | J20: =IFERROR(H20*I20,0) -> 456876 | K20: =IFERROR(J20/2,0) -> 228438 | L20: Excursión panorámica por Pisa desde el crucero. https://www.royalcaribbean.com/account/cruise-planner/category/shorex/product/Y8RO?bookingId=3113096&shipCode=BR&sailDate=20270508 | M20: 27 ago 2026
A21: Comidas | B21: La Spezia (Florencia/Pisa) | C21: 46517 | D21: Comida | E21: EUR | F21: 25 | G21: 2 | H21: 50 | I21: {=IFERROR(INDEX('Tasas de Cambio'!$E$11:$E$15,MATCH(E21,'Tasas de Cambio'!$B$11:$B$15,0)),0)} -> 3788.4 | J21: 189420 | K21: =IFERROR(J21/2,0) -> 94710
A22: Tours y Excursiones | B22: Civitavecchia (Roma) | C22: 46518.0 | D22: Visit to Rome | E22: USD | F22: 142 | G22: 2 | H22: =IFERROR(F22*G22,0) -> 284 | I22: {=IFERROR(INDEX('Tasas de Cambio'!$E$11:$E$15,MATCH(E22,'Tasas de Cambio'!$B$11:$B$15,0)),0)} -> 3263.4 | J22: =IFERROR(H22*I22,0) -> 926805.6 | K22: =IFERROR(J22/2,0) -> 463402.8 | L22: Excursión a Roma desde el crucero. https://www.royalcaribbean.com/account/cruise-planner/category/shorex/product/CV1F?bookingId=3113096&shipCode=BR&sailDate=20270508 | M22: 29 ago 2026
A23: Comidas | B23: Civitavecchia (Roma) | C23: 46518 | D23: Comida | E23: EUR | F23: 25 | G23: 2 | H23: 50 | I23: {=IFERROR(INDEX('Tasas de Cambio'!$E$11:$E$15,MATCH(E23,'Tasas de Cambio'!$B$11:$B$15,0)),0)} -> 3788.4 | J23: 189420 | K23: =IFERROR(J23/2,0) -> 94710
A24: Tours y Excursiones | B24: Salerno (Costa Amalfitana) | C24: 46519.0 | D24: Tour a pie gratis | E24: EUR | F24: 0 | G24: 3 | H24: =IFERROR(F24*G24,0) -> 0 | I24: {=IFERROR(INDEX('Tasas de Cambio'!$E$11:$E$15,MATCH(E24,'Tasas de Cambio'!$B$11:$B$15,0)),0)} -> 3788.4 | J24: =IFERROR(H24*I24,0) -> 0 | K24: =IFERROR(J24/'Tasas de Cambio'!$C$5,0) -> 0 | M24: 27 ago 2026
A25: Tours y Excursiones | B25: Navegacion | C25: 46520 | D25: N/A | E25: CZK | F25: 0 | G25: 3 | H25: 0 | I25: {=IFERROR(INDEX('Tasas de Cambio'!$E$11:$E$15,MATCH(E25,'Tasas de Cambio'!$B$11:$B$15,0)),0)} -> 156.97 | J25: 0 | K25: =IFERROR(J25/'Tasas de Cambio'!$C$5,0) -> 0
A26: Traslados | B26: Zadar, Croacia | C26: 46521 | D26: Transporte - Tour a pie gratis | E26: EUR | F26: 10 | G26: 2 | H26: 20 | I26: {=IFERROR(INDEX('Tasas de Cambio'!$E$11:$E$15,MATCH(E26,'Tasas de Cambio'!$B$11:$B$15,0)),0)} -> 3788.4 | J26: 75768 | K26: =IFERROR(J26/2,0) -> 37884
A27: Alojamiento | B27: Venecia, Italia | C27: 15 – 16 May (1 noche, post-crucero) | D27: Hotel Venecia — costo total (1 noche) | E27: COP | F27: 1100000 | G27: 1 | H27: =IFERROR(F27*G27,0) -> 1100000 | I27: {=IFERROR(INDEX('Tasas de Cambio'!$E$11:$E$15,MATCH(E27,'Tasas de Cambio'!$B$11:$B$15,0)),0)} -> 1 | J27: =IFERROR(H27*I27,0) -> 1100000 | K27: =IFERROR(J27/2,0) -> 550000 | L27: . https://www.booking.com/hotel/it/alloggi-arlecchino.es.html?aid=304142&label=gen173bo-10CAsocUISYWxsb2dnaS1hcmxlY2NoaW5vSApYA2gyiAEBmAEzuAEHyAEM2AED6AEB-AEBiAIBmAIEqAIBuAKxisbUBsACAdICJDYzYjI0MDkzLWUwMDQtNGE1NS05ZjIwLWYwODllODdiODI1ONgCAeACAQ&sid=f6a1a9bb810c453f7b5f1225205f1f26&all_sr_blocks=466062001_143466186_0_0_0&checkin=2027-05-15&checkout=2027-05-16&dest_id=-132007&dest_type=city&dist=0&group_adults=2&group_children=0&hapos=1&highlighted_blocks=466062001_143466186_0_0_0&hpos=1&matching_block_id=466062001_143466186_0_0_0&no_rooms=1&req_adults=2&req_children=0&room1=A%2CA&sb_price_type=total&sr_order=popularity&sr_pri_blocks=466062001_143466186_0_0_0__29079&srepoch=1787921833&srpvid=be9c5b0e91871d4a&type=total&ucfs=1 | M27: 28 ago 2026
A28: Traslados | B28: Italia | C28: 46522.0 | D28: Traslado puerto → Estación Ravenna | E28: EUR | F28: 12 | G28: 2 | H28: =IFERROR(F28*G28,0) -> 24 | I28: {=IFERROR(INDEX('Tasas de Cambio'!$E$11:$E$15,MATCH(E28,'Tasas de Cambio'!$B$11:$B$15,0)),0)} -> 3788.4 | J28: =IFERROR(H28*I28,0) -> 90921.6 | K28: =IFERROR(J28/2,0) -> 45460.8 | M28: 27 ago 2026
A29: Comidas | B29: Rávena (Venecia) | C29: 46522 | D29: Almuerzo y cena | E29: EUR | F29: 30 | G29: 2 | H29: 60 | I29: {=IFERROR(INDEX('Tasas de Cambio'!$E$11:$E$15,MATCH(E29,'Tasas de Cambio'!$B$11:$B$15,0)),0)} -> 3788.4 | J29: 227304 | K29: =IFERROR(J29/2,0) -> 113652
A30: Vuelos y Trenes | B30: Venecia / Bogota | C30: 46523.0 | D30: Vuelo Lufthansa Venecia → Bogotá (vía FRA), regreso | E30: COP | F30: 1491070 | G30: 2 | H30: =IFERROR(F30*G30,0) -> 2982140 | I30: {=IFERROR(INDEX('Tasas de Cambio'!$E$11:$E$15,MATCH(E30,'Tasas de Cambio'!$B$11:$B$15,0)),0)} -> 1 | J30: =IFERROR(H30*I30,0) -> 2982140 | K30: =IFERROR(J30/2,0) -> 1491070 | L30: Lufthansa, VCE 10:55 local → FRA (escala) → BOG 18:55 (hora Colombia aprox). https://shop.lufthansa.com/booking/cart?cartId=1EA66RSYEOGDFEB1&type=cart&shared=true&origin=BOG&utm_source=sharedcart&utm_medium=referral&consent=true | M30: 11 sep 2026
A31: Traslados | B31: Italia | C31: 46523.0 | D31: Traslado hotel → aeropuerto, Venecia | E31: EUR | F31: 30 | G31: 1 | H31: =IFERROR(F31*G31,0) -> 30 | I31: {=IFERROR(INDEX('Tasas de Cambio'!$E$11:$E$15,MATCH(E31,'Tasas de Cambio'!$B$11:$B$15,0)),0)} -> 3788.4 | J31: =IFERROR(H31*I31,0) -> 113652 | K31: =IFERROR(J31/2,0) -> 56826 | M31: 28 ago 2026
A32: Tours y Excursiones | B32: Venecia | C32: 15 May 2027 | D32: Free tour Venecia | E32: EUR | F32: 10 | G32: 2 | H32: =IFERROR(F32*G32,0) -> 20 | I32: {=IFERROR(INDEX('Tasas de Cambio'!$E$11:$E$15,MATCH(E32,'Tasas de Cambio'!$B$11:$B$15,0)),0)} -> 3788.4 | J32: =IFERROR(H32*I32,0) -> 75768 | K32: =IFERROR(J32/2,0) -> 37884 | L32: Free tour guiado por el centro histórico de Venecia. https://www.civitatis.com/es/venecia/free-tour-venecia/?_gl=1*1ijxuzi*_up*MQ..*_ga*ODU4MDQyNjAyLjE3ODc4Nzc2ODY.*_ga_QJQ54CTKPM*czE3ODc4Nzc2ODYkbzEkZzEkdDE3ODc4Nzc2OTEkajU1JGwwJGgxNTA2MDA0ODU0 | M32: 27 ago 2026
A33: Comidas | B33: Venecia | C33: 46523.0 | D33: Desayuno | E33: EUR | F33: 12 | G33: 2 | H33: =IFERROR(F33*G33,0) -> 24 | I33: {=IFERROR(INDEX('Tasas de Cambio'!$E$11:$E$15,MATCH(E33,'Tasas de Cambio'!$B$11:$B$15,0)),0)} -> 3788.4 | J33: =IFERROR(H33*I33,0) -> 90921.6 | K33: =IFERROR(J33/2,0) -> 45460.8 | L33: Almuerzo y cena incluidos en el vuelo de regreso (15h, sale 10:55am) | M33: 28 ago 2026
A34: Tours y Excursiones | B34: Barcelona | C34: 7 May 2027 | D34: Free tour Sagrada Familia | E34: USD | F34: 10 | G34: 2 | H34: =IFERROR(F34*G34,0) -> 20 | I34: {=IFERROR(INDEX('Tasas de Cambio'!$E$11:$E$15,MATCH(E34,'Tasas de Cambio'!$B$11:$B$15,0)),0)} -> 3263.4 | J34: =IFERROR(H34*I34,0) -> 65268 | K34: =IFERROR(J34/2,0) -> 32634 | L34: Free tour guiado por el exterior de la Sagrada Familia. https://www.civitatis.com/es/barcelona/free-tour-sagrada-familia/ | M34: 27 ago 2026
D35: TOTAL GENERAL | J35: =SUM(J5:J33) -> 26823622 | K35: =SUM(K5:K33) -> 8941207.2
A36: Otros y Extras | B36: Navegación | C36: 9 May 2027 | D36: Día de navegación | E36: COP | F36: 0 | G36: 1 | H36: =IFERROR(F36*G36,0) -> 0 | I36: {=IFERROR(INDEX('Tasas de Cambio'!$E$11:$E$15,MATCH(E36,'Tasas de Cambio'!$B$11:$B$15,0)),0)} -> 1 | J36: =IFERROR(H36*I36,0) -> 0 | K36: =IFERROR(J36/'Tasas de Cambio'!$C$5,0) -> 0 | L36: Día de navegación, incluido en la tarifa del crucero. https://www.royalcaribbean.com/lac/es/itinerary/7-night-italy-croatia-cruise-from-barcelona-on-brilliance-BR07M885?sailDate=2027-05-08&packageCode=BR07M885&groupId=BR07BCN-1768961711&country=COL&search=startDate:2027-05-01~2027-05-31 | M36: 27 ago 2026
A37: Otros y Extras | B37: Navegación | C37: 13 May 2027 | D37: Día de navegación | E37: COP | F37: 0 | G37: 1 | H37: =IFERROR(F37*G37,0) -> 0 | I37: {=IFERROR(INDEX('Tasas de Cambio'!$E$11:$E$15,MATCH(E37,'Tasas de Cambio'!$B$11:$B$15,0)),0)} -> 1 | J37: =IFERROR(H37*I37,0) -> 0 | K37: =IFERROR(J37/'Tasas de Cambio'!$C$5,0) -> 0 | L37: Día de navegación, incluido en la tarifa del crucero. https://www.royalcaribbean.com/lac/es/itinerary/7-night-italy-croatia-cruise-from-barcelona-on-brilliance-BR07M885?sailDate=2027-05-08&packageCode=BR07M885&groupId=BR07BCN-1768961711&country=COL&search=startDate:2027-05-01~2027-05-31 | M37: 27 ago 2026
A38: Traslados | B38: Venecia | C38: 15 May 2027 | D38: Vaporetti ACTV | E38: EUR | F38: 25 | G38: 2 | H38: =IFERROR(F38*G38,0) -> 50 | I38: {=IFERROR(INDEX('Tasas de Cambio'!$E$11:$E$15,MATCH(E38,'Tasas de Cambio'!$B$11:$B$15,0)),0)} -> 3788.4 | J38: =IFERROR(H38*I38,0) -> 189420 | K38: =IFERROR(J38/2,0) -> 94710 | L38: Boletos de vaporetto (transporte acuático) por Venecia. https://book.tickets-venice.com/es/book/8748/select/?_gl=1%2A1073ils%2A_gcl_aw%2AR0NMLjE3ODc4NzgwODMuRUFJYUlRb2JDaE1JaFpPNjdZekNsZ01Wd1lSYUJSM2Y1U1JPRUFBWUF5QUFFZ0tjeFBEX0J3RQ..%2A_gcl_au%2ANzIxMTA1MTQ5LjE3ODc4NzgwODMuLS4tLjE3ODc4NzgwODMuMTE2MDU2ODc1MS4xNzg3ODc4MDg0LjE3ODc4NzgwODM.%2A_ga%2ANDcyOTU3MzYyLjE3ODc4NzgwODM.%2A_ga_Y45PC9R73C%2AczE3ODc4NzgwODMkbzEkZzAkdDE3ODc4NzgwODQkajU5JGwwJGgw&cookieBanner=false&date=2027-05-15&tourId=15560&variantId=15560 | M38: 27 ago 2026
A39: Vuelos y Trenes | B39: Italia | C39: 15 May 2027 | D39: Tren Ravenna - Venecia St Lucia | E39: EUR | F39: 25 | G39: 2 | H39: =IFERROR(F39*G39,0) -> 50 | I39: {=IFERROR(INDEX('Tasas de Cambio'!$E$11:$E$15,MATCH(E39,'Tasas de Cambio'!$B$11:$B$15,0)),0)} -> 3788.4 | J39: =IFERROR(H39*I39,0) -> 189420 | K39: =IFERROR(J39/2,0) -> 94710 | L39: Tren regional desde Ravenna hasta Venecia Santa Lucia. https://www.trenitalia.com/en.html | M39: 27 ago 2026
A40: Comidas | B40: Salerno (Costa Amalfitana) | C40: 12 May 2027 | D40: Incluida en el crucero (come a bordo) | E40: EUR | F40: 0 | G40: 3 | H40: =IFERROR(F40*G40,0) -> 0 | I40: {=IFERROR(INDEX('Tasas de Cambio'!$E$11:$E$15,MATCH(E40,'Tasas de Cambio'!$B$11:$B$15,0)),0)} -> 3788.4 | J40: =IFERROR(H40*I40,0) -> 0 | K40: =IFERROR(J40/'Tasas de Cambio'!$C$5,0) -> 0 | L40: Comida incluida en el paquete del crucero, sin costo adicional | M40: 27 ago 2026
A41: Comidas | B41: Zadar, Croacia | C41: 14 May 2027 | D41: Incluida en el crucero (come a bordo) | E41: EUR | F41: 0 | G41: 3 | H41: =IFERROR(F41*G41,0) -> 0 | I41: {=IFERROR(INDEX('Tasas de Cambio'!$E$11:$E$15,MATCH(E41,'Tasas de Cambio'!$B$11:$B$15,0)),0)} -> 3788.4 | J41: =IFERROR(H41*I41,0) -> 0 | K41: =IFERROR(J41/'Tasas de Cambio'!$C$5,0) -> 0 | L41: Comida incluida en el paquete del crucero, sin costo adicional | M41: 27 ago 2026

Sheet Crucero 4P
A2: COTIZACIÓN DETALLADA — EUROPA 2027 (05 May – 16 May 2027) | O2: Vuelos y Trenes | P2: EUR
O3: Traslados | P3: CHF
A4: Categoría | B4: Ciudad / País | C4: Fechas | D4: Concepto / Descripción | E4: Moneda | F4: Costo Unitario (moneda original) | G4: Cantidad | H4: Costo Total (moneda original) | I4: Tasa de Cambio a COP | J4: Costo Total (COP) | K4: Costo por Persona (COP) | L4: Notas | M4: Fecha confirmación precio | O4: Alojamiento | P4: CZK
A5: Otros y Extras | B5: — | C5: Durante el viaje | D5: SIM card de viaje (datos internacionales) | E5: USD | F5: 40 | G5: 1 | H5: =IFERROR(F5*G5,0) -> 40 | I5: {=IFERROR(INDEX('Tasas de Cambio'!$E$11:$E$15,MATCH(E5,'Tasas de Cambio'!$B$11:$B$15,0)),0)} -> 3263.4 | J5: =IFERROR(H5*I5,0) -> 130536 | K5: =IFERROR(J5/4,0) -> 32634 | L5: SIM compartida entre las 4 personas para los 11 días del crucero. https://esim.holafly.com/es/esim-europa/?selectedDays=11&startDate=2027-05-06&endDate=2027-05-16 | M5: 28 ago 2026
A6: Otros y Extras | B6: — | C6: Contingencia | D6: Imprevistos / gastos varios (contingencia) | E6: EUR | F6: 200 | G6: 4 | H6: 800 | I6: {=IFERROR(INDEX('Tasas de Cambio'!$E$11:$E$15,MATCH(E6,'Tasas de Cambio'!$B$11:$B$15,0)),0)} -> 3788.4 | J6: 3030720 | K6: =IFERROR(J6/4,0) -> 757680 | O6: Tours y Excursiones | P6: COP
A7: Seguro de Viaje | B7: Internacional | C7: 5 – 16 may 2027 (12 días de cobertura) | D7: Asistencia médica internacional | E7: COP | F7: 221985 | G7: 4 | H7: =IFERROR(F7*G7,0) -> 887940 | I7: {=IFERROR(INDEX('Tasas de Cambio'!$E$11:$E$15,MATCH(E7,'Tasas de Cambio'!$B$11:$B$15,0)),0)} -> 1 | J7: =IFERROR(H7*I7,0) -> 887940 | K7: =IFERROR(J7/4,0) -> 221985 | L7: Asistencia médica internacional, cobertura USD 60.000 (Cuponatic). https://www.cuponatic.com.co/descuento/asistencia-medica-internacional-cobertura-de-usd-60-000?m=tarjetas-de-asistencia&id_descuento=212587 | M7: 27 ago 2026
A8: Vuelos y Trenes | B8: Bogota / Barcelona | C8: 46512 | D8: Vuelo Lufthansa Bogotá → Barcelona (vía FRA), ida | E8: COP | F8: 1491070 | G8: 4 | H8: 5964280 | I8: {=IFERROR(INDEX('Tasas de Cambio'!$E$11:$E$15,MATCH(E8,'Tasas de Cambio'!$B$11:$B$15,0)),0)} -> 1 | J8: 5964280 | K8: =IFERROR(J8/4,0) -> 1491070 | L8: Lufthansa · BOG 23:30 → BCN 23:05 (+1 día) · 1 escala (FRA) · Duración 16h35m · Economy Light. https://shop.lufthansa.com/booking/cart?cartId=1EA66RSYEOGDFEB1&type=cart&shared=true&origin=BOG&utm_source=sharedcart&utm_medium=referral&consent=true | M8: 27 ago 2026
A9: Alojamiento | B9: Barcelona, España | C9: 6 – 8 May (2 noches, pre-crucero) | D9: Hotel Barcelona — costo total (2 noches) | E9: COP | F9: 1750000 | G9: 1 | H9: =IFERROR(F9*G9,0) -> 1750000 | I9: {=IFERROR(INDEX('Tasas de Cambio'!$E$11:$E$15,MATCH(E9,'Tasas de Cambio'!$B$11:$B$15,0)),0)} -> 1 | J9: =IFERROR(H9*I9,0) -> 1750000 | K9: =IFERROR(J9/4,0) -> 437500 | L9: . https://www.booking.com/hotel/es/hostel-casa-gracia.es.html?aid=2311236&label=es-co-booking-desktop-vjGZbEFOhRc3a9njxeT3IwS652829002024%3Apl%3Ata%3Ap1%3Ap2%3Aac%3Aap%3Aneg%3Afi%3Atikwd-65526620%3Alp9246960%3Ali%3Adec%3Adm&sid=f6a1a9bb810c453f7b5f1225205f1f26&all_sr_blocks=25515454_91915475_0_2_0&checkin=2027-05-06&checkout=2027-05-08&dest_id=-372490&dest_type=city&dist=0&group_adults=4&group_children=0&hapos=3&highlighted_blocks=25515454_91915475_0_2_0&hpos=3&matching_block_id=25515454_91915475_0_2_0&no_rooms=1&req_adults=4&req_children=0&room1=A%2CA%2CA%2CA&sb_price_type=total&sr_order=popularity&sr_pri_blocks=25515454_91915475_0_2_0__40490&srepoch=1787961147&srpvid=a7f6a7cce4750f9a&type=total&ucfs=1 | M9: 28 ago 2026
A10: Traslados | B10: España | C10: 46513.0 | D10: Traslado aeropuerto → hotel, Barcelona | E10: EUR | F10: 40 | G10: 1 | H10: =IFERROR(F10*G10,0) -> 40 | I10: {=IFERROR(INDEX('Tasas de Cambio'!$E$11:$E$15,MATCH(E10,'Tasas de Cambio'!$B$11:$B$15,0)),0)} -> 3788.4 | J10: =IFERROR(H10*I10,0) -> 151536 | K10: =IFERROR(J10/4,0) -> 37884 | M10: 28 ago 2026
A11: Comidas | B11: Barcelona | C11: 46513 | D11: cena | E11: EUR | F11: 15 | G11: 4 | H11: 60 | I11: {=IFERROR(INDEX('Tasas de Cambio'!$E$11:$E$15,MATCH(E11,'Tasas de Cambio'!$B$11:$B$15,0)),0)} -> 3788.4 | J11: 227304 | K11: =IFERROR(J11/4,0) -> 56826
A12: Tours y Excursiones | B12: Barcelona | C12: 7 May 2027 | D12: Tour Barcelona Modernista | E12: USD | F12: 10 | G12: 4 | H12: =IFERROR(F12*G12,0) -> 40 | I12: {=IFERROR(INDEX('Tasas de Cambio'!$E$11:$E$15,MATCH(E12,'Tasas de Cambio'!$B$11:$B$15,0)),0)} -> 3263.4 | J12: =IFERROR(H12*I12,0) -> 130536 | K12: =IFERROR(J12/4,0) -> 32634 | L12: Tour guiado por el Modernismo catalán en Barcelona. https://www.civitatis.com/es/barcelona/tour-barcelona-modernista/ | M12: 27 ago 2026
A13: Comidas | B13: Barcelona | C13: 46514 | D13: 3 comidas | E13: EUR | F13: 30 | G13: 4 | H13: 120 | I13: {=IFERROR(INDEX('Tasas de Cambio'!$E$11:$E$15,MATCH(E13,'Tasas de Cambio'!$B$11:$B$15,0)),0)} -> 3788.4 | J13: 454608 | K13: =IFERROR(J13/4,0) -> 113652
A14: Traslados | B14: Barcelona | C14: 46514.0 | D14: Bus, 4 trayectos | E14: EUR | F14: 12 | G14: 4 | H14: =IFERROR(F14*G14,0) -> 48 | I14: {=IFERROR(INDEX('Tasas de Cambio'!$E$11:$E$15,MATCH(E14,'Tasas de Cambio'!$B$11:$B$15,0)),0)} -> 3788.4 | J14: =IFERROR(H14*I14,0) -> 181843.2 | K14: =IFERROR(J14/4,0) -> 45460.8 | M14: 27 ago 2026
A15: Crucero | B15: Mediterráneo | C15: 8 – 15 May (7 noches) | D15: Crucero Barcelona → Ravena — tarifa por persona (cabina) | E15: USD | F15: 2100 | G15: 1 | H15: =IFERROR(F15*G15,0) -> 2100 | I15: {=IFERROR(INDEX('Tasas de Cambio'!$E$11:$E$15,MATCH(E15,'Tasas de Cambio'!$B$11:$B$15,0)),0)} -> 3263.4 | J15: =IFERROR(H15*I15,0) -> 6853140 | K15: =IFERROR(J15/4,0) -> 1713285 | L15: Crucero Barcelona-Ravena, 7 noches, incluye propinas. https://www.royalcaribbean.com/lac/es/itinerary/7-night-italy-croatia-cruise-from-barcelona-on-brilliance-BR07M885?sailDate=2027-05-08&packageCode=BR07M885&groupId=BR07BCN-1768961711&country=COL&search=startDate:2027-05-01~2027-05-31 | M15: 28 ago 2026
A16: Traslados | B16: España | C16: 46515.0 | D16: Traslado hotel → puerto (embarque crucero), Barcelona | E16: EUR | F16: 30 | G16: 1 | H16: =IFERROR(F16*G16,0) -> 30 | I16: {=IFERROR(INDEX('Tasas de Cambio'!$E$11:$E$15,MATCH(E16,'Tasas de Cambio'!$B$11:$B$15,0)),0)} -> 3788.4 | J16: =IFERROR(H16*I16,0) -> 113652 | K16: =IFERROR(J16/4,0) -> 28413 | M16: 28 ago 2026
A17: Tours y Excursiones | B17: Barcelona | C17: 46515 | D17: N/A | E17: EUR | F17: 0 | G17: 3 | H17: 0 | I17: {=IFERROR(INDEX('Tasas de Cambio'!$E$11:$E$15,MATCH(E17,'Tasas de Cambio'!$B$11:$B$15,0)),0)} -> 3788.4 | J17: 0 | K17: =IFERROR(J17/'Tasas de Cambio'!$C$5,0) -> 0
A18: Comidas | B18: Barcelona | C18: 46515 | D18: desayuno | E18: EUR | F18: 10 | G18: 4 | H18: 40 | I18: {=IFERROR(INDEX('Tasas de Cambio'!$E$11:$E$15,MATCH(E18,'Tasas de Cambio'!$B$11:$B$15,0)),0)} -> 3788.4 | J18: 151536 | K18: =IFERROR(J18/4,0) -> 37884
A19: Tours y Excursiones | B19: Navegacion | C19: 46516 | D19: N/A | E19: EUR | F19: 0 | G19: 3 | H19: 0 | I19: {=IFERROR(INDEX('Tasas de Cambio'!$E$11:$E$15,MATCH(E19,'Tasas de Cambio'!$B$11:$B$15,0)),0)} -> 3788.4 | J19: 0 | K19: =IFERROR(J19/'Tasas de Cambio'!$C$5,0) -> 0
A20: Tours y Excursiones | B20: La Spezia (Florencia/Pisa) | C20: 46517.0 | D20: Panoramic Pisa | E20: USD | F20: 70 | G20: 4 | H20: =IFERROR(F20*G20,0) -> 280 | I20: {=IFERROR(INDEX('Tasas de Cambio'!$E$11:$E$15,MATCH(E20,'Tasas de Cambio'!$B$11:$B$15,0)),0)} -> 3263.4 | J20: =IFERROR(H20*I20,0) -> 913752 | K20: =IFERROR(J20/4,0) -> 228438 | L20: Excursión panorámica por Pisa desde el crucero. https://www.royalcaribbean.com/account/cruise-planner/category/shorex/product/Y8RO?bookingId=3113096&shipCode=BR&sailDate=20270508 | M20: 27 ago 2026
A21: Comidas | B21: La Spezia (Florencia/Pisa) | C21: 46517 | D21: Comida | E21: EUR | F21: 25 | G21: 4 | H21: 100 | I21: {=IFERROR(INDEX('Tasas de Cambio'!$E$11:$E$15,MATCH(E21,'Tasas de Cambio'!$B$11:$B$15,0)),0)} -> 3788.4 | J21: 378840 | K21: =IFERROR(J21/4,0) -> 94710
A22: Tours y Excursiones | B22: Civitavecchia (Roma) | C22: 46518.0 | D22: Visit to Rome | E22: USD | F22: 142 | G22: 4 | H22: =IFERROR(F22*G22,0) -> 568 | I22: {=IFERROR(INDEX('Tasas de Cambio'!$E$11:$E$15,MATCH(E22,'Tasas de Cambio'!$B$11:$B$15,0)),0)} -> 3263.4 | J22: =IFERROR(H22*I22,0) -> 1853611.2 | K22: =IFERROR(J22/4,0) -> 463402.8 | L22: Excursión a Roma desde el crucero. https://www.royalcaribbean.com/account/cruise-planner/category/shorex/product/CV1F?bookingId=3113096&shipCode=BR&sailDate=20270508 | M22: 29 ago 2026
A23: Comidas | B23: Civitavecchia (Roma) | C23: 46518 | D23: Comida | E23: EUR | F23: 25 | G23: 4 | H23: 100 | I23: {=IFERROR(INDEX('Tasas de Cambio'!$E$11:$E$15,MATCH(E23,'Tasas de Cambio'!$B$11:$B$15,0)),0)} -> 3788.4 | J23: 378840 | K23: =IFERROR(J23/4,0) -> 94710
A24: Tours y Excursiones | B24: Salerno (Costa Amalfitana) | C24: 46519.0 | D24: Tour a pie gratis | E24: EUR | F24: 0 | G24: 3 | H24: =IFERROR(F24*G24,0) -> 0 | I24: {=IFERROR(INDEX('Tasas de Cambio'!$E$11:$E$15,MATCH(E24,'Tasas de Cambio'!$B$11:$B$15,0)),0)} -> 3788.4 | J24: =IFERROR(H24*I24,0) -> 0 | K24: =IFERROR(J24/'Tasas de Cambio'!$C$5,0) -> 0 | M24: 27 ago 2026
A25: Tours y Excursiones | B25: Navegacion | C25: 46520 | D25: N/A | E25: CZK | F25: 0 | G25: 3 | H25: 0 | I25: {=IFERROR(INDEX('Tasas de Cambio'!$E$11:$E$15,MATCH(E25,'Tasas de Cambio'!$B$11:$B$15,0)),0)} -> 156.97 | J25: 0 | K25: =IFERROR(J25/'Tasas de Cambio'!$C$5,0) -> 0
A26: Traslados | B26: Zadar, Croacia | C26: 46521 | D26: Transporte - Tour a pie gratis | E26: EUR | F26: 10 | G26: 4 | H26: 40 | I26: {=IFERROR(INDEX('Tasas de Cambio'!$E$11:$E$15,MATCH(E26,'Tasas de Cambio'!$B$11:$B$15,0)),0)} -> 3788.4 | J26: 151536 | K26: =IFERROR(J26/4,0) -> 37884
A27: Alojamiento | B27: Venecia, Italia | C27: 15 – 16 May (1 noche, post-crucero) | D27: Hotel Venecia — costo total (1 noche) | E27: COP | F27: 1000000 | G27: 1 | H27: =IFERROR(F27*G27,0) -> 1000000 | I27: {=IFERROR(INDEX('Tasas de Cambio'!$E$11:$E$15,MATCH(E27,'Tasas de Cambio'!$B$11:$B$15,0)),0)} -> 1 | J27: =IFERROR(H27*I27,0) -> 1000000 | K27: =IFERROR(J27/4,0) -> 250000 | L27: . https://www.booking.com/hotel/it/la-perla-tolentini-venice.es.html?aid=2311236&label=es-co-booking-desktop-vjGZbEFOhRc3a9njxeT3IwS652829002024%3Apl%3Ata%3Ap1%3Ap2%3Aac%3Aap%3Aneg%3Afi%3Atikwd-65526620%3Alp9246960%3Ali%3Adec%3Adm&sid=f6a1a9bb810c453f7b5f1225205f1f26&all_sr_blocks=1682202104_439951886_4_2_0&checkin=2027-05-15&checkout=2027-05-16&dest_id=-132007&dest_type=city&dist=0&group_adults=4&group_children=0&hapos=2&highlighted_blocks=1682202104_439951886_4_2_0&hpos=2&matching_block_id=1682202104_439951886_4_2_0&no_rooms=1&req_adults=4&req_children=0&room1=A%2CA%2CA%2CA&sb_price_type=total&sr_order=popularity&sr_pri_blocks=1682202104_439951886_4_2_0__21840&srepoch=1787961062&srpvid=4b2da7a784550840&type=total&ucfs=1 | M27: 28 ago 2026
A28: Traslados | B28: Italia | C28: 46522.0 | D28: Traslado puerto → Estación Ravenna | E28: EUR | F28: 12 | G28: 4 | H28: =IFERROR(F28*G28,0) -> 48 | I28: {=IFERROR(INDEX('Tasas de Cambio'!$E$11:$E$15,MATCH(E28,'Tasas de Cambio'!$B$11:$B$15,0)),0)} -> 3788.4 | J28: =IFERROR(H28*I28,0) -> 181843.2 | K28: =IFERROR(J28/4,0) -> 45460.8 | M28: 27 ago 2026
A29: Comidas | B29: Rávena (Venecia) | C29: 46522 | D29: Almuerzo y cena | E29: EUR | F29: 30 | G29: 4 | H29: 120 | I29: {=IFERROR(INDEX('Tasas de Cambio'!$E$11:$E$15,MATCH(E29,'Tasas de Cambio'!$B$11:$B$15,0)),0)} -> 3788.4 | J29: 454608 | K29: =IFERROR(J29/4,0) -> 113652
A30: Vuelos y Trenes | B30: Venecia / Bogota | C30: 46523 | D30: Vuelo Lufthansa Venecia → Bogotá (vía FRA), regreso | E30: COP | F30: 1491070 | G30: 4 | H30: 5964280 | I30: {=IFERROR(INDEX('Tasas de Cambio'!$E$11:$E$15,MATCH(E30,'Tasas de Cambio'!$B$11:$B$15,0)),0)} -> 1 | J30: 5964280 | K30: =IFERROR(J30/4,0) -> 1491070 | L30: Lufthansa · VCE 10:55 → BOG 18:55 · 1 escala (FRA) · Duración 15h00m · Economy Light. https://shop.lufthansa.com/booking/cart?cartId=1EA66RSYEOGDFEB1&type=cart&shared=true&origin=BOG&utm_source=sharedcart&utm_medium=referral&consent=true | M30: 27 ago 2026
A31: Traslados | B31: Italia | C31: 46523.0 | D31: Traslado hotel → aeropuerto, Venecia | E31: EUR | F31: 30 | G31: 1 | H31: =IFERROR(F31*G31,0) -> 30 | I31: {=IFERROR(INDEX('Tasas de Cambio'!$E$11:$E$15,MATCH(E31,'Tasas de Cambio'!$B$11:$B$15,0)),0)} -> 3788.4 | J31: =IFERROR(H31*I31,0) -> 113652 | K31: =IFERROR(J31/4,0) -> 28413 | M31: 28 ago 2026
A32: Tours y Excursiones | B32: Venecia | C32: 15 May 2027 | D32: Free tour Venecia | E32: EUR | F32: 10 | G32: 4 | H32: =IFERROR(F32*G32,0) -> 40 | I32: {=IFERROR(INDEX('Tasas de Cambio'!$E$11:$E$15,MATCH(E32,'Tasas de Cambio'!$B$11:$B$15,0)),0)} -> 3788.4 | J32: =IFERROR(H32*I32,0) -> 151536 | K32: =IFERROR(J32/4,0) -> 37884 | L32: Free tour guiado por el centro histórico de Venecia. https://www.civitatis.com/es/venecia/free-tour-venecia/?_gl=1*1ijxuzi*_up*MQ..*_ga*ODU4MDQyNjAyLjE3ODc4Nzc2ODY.*_ga_QJQ54CTKPM*czE3ODc4Nzc2ODYkbzEkZzEkdDE3ODc4Nzc2OTEkajU1JGwwJGgxNTA2MDA0ODU0 | M32: 27 ago 2026
A33: Comidas | B33: Venecia | C33: 46523.0 | D33: Desayuno | E33: EUR | F33: 12 | G33: 4 | H33: =IFERROR(F33*G33,0) -> 48 | I33: {=IFERROR(INDEX('Tasas de Cambio'!$E$11:$E$15,MATCH(E33,'Tasas de Cambio'!$B$11:$B$15,0)),0)} -> 3788.4 | J33: =IFERROR(H33*I33,0) -> 181843.2 | K33: =IFERROR(J33/4,0) -> 45460.8 | L33: Almuerzo y cena incluidos en el vuelo de regreso (15h, sale 10:55am) | M33: 28 ago 2026
A34: Tours y Excursiones | B34: Barcelona | C34: 7 May 2027 | D34: Free tour Sagrada Familia | E34: USD | F34: 10 | G34: 4 | H34: =IFERROR(F34*G34,0) -> 40 | I34: {=IFERROR(INDEX('Tasas de Cambio'!$E$11:$E$15,MATCH(E34,'Tasas de Cambio'!$B$11:$B$15,0)),0)} -> 3263.4 | J34: =IFERROR(H34*I34,0) -> 130536 | K34: =IFERROR(J34/4,0) -> 32634 | L34: Free tour guiado por el exterior de la Sagrada Familia. https://www.civitatis.com/es/barcelona/free-tour-sagrada-familia/ | M34: 27 ago 2026
D35: TOTAL GENERAL | J35: =SUM(J5:J33) -> 26823622 | K35: =SUM(K5:K33) -> 8941207.2
A36: Otros y Extras | B36: Navegación | C36: 9 May 2027 | D36: Día de navegación | E36: COP | F36: 0 | G36: 1 | H36: =IFERROR(F36*G36,0) -> 0 | I36: {=IFERROR(INDEX('Tasas de Cambio'!$E$11:$E$15,MATCH(E36,'Tasas de Cambio'!$B$11:$B$15,0)),0)} -> 1 | J36: =IFERROR(H36*I36,0) -> 0 | K36: =IFERROR(J36/'Tasas de Cambio'!$C$5,0) -> 0 | L36: Día de navegación, incluido en la tarifa del crucero. https://www.royalcaribbean.com/lac/es/itinerary/7-night-italy-croatia-cruise-from-barcelona-on-brilliance-BR07M885?sailDate=2027-05-08&packageCode=BR07M885&groupId=BR07BCN-1768961711&country=COL&search=startDate:2027-05-01~2027-05-31 | M36: 27 ago 2026
A37: Otros y Extras | B37: Navegación | C37: 13 May 2027 | D37: Día de navegación | E37: COP | F37: 0 | G37: 1 | H37: =IFERROR(F37*G37,0) -> 0 | I37: {=IFERROR(INDEX('Tasas de Cambio'!$E$11:$E$15,MATCH(E37,'Tasas de Cambio'!$B$11:$B$15,0)),0)} -> 1 | J37: =IFERROR(H37*I37,0) -> 0 | K37: =IFERROR(J37/'Tasas de Cambio'!$C$5,0) -> 0 | L37: Día de navegación, incluido en la tarifa del crucero. https://www.royalcaribbean.com/lac/es/itinerary/7-night-italy-croatia-cruise-from-barcelona-on-brilliance-BR07M885?sailDate=2027-05-08&packageCode=BR07M885&groupId=BR07BCN-1768961711&country=COL&search=startDate:2027-05-01~2027-05-31 | M37: 27 ago 2026
A38: Traslados | B38: Venecia | C38: 15 May 2027 | D38: Vaporetti ACTV | E38: EUR | F38: 25 | G38: 4 | H38: =IFERROR(F38*G38,0) -> 100 | I38: {=IFERROR(INDEX('Tasas de Cambio'!$E$11:$E$15,MATCH(E38,'Tasas de Cambio'!$B$11:$B$15,0)),0)} -> 3788.4 | J38: =IFERROR(H38*I38,0) -> 378840 | K38: =IFERROR(J38/4,0) -> 94710 | L38: Boletos de vaporetto (transporte acuático) por Venecia. https://book.tickets-venice.com/es/book/8748/select/?_gl=1%2A1073ils%2A_gcl_aw%2AR0NMLjE3ODc4NzgwODMuRUFJYUlRb2JDaE1JaFpPNjdZekNsZ01Wd1lSYUJSM2Y1U1JPRUFBWUF5QUFFZ0tjeFBEX0J3RQ..%2A_gcl_au%2ANzIxMTA1MTQ5LjE3ODc4NzgwODMuLS4tLjE3ODc4NzgwODMuMTE2MDU2ODc1MS4xNzg3ODc4MDg0LjE3ODc4NzgwODM.%2A_ga%2ANDcyOTU3MzYyLjE3ODc4NzgwODM.%2A_ga_Y45PC9R73C%2AczE3ODc4NzgwODMkbzEkZzAkdDE3ODc4NzgwODQkajU5JGwwJGgw&cookieBanner=false&date=2027-05-15&tourId=15560&variantId=15560 | M38: 27 ago 2026
A39: Vuelos y Trenes | B39: Italia | C39: 15 May 2027 | D39: Tren Ravenna - Venecia St Lucia | E39: EUR | F39: 25 | G39: 4 | H39: =IFERROR(F39*G39,0) -> 100 | I39: {=IFERROR(INDEX('Tasas de Cambio'!$E$11:$E$15,MATCH(E39,'Tasas de Cambio'!$B$11:$B$15,0)),0)} -> 3788.4 | J39: =IFERROR(H39*I39,0) -> 378840 | K39: =IFERROR(J39/4,0) -> 94710 | L39: Tren regional desde Ravenna hasta Venecia Santa Lucia. https://www.trenitalia.com/en.html | M39: 27 ago 2026
A40: Comidas | B40: Salerno (Costa Amalfitana) | C40: 12 May 2027 | D40: Incluida en el crucero (come a bordo) | E40: EUR | F40: 0 | G40: 3 | H40: =IFERROR(F40*G40,0) -> 0 | I40: {=IFERROR(INDEX('Tasas de Cambio'!$E$11:$E$15,MATCH(E40,'Tasas de Cambio'!$B$11:$B$15,0)),0)} -> 3788.4 | J40: =IFERROR(H40*I40,0) -> 0 | K40: =IFERROR(J40/'Tasas de Cambio'!$C$5,0) -> 0 | L40: Comida incluida en el paquete del crucero, sin costo adicional | M40: 27 ago 2026
A41: Comidas | B41: Zadar, Croacia | C41: 14 May 2027 | D41: Incluida en el crucero (come a bordo) | E41: EUR | F41: 0 | G41: 3 | H41: =IFERROR(F41*G41,0) -> 0 | I41: {=IFERROR(INDEX('Tasas de Cambio'!$E$11:$E$15,MATCH(E41,'Tasas de Cambio'!$B$11:$B$15,0)),0)} -> 3788.4 | J41: =IFERROR(H41*I41,0) -> 0 | K41: =IFERROR(J41/'Tasas de Cambio'!$C$5,0) -> 0 | L41: Comida incluida en el paquete del crucero, sin costo adicional | M41: 27 ago 2026

Sheet Resumen Crucero
B2: RESUMEN DE COTIZACIÓN — EUROPA 2027
B3: 5 de mayo al 16 de mayo de 2027 · 11 días
B5: TOTAL POR CATEGORÍA
B6: Categoría | C6: Total (COP) | D6: Total (USD) | E6: % del total
B7: Vuelos y Trenes | C7: =SUMIF(Crucero!$A:$A,B7,Crucero!$J:$J) -> 8840310 | D7: =IFERROR(C7/'Tasas de Cambio'!$E$14,0) -> 2746.9308 | E7: =IFERROR(C7/$C$15,0) -> 0.32957183
B8: Traslados | C8: =SUMIF(Crucero!$A:$A,B8,Crucero!$J:$J) -> 1241448.6 | D8: =IFERROR(C8/'Tasas de Cambio'!$E$14,0) -> 385.75269 | E8: =IFERROR(C8/$C$15,0) -> 0.046281916
B9: Alojamiento | C9: =SUMIF(Crucero!$A:$A,B9,Crucero!$J:$J) -> 3450552 | D9: =IFERROR(C9/'Tasas de Cambio'!$E$14,0) -> 1072.1827 | E9: =IFERROR(C9/$C$15,0) -> 0.12863856
B10: Crucero | C10: =SUMIF(Crucero!$A:$A,B10,Crucero!$J:$J) -> 6468682.5 | D10: =IFERROR(C10/'Tasas de Cambio'!$E$14,0) -> 2010 | E10: =IFERROR(C10/$C$15,0) -> 0.24115619
B11: Tours y Excursiones | C11: =SUMIF(Crucero!$A:$A,B11,Crucero!$J:$J) -> 2171956.5 | D11: =IFERROR(C11/'Tasas de Cambio'!$E$14,0) -> 674.88744 | E11: =IFERROR(C11/$C$15,0) -> 0.080971784
B12: Comidas | C12: =SUMIF(Crucero!$A:$A,B12,Crucero!$J:$J) -> 1800288 | D12: =IFERROR(C12/'Tasas de Cambio'!$E$14,0) -> 559.39967 | E12: =IFERROR(C12/$C$15,0) -> 0.067115769
B13: Seguro de Viaje | C13: =SUMIF(Crucero!$A:$A,B13,Crucero!$J:$J) -> 450000 | D13: =IFERROR(C13/'Tasas de Cambio'!$E$14,0) -> 139.82755 | E13: =IFERROR(C13/$C$15,0) -> 0.016776258
B14: Otros y Extras | C14: =SUMIF(Crucero!$A:$A,B14,Crucero!$J:$J) -> 2400384 | D14: =IFERROR(C14/'Tasas de Cambio'!$E$14,0) -> 745.86623 | E14: =IFERROR(C14/$C$15,0) -> 0.089487692
B15: TOTAL GENERAL | C15: =SUM(C7:C14) -> 26823622 | D15: =SUM(D7:D14) -> 8334.8471
B17: COSTO POR PERSONA
B18: Número de personas | C18: ='Tasas de Cambio'!$C$5 -> 3
B19: Costo por persona (COP) | C19: =IFERROR($C$15/'Tasas de Cambio'!$C$5,0) -> 8941207.2
B20: Costo por persona (USD) | C20: =IFERROR($D$15/'Tasas de Cambio'!$C$5,0) -> 2778.2824
B21: Costo promedio por persona / día (COP) | C21: =IFERROR(C19/11,0) -> 812837.02
B23: TASAS DE CAMBIO UTILIZADAS
B24: Moneda | C24: Tasa a COP
B25: ='Tasas de Cambio'!$B$11 -> EUR | C25: ='Tasas de Cambio'!$E$11 -> 3750.6
B26: ='Tasas de Cambio'!$B$12 -> CHF | C26: ='Tasas de Cambio'!$E$12 -> 4053
B27: ='Tasas de Cambio'!$B$13 -> CZK | C27: ='Tasas de Cambio'!$E$13 -> 155.82
B28: ='Tasas de Cambio'!$B$14 -> USD | C28: ='Tasas de Cambio'!$E$14 -> 3218.25
B29: ='Tasas de Cambio'!$B$15 -> COP | C29: ='Tasas de Cambio'!$E$15 -> 1
B31: Cifras referenciales — sujetas a disponibilidad, temporada y tasa de cambio del día de pago. Documento generado como herramienta de cotización, no constituye una tarifa garantizada.

Sheet Crucero Milan
A2: COTIZACIÓN DETALLADA — EUROPA 2027 (01 May – 16 May 2027) — OPCIÓN 4: MÚNICH en vez de ZÚRICH | O2: Vuelos y Trenes | P2: EUR
O3: Traslados | P3: CHF
A4: Categoría | B4: Ciudad / País | C4: Fechas | D4: Concepto / Descripción | E4: Moneda | F4: Costo Unitario (moneda original) | G4: Cantidad | H4: Costo Total (moneda original) | I4: Tasa de Cambio a COP | J4: Costo Total (COP) | K4: Costo por Persona (COP) | L4: Notas | M4: Fecha confirmación precio | O4: Alojamiento | P4: CZK
A5: Vuelos y Trenes | B5: Milán | C5: 1 May 2027 | D5: Bus Venecia → Milán (FlixBus) | E5: EUR | F5: 65.73 | G5: 1 | H5: =IFERROR(F5*G5,0) -> 65.73 | I5: {=IFERROR(INDEX('Tasas de Cambio'!$E$11:$E$15,MATCH(E5,'Tasas de Cambio'!$B$11:$B$15,0)),0)} -> 3788.4 | J5: =IFERROR(H5*I5,0) -> 249011.53 | K5: =IFERROR(J5/'Tasas de Cambio'!$C$5,0) -> 83003.844 | L5: FlixBus nocturno, Aeropuerto Marco Polo → Estación Lampugnano, 19:20-00:15. Reserva #3392231315. | M5: 11 sep 2026
A6: Traslados | B6: Milán | C6: 2 May 2027 | D6: Traslado estación de autobuses → hotel, Milán | E6: EUR | F6: 15 | G6: 1 | H6: =IFERROR(F6*G6,0) -> 15 | I6: {=IFERROR(INDEX('Tasas de Cambio'!$E$11:$E$15,MATCH(E6,'Tasas de Cambio'!$B$11:$B$15,0)),0)} -> 3788.4 | J6: =IFERROR(H6*I6,0) -> 56826 | K6: =IFERROR(J6/'Tasas de Cambio'!$C$5,0) -> 18942 | L6: Estimado: taxi corto desde Lampugnano al hotel (llegada 00:15), ~15-20 min, €15-20. | M6: 11 sep 2026
A7: Otros y Extras | B7: Navegación | C7: 9 May 2027 | D7: Día de navegación | E7: COP | F7: 0 | G7: 1 | H7: =IFERROR(F7*G7,0) -> 0 | I7: {=IFERROR(INDEX('Tasas de Cambio'!$E$11:$E$15,MATCH(E7,'Tasas de Cambio'!$B$11:$B$15,0)),0)} -> 1 | J7: =IFERROR(H7*I7,0) -> 0 | K7: =IFERROR(J7/'Tasas de Cambio'!$C$5,0) -> 0 | L7: Día de navegación, incluido en la tarifa del crucero. https://www.royalcaribbean.com/lac/es/itinerary/7-night-italy-croatia-cruise-from-barcelona-on-brilliance-BR07M885?sailDate=2027-05-08&packageCode=BR07M885&groupId=BR07BCN-1768961711&country=COL&search=startDate:2027-05-01~2027-05-31 | M7: 27 ago 2026
A8: Otros y Extras | B8: Navegación | C8: 13 May 2027 | D8: Día de navegación | E8: COP | F8: 0 | G8: 1 | H8: =IFERROR(F8*G8,0) -> 0 | I8: {=IFERROR(INDEX('Tasas de Cambio'!$E$11:$E$15,MATCH(E8,'Tasas de Cambio'!$B$11:$B$15,0)),0)} -> 1 | J8: =IFERROR(H8*I8,0) -> 0 | K8: =IFERROR(J8/'Tasas de Cambio'!$C$5,0) -> 0 | L8: Día de navegación, incluido en la tarifa del crucero. https://www.royalcaribbean.com/lac/es/itinerary/7-night-italy-croatia-cruise-from-barcelona-on-brilliance-BR07M885?sailDate=2027-05-08&packageCode=BR07M885&groupId=BR07BCN-1768961711&country=COL&search=startDate:2027-05-01~2027-05-31 | M8: 27 ago 2026
A9: Traslados | B9: Venecia | C9: 15 May 2027 | D9: Vaporetti ACTV | E9: EUR | F9: 25 | G9: 3 | H9: =IFERROR(F9*G9,0) -> 75 | I9: {=IFERROR(INDEX('Tasas de Cambio'!$E$11:$E$15,MATCH(E9,'Tasas de Cambio'!$B$11:$B$15,0)),0)} -> 3788.4 | J9: =IFERROR(H9*I9,0) -> 284130 | K9: =IFERROR(J9/'Tasas de Cambio'!$C$5,0) -> 94710 | L9: Boletos de vaporetto (transporte acuático) por Venecia. https://book.tickets-venice.com/es/book/8748/select/?_gl=1%2A1073ils%2A_gcl_aw%2AR0NMLjE3ODc4NzgwODMuRUFJYUlRb2JDaE1JaFpPNjdZekNsZ01Wd1lSYUJSM2Y1U1JPRUFBWUF5QUFFZ0tjeFBEX0J3RQ..%2A_gcl_au%2ANzIxMTA1MTQ5LjE3ODc4NzgwODMuLS4tLjE3ODc4NzgwODMuMTE2MDU2ODc1MS4xNzg3ODc4MDg0LjE3ODc4NzgwODM.%2A_ga%2ANDcyOTU3MzYyLjE3ODc4NzgwODM.%2A_ga_Y45PC9R73C%2AczE3ODc4NzgwODMkbzEkZzAkdDE3ODc4NzgwODQkajU5JGwwJGgw&cookieBanner=false&date=2027-05-15&tourId=15560&variantId=15560 | M9: 27 ago 2026
A10: Otros y Extras | C10: Durante el viaje | D10: SIM card de viaje (datos internacionales) | E10: USD | F10: 52 | G10: 1 | H10: 52 | I10: {=IFERROR(INDEX('Tasas de Cambio'!$E$11:$E$15,MATCH(E10,'Tasas de Cambio'!$B$11:$B$15,0)),0)} -> 3263.4 | J10: 169696.8 | K10: =IFERROR(J10/'Tasas de Cambio'!$C$5,0) -> 56565.6 | L10: SIM compartida entre las 3 personas para los 16 días del viaje. https://esim.holafly.com/es/esim-europa/?selectedDays=16&startDate=2027-05-01&endDate=2027-05-16 | M10: 27 ago 2026
A11: Otros y Extras | C11: Contingencia | D11: Imprevistos / gastos varios (contingencia) | E11: EUR | F11: 200 | G11: 3 | H11: 600 | I11: {=IFERROR(INDEX('Tasas de Cambio'!$E$11:$E$15,MATCH(E11,'Tasas de Cambio'!$B$11:$B$15,0)),0)} -> 3788.4 | J11: 2273040 | K11: =IFERROR(J11/'Tasas de Cambio'!$C$5,0) -> 757680
A12: Vuelos y Trenes | B12: Bogota / Venecia | C12: 30 Abr 2027 | D12: Vuelo internacional Bogotá → Venecia (ida) | E12: COP | F12: 1500000 | G12: 3 | H12: =IFERROR(F12*G12,0) -> 4500000 | I12: {=IFERROR(INDEX('Tasas de Cambio'!$E$11:$E$15,MATCH(E12,'Tasas de Cambio'!$B$11:$B$15,0)),0)} -> 1 | J12: =IFERROR(H12*I12,0) -> 4500000 | K12: =IFERROR(J12/'Tasas de Cambio'!$C$5,0) -> 1500000 | L12: Air Europa UX194, BOG 20:15 (hora Colombia) → MAD 13:00 (+1, local); UX1083 → VCE 17:45 local. | M12: 11 sep 2026
A14: Alojamiento | B14: Milán, Italia | C14: 1 – 4 May (3 noches) | D14: Hotel Milán — costo total (3 noches) | E14: COP | F14: 2020000 | G14: 1 | H14: =IFERROR(F14*G14,0) -> 2020000 | I14: {=IFERROR(INDEX('Tasas de Cambio'!$E$11:$E$15,MATCH(E14,'Tasas de Cambio'!$B$11:$B$15,0)),0)} -> 1 | J14: =IFERROR(H14*I14,0) -> 2020000 | K14: =IFERROR(J14/'Tasas de Cambio'!$C$5,0) -> 673333.33 | L14: Franca's Apartment Milano, 3 noches, tarifa total confirmada. https://www.booking.com/hotel/it/francas-apartment-milano17.es.html?aid=304142&label=gen173nr-10CA4oggI46AdIClgEaDKIAQGYATO4AQfIAQzYAQPoAQH4AQGIAgGoAgG4AsCS0tQGwAIB0gIkOGVkYmE2NGQtNGY0OS00MTU4LTgzNzAtZGVlNWVjY2Y3NmE32AIB4AIB&sid=f6a1a9bb810c453f7b5f1225205f1f26&all_sr_blocks=1429932801_439269609_3_0_0&checkin=2027-05-01&checkout=2027-05-04&dest_id=2303&dest_type=district&dist=0&group_adults=3&group_children=0&hapos=7&highlighted_blocks=1429932801_439269609_3_0_0&hpos=7&matching_block_id=1429932801_439269609_3_0_0&nflt=fc%3D2&no_rooms=1&req_adults=3&req_children=0&room1=A%2CA%2CA&sb_price_type=total&sr_order=popularity&sr_pri_blocks=1429932801_439269609_3_0_0__41616&srepoch=1788119649&srpvid=1eb98b8ab11b1a94&type=total&ucfs=1 | M14: 30 ago 2026
A15: Seguro de Viaje | B15: Internacional | C15: 1 – 16 may 2027 (16 días de cobertura) | D15: Asistencia médica internacional | E15: COP | F15: 295980 | G15: 3 | H15: =IFERROR(F15*G15,0) -> 887940 | I15: {=IFERROR(INDEX('Tasas de Cambio'!$E$11:$E$15,MATCH(E15,'Tasas de Cambio'!$B$11:$B$15,0)),0)} -> 1 | J15: =IFERROR(H15*I15,0) -> 887940 | K15: =IFERROR(J15/'Tasas de Cambio'!$C$5,0) -> 295980 | L15: Asistencia médica internacional, cobertura USD 60.000 (Cuponatic). https://www.cuponatic.com.co/descuento/asistencia-medica-internacional-cobertura-de-usd-60-000?m=tarjetas-de-asistencia&id_descuento=212587 | M15: 27 ago 2026
A16: Vuelos y Trenes | B16: Milán / Florencia | C16: 4 May 2027 | D16: Tren Milán → Florencia, directo | E16: EUR | F16: 25 | G16: 3 | H16: =IFERROR(F16*G16,0) -> 75 | I16: {=IFERROR(INDEX('Tasas de Cambio'!$E$11:$E$15,MATCH(E16,'Tasas de Cambio'!$B$11:$B$15,0)),0)} -> 3788.4 | J16: =IFERROR(H16*I16,0) -> 284130 | K16: =IFERROR(J16/'Tasas de Cambio'!$C$5,0) -> 94710 | L16: Frecciarossa, sale temprano ~6:05am, directo, ~1h54m | M16: 29 ago 2026
A17: Tours y Excursiones | B17: Milán | C17: 46509.0 | D17: Alpine Wonders: almuerzo en Diavolezza y tren Bernina | E17: USD | F17: 250 | G17: 3 | H17: =IFERROR(F17*G17,0) -> 750 | I17: {=IFERROR(INDEX('Tasas de Cambio'!$E$11:$E$15,MATCH(E17,'Tasas de Cambio'!$B$11:$B$15,0)),0)} -> 3263.4 | J17: =IFERROR(H17*I17,0) -> 2447550 | K17: =IFERROR(J17/'Tasas de Cambio'!$C$5,0) -> 815850 | L17: Excursión de día completo desde Milán, tren panorámico Bernina. https://www.tripadvisor.com/AttractionProductReview-g187849-d15090556-From_Milan_Alpine_Wonders_Lunch_at_Diavolezza_and_Bernina_Train-Milan_Lombardy.html | M17: 28 ago 2026
A18: Comidas | B18: Milán | C18: 46509.0 | D18: Comida del día (desayuno, almuerzo y cena) | E18: EUR | F18: 40 | G18: 3 | H18: =IFERROR(F18*G18,0) -> 120 | I18: {=IFERROR(INDEX('Tasas de Cambio'!$E$11:$E$15,MATCH(E18,'Tasas de Cambio'!$B$11:$B$15,0)),0)} -> 3788.4 | J18: =IFERROR(H18*I18,0) -> 454608 | K18: =IFERROR(J18/'Tasas de Cambio'!$C$5,0) -> 151536 | L18: Estimado: ~€40/persona/día (desayuno+almuerzo+cena) | M18: 28 ago 2026
A20: Comidas | B20: Milán | C20: 46510.0 | D20: Comida del día (desayuno, almuerzo y cena) | E20: EUR | F20: 40 | G20: 3 | H20: =IFERROR(F20*G20,0) -> 120 | I20: {=IFERROR(INDEX('Tasas de Cambio'!$E$11:$E$15,MATCH(E20,'Tasas de Cambio'!$B$11:$B$15,0)),0)} -> 3788.4 | J20: =IFERROR(H20*I20,0) -> 454608 | K20: =IFERROR(J20/'Tasas de Cambio'!$C$5,0) -> 151536 | L20: Estimado: ~€40/persona/día (desayuno+almuerzo+cena) | M20: 28 ago 2026
A21: Tours y Excursiones | B21: Milán | C21: 3 May 2027 | D21: Duomo di Milano y terrazas (entrada) | E21: EUR | F21: 16 | G21: 3 | H21: =IFERROR(F21*G21,0) -> 48 | I21: {=IFERROR(INDEX('Tasas de Cambio'!$E$11:$E$15,MATCH(E21,'Tasas de Cambio'!$B$11:$B$15,0)),0)} -> 3788.4 | J21: =IFERROR(H21*I21,0) -> 181843.2 | K21: =IFERROR(J21/'Tasas de Cambio'!$C$5,0) -> 60614.4 | L21: Entrada terrazas con ascensor, precio oficial. https://ticket.duomomilano.it/en/categoria/terrazze/ | M21: 30 ago 2026
A22: Comidas | B22: Florencia | C22: 46511.0 | D22: Comida del día (desayuno, almuerzo y cena) | E22: EUR | F22: 40 | G22: 3 | H22: =IFERROR(F22*G22,0) -> 120 | I22: {=IFERROR(INDEX('Tasas de Cambio'!$E$11:$E$15,MATCH(E22,'Tasas de Cambio'!$B$11:$B$15,0)),0)} -> 3788.4 | J22: =IFERROR(H22*I22,0) -> 454608 | K22: =IFERROR(J22/'Tasas de Cambio'!$C$5,0) -> 151536 | L22: Estimado: ~€40/persona/día (desayuno+almuerzo+cena) | M22: 29 ago 2026
A23: Comidas | B23: Florencia | C23: 46512.0 | D23: Comida del día (desayuno, almuerzo y cena) | E23: EUR | F23: 40 | G23: 3 | H23: =IFERROR(F23*G23,0) -> 120 | I23: {=IFERROR(INDEX('Tasas de Cambio'!$E$11:$E$15,MATCH(E23,'Tasas de Cambio'!$B$11:$B$15,0)),0)} -> 3788.4 | J23: =IFERROR(H23*I23,0) -> 454608 | K23: =IFERROR(J23/'Tasas de Cambio'!$C$5,0) -> 151536 | L23: Estimado: ~€40/persona/día (desayuno+almuerzo+cena) | M23: 29 ago 2026
A24: Alojamiento | B24: Barcelona, España | C24: 6 – 8 May (2 noches, pre-crucero) | D24: Hotel Barcelona — costo total (2 noches) | E24: COP | F24: 1900000 | G24: 1 | H24: =IFERROR(F24*G24,0) -> 1900000 | I24: {=IFERROR(INDEX('Tasas de Cambio'!$E$11:$E$15,MATCH(E24,'Tasas de Cambio'!$B$11:$B$15,0)),0)} -> 1 | J24: =IFERROR(H24*I24,0) -> 1900000 | K24: =IFERROR(J24/'Tasas de Cambio'!$C$5,0) -> 633333.33 | L24: Sagrada Familia, 2 noches (6-8 may). https://www.booking.com/hotel/es/sagradafamilia.es.html?aid=2311236&label=es-co-booking-desktop-vjGZbEFOhRc3a9njxeT3IwS652829002024%3Apl%3Ata%3Ap1%3Ap2%3Aac%3Aap%3Aneg%3Afi%3Atikwd-65526620%3Alp9246960%3Ali%3Adec%3Adm&sid=f6a1a9bb810c453f7b5f1225205f1f26&all_sr_blocks=9118812_91908190_0_2_0&checkin=2027-05-06&checkout=2027-05-08&dest_id=-372490&dest_type=city&dist=0&group_adults=3&group_children=0&hapos=1&highlighted_blocks=9118812_91908190_0_2_0&hpos=1&matching_block_id=9118812_91908190_0_2_0&no_rooms=1&req_adults=3&req_children=0&room1=A%2CA%2CA&sb_price_type=total&sr_order=popularity&sr_pri_blocks=9118812_91908190_0_2_0__37600&srepoch=1787875557&srpvid=a2d600b07c230149&type=total&ucfs=1 | M24: 27 ago 2026
A25: Vuelos y Trenes | B25: Florencia / Barcelona | C25: 46513.0 | D25: Vuelo Florencia → Barcelona, directo | E25: EUR | F25: 25 | G25: 3 | H25: =IFERROR(F25*G25,0) -> 75 | I25: {=IFERROR(INDEX('Tasas de Cambio'!$E$11:$E$15,MATCH(E25,'Tasas de Cambio'!$B$11:$B$15,0)),0)} -> 3788.4 | J25: =IFERROR(H25*I25,0) -> 284130 | K25: =IFERROR(J25/'Tasas de Cambio'!$C$5,0) -> 94710 | L25: Estimado: Vueling, tarifa básica solo maleta de mano | M25: 29 ago 2026
A26: Traslados | B26: Italia | C26: 4 May 2027 | D26: Traslado hotel → Estación Milano Centrale | E26: EUR | F26: 15 | G26: 1 | H26: =IFERROR(F26*G26,0) -> 15 | I26: {=IFERROR(INDEX('Tasas de Cambio'!$E$11:$E$15,MATCH(E26,'Tasas de Cambio'!$B$11:$B$15,0)),0)} -> 3788.4 | J26: =IFERROR(H26*I26,0) -> 56826 | K26: =IFERROR(J26/'Tasas de Cambio'!$C$5,0) -> 18942 | L26: Estimado: taxi corto centro Milán (1 carro para el grupo) | M26: 29 ago 2026
A27: Traslados | B27: España | C27: 46513.0 | D27: Traslado aeropuerto → hotel, Barcelona | E27: EUR | F27: 40 | G27: 1 | H27: =IFERROR(F27*G27,0) -> 40 | I27: {=IFERROR(INDEX('Tasas de Cambio'!$E$11:$E$15,MATCH(E27,'Tasas de Cambio'!$B$11:$B$15,0)),0)} -> 3788.4 | J27: =IFERROR(H27*I27,0) -> 151536 | K27: =IFERROR(J27/'Tasas de Cambio'!$C$5,0) -> 50512 | M27: 27 ago 2026
A28: Comidas | B28: Barcelona | C28: 46513 | D28: cena | E28: EUR | F28: 15 | G28: 3 | H28: 45 | I28: {=IFERROR(INDEX('Tasas de Cambio'!$E$11:$E$15,MATCH(E28,'Tasas de Cambio'!$B$11:$B$15,0)),0)} -> 3788.4 | J28: 170478 | K28: =IFERROR(J28/'Tasas de Cambio'!$C$5,0) -> 56826
A29: Vuelos y Trenes | B29: Italia | C29: 15 May 2027 | D29: Tren Ravenna - Venecia St Lucia | E29: EUR | F29: 25 | G29: 3 | H29: =IFERROR(F29*G29,0) -> 75 | I29: {=IFERROR(INDEX('Tasas de Cambio'!$E$11:$E$15,MATCH(E29,'Tasas de Cambio'!$B$11:$B$15,0)),0)} -> 3788.4 | J29: =IFERROR(H29*I29,0) -> 284130 | K29: =IFERROR(J29/'Tasas de Cambio'!$C$5,0) -> 94710 | L29: Tren regional desde Ravenna hasta Venecia Santa Lucia. https://www.trenitalia.com/en.html | M29: 27 ago 2026
A30: Comidas | B30: Barcelona | C30: 46514 | D30: 3 comidas | E30: EUR | F30: 30 | G30: 3 | H30: 90 | I30: {=IFERROR(INDEX('Tasas de Cambio'!$E$11:$E$15,MATCH(E30,'Tasas de Cambio'!$B$11:$B$15,0)),0)} -> 3788.4 | J30: 340956 | K30: =IFERROR(J30/'Tasas de Cambio'!$C$5,0) -> 113652
A31: Traslados | B31: Barcelona | C31: 46514.0 | D31: Bus, 4 trayectos | E31: EUR | F31: 12 | G31: 3 | H31: =IFERROR(F31*G31,0) -> 36 | I31: {=IFERROR(INDEX('Tasas de Cambio'!$E$11:$E$15,MATCH(E31,'Tasas de Cambio'!$B$11:$B$15,0)),0)} -> 3788.4 | J31: =IFERROR(H31*I31,0) -> 136382.4 | K31: =IFERROR(J31/'Tasas de Cambio'!$C$5,0) -> 45460.8 | M31: 27 ago 2026
A32: Crucero | B32: Mediterráneo | C32: 8 – 15 May (7 noches) | D32: Crucero Barcelona → Ravena — tarifa por persona (cabina) | E32: USD | F32: 670 | G32: 3 | H32: =IFERROR(F32*G32,0) -> 2010 | I32: {=IFERROR(INDEX('Tasas de Cambio'!$E$11:$E$15,MATCH(E32,'Tasas de Cambio'!$B$11:$B$15,0)),0)} -> 3263.4 | J32: =IFERROR(H32*I32,0) -> 6559434 | K32: =IFERROR(J32/'Tasas de Cambio'!$C$5,0) -> 2186478 | L32: Crucero Barcelona-Ravena, 7 noches, incluye propinas. https://www.royalcaribbean.com/lac/es/itinerary/7-night-italy-croatia-cruise-from-barcelona-on-brilliance-BR07M885?sailDate=2027-05-08&packageCode=BR07M885&groupId=BR07BCN-1768961711&country=COL&search=startDate:2027-05-01~2027-05-31 | M32: 27 ago 2026
A33: Traslados | B33: España | C33: 46515 | D33: Traslado hotel → puerto (embarque crucero), Barcelona | E33: EUR | F33: 30 | G33: 1 | H33: 30 | I33: {=IFERROR(INDEX('Tasas de Cambio'!$E$11:$E$15,MATCH(E33,'Tasas de Cambio'!$B$11:$B$15,0)),0)} -> 3788.4 | J33: 113652 | K33: =IFERROR(J33/'Tasas de Cambio'!$C$5,0) -> 37884
A34: Tours y Excursiones | B34: Barcelona | C34: 46515 | D34: N/A | E34: EUR | F34: 0 | G34: 3 | H34: 0 | I34: {=IFERROR(INDEX('Tasas de Cambio'!$E$11:$E$15,MATCH(E34,'Tasas de Cambio'!$B$11:$B$15,0)),0)} -> 3788.4 | J34: 0 | K34: =IFERROR(J34/'Tasas de Cambio'!$C$5,0) -> 0
A35: Comidas | B35: Barcelona | C35: 46515 | D35: desayuno | E35: EUR | F35: 10 | G35: 3 | H35: 30 | I35: {=IFERROR(INDEX('Tasas de Cambio'!$E$11:$E$15,MATCH(E35,'Tasas de Cambio'!$B$11:$B$15,0)),0)} -> 3788.4 | J35: 113652 | K35: =IFERROR(J35/'Tasas de Cambio'!$C$5,0) -> 37884
A36: Tours y Excursiones | B36: Navegacion | C36: 46516 | D36: N/A | E36: EUR | F36: 0 | G36: 3 | H36: 0 | I36: {=IFERROR(INDEX('Tasas de Cambio'!$E$11:$E$15,MATCH(E36,'Tasas de Cambio'!$B$11:$B$15,0)),0)} -> 3788.4 | J36: 0 | K36: =IFERROR(J36/'Tasas de Cambio'!$C$5,0) -> 0
A37: Tours y Excursiones | B37: La Spezia (Florencia/Pisa) | C37: 46517.0 | D37: Panoramic Pisa | E37: USD | F37: 70 | G37: 3 | H37: =IFERROR(F37*G37,0) -> 210 | I37: {=IFERROR(INDEX('Tasas de Cambio'!$E$11:$E$15,MATCH(E37,'Tasas de Cambio'!$B$11:$B$15,0)),0)} -> 3263.4 | J37: =IFERROR(H37*I37,0) -> 685314 | K37: =IFERROR(J37/'Tasas de Cambio'!$C$5,0) -> 228438 | L37: Excursión panorámica por Pisa desde el crucero. https://www.royalcaribbean.com/account/cruise-planner/category/shorex/product/Y8RO?bookingId=3113096&shipCode=BR&sailDate=20270508 | M37: 27 ago 2026
A38: Comidas | B38: La Spezia (Florencia/Pisa) | C38: 46517.0 | D38: Almuerzo en tierra | E38: EUR | F38: 25 | G38: 3 | H38: =IFERROR(F38*G38,0) -> 75 | I38: {=IFERROR(INDEX('Tasas de Cambio'!$E$11:$E$15,MATCH(E38,'Tasas de Cambio'!$B$11:$B$15,0)),0)} -> 3788.4 | J38: =IFERROR(H38*I38,0) -> 284130 | K38: =IFERROR(J38/'Tasas de Cambio'!$C$5,0) -> 94710 | L38: Desayuno y cena incluidos en el crucero, almuerzo en Pisa/Florencia | M38: 28 ago 2026
A39: Tours y Excursiones | B39: Civitavecchia (Roma) | C39: 46518.0 | D39: Visit to Rome | E39: USD | F39: 142 | G39: 3 | H39: =IFERROR(F39*G39,0) -> 426 | I39: {=IFERROR(INDEX('Tasas de Cambio'!$E$11:$E$15,MATCH(E39,'Tasas de Cambio'!$B$11:$B$15,0)),0)} -> 3263.4 | J39: =IFERROR(H39*I39,0) -> 1390208.4 | K39: =IFERROR(J39/'Tasas de Cambio'!$C$5,0) -> 463402.8 | L39: Excursión a Roma desde el crucero. https://www.royalcaribbean.com/account/cruise-planner/category/shorex/product/CV1F?bookingId=3113096&shipCode=BR&sailDate=20270508 | M39: 29 ago 2026
A40: Comidas | B40: Civitavecchia (Roma) | C40: 46518.0 | D40: Almuerzo en tierra | E40: EUR | F40: 25 | G40: 3 | H40: =IFERROR(F40*G40,0) -> 75 | I40: {=IFERROR(INDEX('Tasas de Cambio'!$E$11:$E$15,MATCH(E40,'Tasas de Cambio'!$B$11:$B$15,0)),0)} -> 3788.4 | J40: =IFERROR(H40*I40,0) -> 284130 | K40: =IFERROR(J40/'Tasas de Cambio'!$C$5,0) -> 94710 | L40: Desayuno y cena incluidos en el crucero, almuerzo en Roma | M40: 28 ago 2026
A41: Tours y Excursiones | B41: Salerno (Costa Amalfitana) | C41: 46519.0 | D41: Tour a pie gratis | E41: EUR | F41: 0 | G41: 3 | H41: =IFERROR(F41*G41,0) -> 0 | I41: {=IFERROR(INDEX('Tasas de Cambio'!$E$11:$E$15,MATCH(E41,'Tasas de Cambio'!$B$11:$B$15,0)),0)} -> 3788.4 | J41: =IFERROR(H41*I41,0) -> 0 | K41: =IFERROR(J41/'Tasas de Cambio'!$C$5,0) -> 0 | M41: 27 ago 2026
A42: Comidas | B42: Salerno (Costa Amalfitana) | C42: 46519.0 | D42: Incluida en el crucero (come a bordo) | E42: EUR | F42: 0 | G42: 3 | H42: =IFERROR(F42*G42,0) -> 0 | I42: {=IFERROR(INDEX('Tasas de Cambio'!$E$11:$E$15,MATCH(E42,'Tasas de Cambio'!$B$11:$B$15,0)),0)} -> 3788.4 | J42: =IFERROR(H42*I42,0) -> 0 | K42: =IFERROR(J42/'Tasas de Cambio'!$C$5,0) -> 0 | L42: Comida incluida en el paquete del crucero, sin costo adicional | M42: 27 ago 2026
A43: Tours y Excursiones | B43: Navegacion | C43: 46520 | D43: N/A | E43: CZK | F43: 0 | G43: 3 | H43: 0 | I43: {=IFERROR(INDEX('Tasas de Cambio'!$E$11:$E$15,MATCH(E43,'Tasas de Cambio'!$B$11:$B$15,0)),0)} -> 156.97 | J43: 0 | K43: =IFERROR(J43/'Tasas de Cambio'!$C$5,0) -> 0
A44: Traslados | B44: Zadar, Croacia | C44: 46521 | D44: Transporte - Tour a pie gratis | E44: EUR | F44: 10 | G44: 3 | H44: 30 | I44: {=IFERROR(INDEX('Tasas de Cambio'!$E$11:$E$15,MATCH(E44,'Tasas de Cambio'!$B$11:$B$15,0)),0)} -> 3788.4 | J44: 113652 | K44: =IFERROR(J44/'Tasas de Cambio'!$C$5,0) -> 37884
A45: Comidas | B45: Zadar, Croacia | C45: 46521.0 | D45: Incluida en el crucero (come a bordo) | E45: EUR | F45: 0 | G45: 3 | H45: =IFERROR(F45*G45,0) -> 0 | I45: {=IFERROR(INDEX('Tasas de Cambio'!$E$11:$E$15,MATCH(E45,'Tasas de Cambio'!$B$11:$B$15,0)),0)} -> 3788.4 | J45: =IFERROR(H45*I45,0) -> 0 | K45: =IFERROR(J45/'Tasas de Cambio'!$C$5,0) -> 0 | L45: Comida incluida en el paquete del crucero, sin costo adicional | M45: 27 ago 2026
A46: Alojamiento | B46: Venecia, Italia | C46: 15 – 16 May (1 noche, post-crucero) | D46: Hotel Venecia — costo total (1 noche) | E46: EUR | F46: 400 | G46: 1 | H46: =IFERROR(F46*G46,0) -> 400 | I46: {=IFERROR(INDEX('Tasas de Cambio'!$E$11:$E$15,MATCH(E46,'Tasas de Cambio'!$B$11:$B$15,0)),0)} -> 3788.4 | J46: =IFERROR(H46*I46,0) -> 1515360 | K46: =IFERROR(J46/'Tasas de Cambio'!$C$5,0) -> 505120 | M46: 28 ago 2026
A47: Traslados | B47: Italia | C47: 46522.0 | D47: Traslado puerto → Estación Ravenna | E47: EUR | F47: 12 | G47: 3 | H47: =IFERROR(F47*G47,0) -> 36 | I47: {=IFERROR(INDEX('Tasas de Cambio'!$E$11:$E$15,MATCH(E47,'Tasas de Cambio'!$B$11:$B$15,0)),0)} -> 3788.4 | J47: =IFERROR(H47*I47,0) -> 136382.4 | K47: =IFERROR(J47/'Tasas de Cambio'!$C$5,0) -> 45460.8 | M47: 27 ago 2026
A48: Comidas | B48: Rávena (Venecia) | C48: 46522 | D48: Almuerzo y cena | E48: EUR | F48: 30 | G48: 3 | H48: 90 | I48: {=IFERROR(INDEX('Tasas de Cambio'!$E$11:$E$15,MATCH(E48,'Tasas de Cambio'!$B$11:$B$15,0)),0)} -> 3788.4 | J48: 340956 | K48: =IFERROR(J48/'Tasas de Cambio'!$C$5,0) -> 113652
A49: Vuelos y Trenes | B49: Venecia / Bogota | C49: 46523.0 | D49: Vuelo internacional Venecia → Bogotá (regreso) | E49: COP | F49: 1500000 | G49: 3 | H49: =IFERROR(F49*G49,0) -> 4500000 | I49: {=IFERROR(INDEX('Tasas de Cambio'!$E$11:$E$15,MATCH(E49,'Tasas de Cambio'!$B$11:$B$15,0)),0)} -> 1 | J49: =IFERROR(H49*I49,0) -> 4500000 | K49: =IFERROR(J49/'Tasas de Cambio'!$C$5,0) -> 1500000 | L49: Air Europa UX1082, VCE 10:25 local → MAD 13:10; UX193 → BOG 18:15 (hora Colombia). | M49: 11 sep 2026
A50: Traslados | B50: Italia | C50: 46523 | D50: Traslado hotel → aeropuerto, Venecia | E50: EUR | F50: 30 | G50: 1 | H50: 30 | I50: {=IFERROR(INDEX('Tasas de Cambio'!$E$11:$E$15,MATCH(E50,'Tasas de Cambio'!$B$11:$B$15,0)),0)} -> 3788.4 | J50: 113652 | K50: =IFERROR(J50/'Tasas de Cambio'!$C$5,0) -> 37884
A51: Tours y Excursiones | B51: Venecia | C51: 15 May 2027 | D51: Free tour Venecia | E51: EUR | F51: 10 | G51: 3 | H51: =IFERROR(F51*G51,0) -> 30 | I51: {=IFERROR(INDEX('Tasas de Cambio'!$E$11:$E$15,MATCH(E51,'Tasas de Cambio'!$B$11:$B$15,0)),0)} -> 3788.4 | J51: =IFERROR(H51*I51,0) -> 113652 | K51: =IFERROR(J51/'Tasas de Cambio'!$C$5,0) -> 37884 | L51: Free tour guiado por el centro histórico de Venecia. https://www.civitatis.com/es/venecia/free-tour-venecia/?_gl=1*1ijxuzi*_up*MQ..*_ga*ODU4MDQyNjAyLjE3ODc4Nzc2ODY.*_ga_QJQ54CTKPM*czE3ODc4Nzc2ODYkbzEkZzEkdDE3ODc4Nzc2OTEkajU1JGwwJGgxNTA2MDA0ODU0 | M51: 27 ago 2026
A52: Comidas | B52: Venecia | C52: 46523.0 | D52: Desayuno | E52: EUR | F52: 12 | G52: 3 | H52: =IFERROR(F52*G52,0) -> 36 | I52: {=IFERROR(INDEX('Tasas de Cambio'!$E$11:$E$15,MATCH(E52,'Tasas de Cambio'!$B$11:$B$15,0)),0)} -> 3788.4 | J52: =IFERROR(H52*I52,0) -> 136382.4 | K52: =IFERROR(J52/'Tasas de Cambio'!$C$5,0) -> 45460.8 | L52: Almuerzo y cena incluidos en el vuelo de regreso (15h, sale 10:55am) | M52: 28 ago 2026
A53: Comidas | B53: — | C53: 30 Abr 2027 | D53: Comidas a bordo | E53: COP | F53: 0 | G53: 1 | H53: =IFERROR(F53*G53,0) -> 0 | I53: {=IFERROR(INDEX('Tasas de Cambio'!$E$11:$E$15,MATCH(E53,'Tasas de Cambio'!$B$11:$B$15,0)),0)} -> 1 | J53: =IFERROR(H53*I53,0) -> 0 | K53: =IFERROR(J53/'Tasas de Cambio'!$C$5,0) -> 0 | L53: Incluidas en el vuelo internacional | M53: 28 ago 2026
D54: TOTAL GENERAL | J54: =SUM(J5:J52) -> 37314742 | K54: =SUM(K5:K52) -> 12438247
A55: Comidas | B55: Navegación | C55: 9 May 2027 | D55: Incluidas en el crucero (come a bordo) | E55: COP | F55: 0 | G55: 1 | H55: =IFERROR(F55*G55,0) -> 0 | I55: {=IFERROR(INDEX('Tasas de Cambio'!$E$11:$E$15,MATCH(E55,'Tasas de Cambio'!$B$11:$B$15,0)),0)} -> 1 | J55: =IFERROR(H55*I55,0) -> 0 | K55: =IFERROR(J55/'Tasas de Cambio'!$C$5,0) -> 0 | M55: 28 ago 2026
A56: Comidas | B56: Navegación | C56: 13 May 2027 | D56: Incluidas en el crucero (come a bordo) | E56: COP | F56: 0 | G56: 1 | H56: =IFERROR(F56*G56,0) -> 0 | I56: {=IFERROR(INDEX('Tasas de Cambio'!$E$11:$E$15,MATCH(E56,'Tasas de Cambio'!$B$11:$B$15,0)),0)} -> 1 | J56: =IFERROR(H56*I56,0) -> 0 | K56: =IFERROR(J56/'Tasas de Cambio'!$C$5,0) -> 0 | M56: 28 ago 2026
A58: Traslados | B58: Italia | C58: 4 May 2027 | D58: Traslado estación → hotel, Florencia | E58: EUR | F58: 12 | G58: 1 | H58: =IFERROR(F58*G58,0) -> 12 | I58: {=IFERROR(INDEX('Tasas de Cambio'!$E$11:$E$15,MATCH(E58,'Tasas de Cambio'!$B$11:$B$15,0)),0)} -> 3788.4 | J58: =IFERROR(H58*I58,0) -> 45460.8 | K58: =IFERROR(J58/'Tasas de Cambio'!$C$5,0) -> 15153.6 | L58: Estimado: taxi corto, centro histórico (1 carro para el grupo) | M58: 29 ago 2026
A60: Alojamiento | B60: Florencia, Italia | C60: 4 – 6 May (2 noches) | D60: Hotel Florencia — costo total (2 noches) | E60: COP | F60: 1500000 | G60: 1 | H60: =IFERROR(F60*G60,0) -> 1500000 | I60: {=IFERROR(INDEX('Tasas de Cambio'!$E$11:$E$15,MATCH(E60,'Tasas de Cambio'!$B$11:$B$15,0)),0)} -> 1 | J60: =IFERROR(H60*I60,0) -> 1500000 | K60: =IFERROR(J60/'Tasas de Cambio'!$C$5,0) -> 500000 | L60: Appartamento luminoso e silenzioso, centro Firenze, 2 noches. https://www.booking.com/hotel/it/appartamento-luminoso-e-silenzioso-centro-firenze.es.html?aid=304142&label=gen173nr-10CA4oggI46AdIClgEaDKIAQGYATO4AQfIAQzYAQPoAQH4AQGIAgGoAgG4AsCS0tQGwAIB0gIkOGVkYmE2NGQtNGY0OS00MTU4LTgzNzAtZGVlNWVjY2Y3NmE32AIB4AIB&sid=f6a1a9bb810c453f7b5f1225205f1f26&all_sr_blocks=1056357901_385521136_3_0_0&checkin=2027-05-04&checkout=2027-05-06&dest_id=-117543&dest_type=city&dist=0&group_adults=3&group_children=0&hapos=1&highlighted_blocks=1056357901_385521136_3_0_0&hpos=1&matching_block_id=1056357901_385521136_3_0_0&nflt=fc%3D2&no_rooms=1&req_adults=3&req_children=0&room1=A%2CA%2CA&sb_price_type=total&sr_order=popularity&sr_pri_blocks=1056357901_385521136_3_0_0__35530&srepoch=1788120061&srpvid=65fe8c46f7330627&type=total&ucfs=1 | M60: 30 ago 2026
A61: Traslados | B61: Italia | C61: 6 May 2027 | D61: Traslado hotel → aeropuerto, Florencia | E61: EUR | F61: 20 | G61: 1 | H61: =IFERROR(F61*G61,0) -> 20 | I61: {=IFERROR(INDEX('Tasas de Cambio'!$E$11:$E$15,MATCH(E61,'Tasas de Cambio'!$B$11:$B$15,0)),0)} -> 3788.4 | J61: =IFERROR(H61*I61,0) -> 75768 | K61: =IFERROR(J61/'Tasas de Cambio'!$C$5,0) -> 25256 | L61: Estimado: taxi corto, aeropuerto muy cerca del centro | M61: 29 ago 2026

Sheet Cotizacion Milan
A2: COTIZACIÓN DETALLADA — EUROPA 2027 (30 Abr – 29 May 2027) | O2: Vuelos y Trenes | P2: EUR
O3: Traslados | P3: CHF
A4: Categoría | B4: Ciudad / País | C4: Fechas | D4: Concepto / Descripción | E4: Moneda | F4: Costo Unitario (moneda original) | G4: Cantidad | H4: Costo Total (moneda original) | I4: Tasa de Cambio a COP | J4: Costo Total (COP) | K4: Costo por Persona (COP) | L4: Notas | M4: Fecha confirmación precio | O4: Alojamiento | P4: CZK
A5: Seguro de Viaje | B5: Internacional | C5: 29 Abr – 30 May 2027 (31 días de cobertura) | D5: Asistencia médica internacional | E5: COP | F5: 443970 | G5: 3 | H5: =IFERROR(F5*G5,0) -> 1331910 | I5: {=IFERROR(INDEX('Tasas de Cambio'!$E$11:$E$15,MATCH(E5,'Tasas de Cambio'!$B$11:$B$15,0)),0)} -> 1 | J5: =IFERROR(H5*I5,0) -> 1331910 | K5: =IFERROR(J5/'Tasas de Cambio'!$C$5,0) -> 443970 | L5: Asistencia médica internacional, cobertura USD 60.000 (Cuponatic). https://www.cuponatic.com.co/descuento/asistencia-medica-internacional-cobertura-de-usd-60-000?m=tarjetas-de-asistencia&id_descuento=212587 | M5: 27 ago 2026
A6: Vuelos y Trenes | B6: Bogota / Milán | C6: 29 Abr 2027 | D6: Vuelo internacional Bogotá → Milán (ida) | E6: COP | F6: 1670000 | G6: 3 | H6: =IFERROR(F6*G6,0) -> 5010000 | I6: {=IFERROR(INDEX('Tasas de Cambio'!$E$11:$E$15,MATCH(E6,'Tasas de Cambio'!$B$11:$B$15,0)),0)} -> 1 | J6: =IFERROR(H6*I6,0) -> 5010000 | K6: =IFERROR(J6/'Tasas de Cambio'!$C$5,0) -> 1670000 | L6: Lufthansa · BOG 23:30 → LIN 22:05 (+1 día) · 1 escala (FRA) · Duración 15h35m · Economy Light. https://shop.lufthansa.com/booking/cart?cartId=1SA8AR74PERX9J3T&type=cart&shared=true&origin=BOG&utm_source=sharedcart&utm_medium=referral&consent=true | M6: 30 ago 2026
A7: Traslados | B7: Italia | C7: 30 Abr 2027 | D7: Traslado aeropuerto → hotel, Milán | E7: EUR | F7: 30 | G7: 1 | H7: =IFERROR(F7*G7,0) -> 30 | I7: {=IFERROR(INDEX('Tasas de Cambio'!$E$11:$E$15,MATCH(E7,'Tasas de Cambio'!$B$11:$B$15,0)),0)} -> 3788.4 | J7: =IFERROR(H7*I7,0) -> 113652 | K7: =IFERROR(J7/'Tasas de Cambio'!$C$5,0) -> 37884 | L7: Estimado: taxi tarifa fija Linate-centro €30 (1 carro para el grupo) | M7: 30 ago 2026
A8: Alojamiento | B8: Milán, Italia | C8: 30 Abr – 3 May (3 noches) | D8: Hotel Milán — costo total (3 noches) | E8: COP | F8: 2220000 | G8: 1 | H8: =IFERROR(F8*G8,0) -> 2220000 | I8: {=IFERROR(INDEX('Tasas de Cambio'!$E$11:$E$15,MATCH(E8,'Tasas de Cambio'!$B$11:$B$15,0)),0)} -> 1 | J8: =IFERROR(H8*I8,0) -> 2220000 | K8: =IFERROR(J8/'Tasas de Cambio'!$C$5,0) -> 740000 | L8: Ajustado proporcional a 3 noches (de cotización de 5), confirmar. https://www.booking.com/hotel/it/breramor.es.html?aid=2311236&label=es-co-booking-desktop-vjGZbEFOhRc3a9njxeT3IwS652829002024%3Apl%3Ata%3Ap1%3Ap2%3Aac%3Aap%3Aneg%3Afi%3Atikwd-65526620%3Alp9246960%3Ali%3Adec%3Adm&sid=f6a1a9bb810c453f7b5f1225205f1f26&all_sr_blocks=985025801_370905765_4_0_0&checkin=2027-05-01&checkout=2027-05-06&dest_id=2303&dest_type=district&dist=0&group_adults=3&group_children=0&hapos=1&highlighted_blocks=985025801_370905765_4_0_0&hpos=1&matching_block_id=985025801_370905765_4_0_0&no_rooms=1&req_adults=3&req_children=0&room1=A%2CA%2CA&sb_price_type=total&sr_order=popularity&sr_pri_blocks=985025801_370905765_4_0_0__84289&srepoch=1787963291&srpvid=81d403311ef809df&type=total&ucfs=1 | M8: 30 ago 2026
A9: Otros y Extras | B9: — | C9: Contingencia | D9: Imprevistos / gastos varios (contingencia) | E9: EUR | F9: 200 | G9: 3 | H9: 600 | I9: {=IFERROR(INDEX('Tasas de Cambio'!$E$11:$E$15,MATCH(E9,'Tasas de Cambio'!$B$11:$B$15,0)),0)} -> 3788.4 | J9: 2273040 | K9: =IFERROR(J9/'Tasas de Cambio'!$C$5,0) -> 757680 | L9: Aplica solo al plan corto — revisar si alcanza para 30 días | O9: Otros y Extras
A10: Otros y Extras | B10: — | C10: Durante el viaje | D10: SIM card de viaje (datos internacionales) | E10: USD | F10: 54 | G10: 1 | H10: 54 | I10: {=IFERROR(INDEX('Tasas de Cambio'!$E$11:$E$15,MATCH(E10,'Tasas de Cambio'!$B$11:$B$15,0)),0)} -> 3263.4 | J10: 176223.6 | K10: =IFERROR(J10/'Tasas de Cambio'!$C$5,0) -> 58741.2 | L10: SIM compartida entre las 3 personas para 17 días del viaje. https://esim.holafly.com/es/esim-europa/?selectedDays=17&startDate=2027-04-30&endDate=2027-05-16 | M10: 27 ago 2026
A11: Comidas | B11: Milán | C11: 1 May 2027 | D11: Comida del día (desayuno, almuerzo y cena) | E11: EUR | F11: 40 | G11: 3 | H11: =IFERROR(F11*G11,0) -> 120 | I11: {=IFERROR(INDEX('Tasas de Cambio'!$E$11:$E$15,MATCH(E11,'Tasas de Cambio'!$B$11:$B$15,0)),0)} -> 3788.4 | J11: =IFERROR(H11*I11,0) -> 454608 | K11: =IFERROR(J11/'Tasas de Cambio'!$C$5,0) -> 151536 | L11: Estimado: ~€40/persona/día (desayuno+almuerzo+cena) | M11: 30 ago 2026
A12: Tours y Excursiones | B12: Milán | C12: 1 May 2027 | D12: Duomo di Milano y terrazas (entrada) | E12: EUR | F12: 16 | G12: 3 | H12: =IFERROR(F12*G12,0) -> 48 | I12: {=IFERROR(INDEX('Tasas de Cambio'!$E$11:$E$15,MATCH(E12,'Tasas de Cambio'!$B$11:$B$15,0)),0)} -> 3788.4 | J12: =IFERROR(H12*I12,0) -> 181843.2 | K12: =IFERROR(J12/'Tasas de Cambio'!$C$5,0) -> 60614.4 | L12: Entrada terrazas con ascensor, precio oficial. https://ticket.duomomilano.it/en/categoria/terrazze/ | M12: 30 ago 2026
A13: Tours y Excursiones | B13: Milán | C13: 2 May 2027 | D13: Alpine Wonders: almuerzo en Diavolezza y tren Bernina | E13: USD | F13: 250 | G13: 3 | H13: =IFERROR(F13*G13,0) -> 750 | I13: {=IFERROR(INDEX('Tasas de Cambio'!$E$11:$E$15,MATCH(E13,'Tasas de Cambio'!$B$11:$B$15,0)),0)} -> 3263.4 | J13: =IFERROR(H13*I13,0) -> 2447550 | K13: =IFERROR(J13/'Tasas de Cambio'!$C$5,0) -> 815850 | L13: Excursión de día completo desde Milán, tren panorámico Bernina. https://www.tripadvisor.com/AttractionProductReview-g187849-d15090556-From_Milan_Alpine_Wonders_Lunch_at_Diavolezza_and_Bernina_Train-Milan_Lombardy.html | M13: 30 ago 2026
A14: Comidas | B14: Milán | C14: 2 May 2027 | D14: Comida del día (desayuno, almuerzo y cena) | E14: EUR | F14: 40 | G14: 3 | H14: =IFERROR(F14*G14,0) -> 120 | I14: {=IFERROR(INDEX('Tasas de Cambio'!$E$11:$E$15,MATCH(E14,'Tasas de Cambio'!$B$11:$B$15,0)),0)} -> 3788.4 | J14: =IFERROR(H14*I14,0) -> 454608 | K14: =IFERROR(J14/'Tasas de Cambio'!$C$5,0) -> 151536 | L14: Estimado: ~€40/persona/día (desayuno+almuerzo+cena) | M14: 30 ago 2026
A15: Vuelos y Trenes | B15: Milán / París | C15: 3 May 2027 | D15: Vuelo Milán → París, directo | E15: EUR | F15: 102 | G15: 3 | H15: =IFERROR(F15*G15,0) -> 306 | I15: {=IFERROR(INDEX('Tasas de Cambio'!$E$11:$E$15,MATCH(E15,'Tasas de Cambio'!$B$11:$B$15,0)),0)} -> 3788.4 | J15: =IFERROR(H15*I15,0) -> 1159250.4 | K15: =IFERROR(J15/'Tasas de Cambio'!$C$5,0) -> 386416.8 | L15: easyJet EJU4890 · LIN 08:30 → ORY 09:55 · Duración 1h25m · directo | M15: 30 ago 2026
A16: Traslados | B16: Italia | C16: 3 May 2027 | D16: Traslado hotel → aeropuerto, Milán | E16: EUR | F16: 10 | G16: 3 | H16: =IFERROR(F16*G16,0) -> 30 | I16: {=IFERROR(INDEX('Tasas de Cambio'!$E$11:$E$15,MATCH(E16,'Tasas de Cambio'!$B$11:$B$15,0)),0)} -> 3788.4 | J16: =IFERROR(H16*I16,0) -> 113652 | K16: =IFERROR(J16/'Tasas de Cambio'!$C$5,0) -> 37884 | L16: Estimado: taxi tarifa fija Linate-centro €30 (1 carro para el grupo) | M16: 30 ago 2026
A17: Traslados | B17: Francia | C17: 3 May 2027 | D17: Traslado estación/aeropuerto → hotel, París | E17: EUR | F17: 12.33 | G17: 3 | H17: =IFERROR(F17*G17,0) -> 36.99 | I17: {=IFERROR(INDEX('Tasas de Cambio'!$E$11:$E$15,MATCH(E17,'Tasas de Cambio'!$B$11:$B$15,0)),0)} -> 3788.4 | J17: =IFERROR(H17*I17,0) -> 140132.92 | K17: =IFERROR(J17/'Tasas de Cambio'!$C$5,0) -> 46710.972 | L17: Estimado: taxi tarifa fija Orly-centro (Rive Droite) €37 (1 carro para el grupo) | M17: 30 ago 2026
A18: Alojamiento | B18: París, Francia | C18: 3 – 6 May (3 noches) | D18: Hotel París — costo por noche | E18: EUR | F18: 150 | G18: 3 | H18: 450 | I18: {=IFERROR(INDEX('Tasas de Cambio'!$E$11:$E$15,MATCH(E18,'Tasas de Cambio'!$B$11:$B$15,0)),0)} -> 3788.4 | J18: 1704780 | K18: =IFERROR(J18/'Tasas de Cambio'!$C$5,0) -> 568260 | L18: Recomendado: Hôtel Augustin - Astotel, boutique 4*, a 1 min de Boulevard Haussmann y 500m de Gare Saint-Lazare (zona Opéra/Grands Boulevards, muy céntrica y bien conectada). Cadena Astotel, buena calificación en Booking (~8.5+). https://www.booking.com/budget/city/fr/paris.en-gb.html
A19: Comidas | B19: París | C19: 3 May 2027 | D19: Comida del día (desayuno, almuerzo y cena) | E19: EUR | F19: 62 | G19: 3 | H19: =IFERROR(F19*G19,0) -> 186 | I19: {=IFERROR(INDEX('Tasas de Cambio'!$E$11:$E$15,MATCH(E19,'Tasas de Cambio'!$B$11:$B$15,0)),0)} -> 3788.4 | J19: =IFERROR(H19*I19,0) -> 704642.4 | K19: =IFERROR(J19/'Tasas de Cambio'!$C$5,0) -> 234880.8 | M19: 28 ago 2026
A20: Tours y Excursiones | B20: Francia | C20: 4 May 2027 | D20: Entrada Disneyland Paris — 1 día / 2 parques | E20: EUR | F20: 110 | G20: 3 | H20: 330 | I20: {=IFERROR(INDEX('Tasas de Cambio'!$E$11:$E$15,MATCH(E20,'Tasas de Cambio'!$B$11:$B$15,0)),0)} -> 3788.4 | J20: 1250172 | K20: =IFERROR(J20/'Tasas de Cambio'!$C$5,0) -> 416724 | L20: Recomendado: Ticket 1 día / 2 parques, tarifa media temporada. https://www.attractiontickets.com/en/paris-attraction-tickets/disneyland-paris-tickets/1-day-2-parks-disneyland-paris-hopper-ticket
A21: Comidas | B21: París | C21: 4 May 2027 | D21: Comida del día (desayuno, almuerzo y cena) | E21: EUR | F21: 62 | G21: 3 | H21: =IFERROR(F21*G21,0) -> 186 | I21: {=IFERROR(INDEX('Tasas de Cambio'!$E$11:$E$15,MATCH(E21,'Tasas de Cambio'!$B$11:$B$15,0)),0)} -> 3788.4 | J21: =IFERROR(H21*I21,0) -> 704642.4 | K21: =IFERROR(J21/'Tasas de Cambio'!$C$5,0) -> 234880.8 | M21: 28 ago 2026
A22: Tours y Excursiones | B22: Francia | C22: 5 May 2027 | D22: Crucero por el Sena | E22: EUR | F22: 19 | G22: 3 | H22: 57 | I22: {=IFERROR(INDEX('Tasas de Cambio'!$E$11:$E$15,MATCH(E22,'Tasas de Cambio'!$B$11:$B$15,0)),0)} -> 3788.4 | J22: 215938.8 | K22: =IFERROR(J22/'Tasas de Cambio'!$C$5,0) -> 71979.6 | L22: Recomendado: Crucero panorámico Bateaux Mouches, 1h10m. https://ryo.co/en/articles/france/paris/how-to-take-seine-cruise-paris/
A23: Comidas | B23: París | C23: 5 May 2027 | D23: Comida del día (desayuno, almuerzo y cena) | E23: EUR | F23: 62 | G23: 3 | H23: =IFERROR(F23*G23,0) -> 186 | I23: {=IFERROR(INDEX('Tasas de Cambio'!$E$11:$E$15,MATCH(E23,'Tasas de Cambio'!$B$11:$B$15,0)),0)} -> 3788.4 | J23: =IFERROR(H23*I23,0) -> 704642.4 | K23: =IFERROR(J23/'Tasas de Cambio'!$C$5,0) -> 234880.8 | M23: 28 ago 2026
A24: Vuelos y Trenes | B24: París / Barcelona | C24: 6 May 2027 | D24: Vuelo interno París → Barcelona | E24: EUR | F24: 130 | G24: 3 | H24: 390 | I24: {=IFERROR(INDEX('Tasas de Cambio'!$E$11:$E$15,MATCH(E24,'Tasas de Cambio'!$B$11:$B$15,0)),0)} -> 3788.4 | J24: 1477476 | K24: =IFERROR(J24/'Tasas de Cambio'!$C$5,0) -> 492492 | L24: Vuelo Vueling, París (CDG/ORY) → Barcelona, directo, ~1h40m. Incluye 1 maleta de mano + 1 facturada (23kg). https://www.omio.com/flights/paris/barcelona
A25: Traslados | B25: Francia | C25: 6 May 2027 | D25: Traslado hotel → aeropuerto, París | E25: EUR | F25: 50 | G25: 1 | H25: 50 | I25: {=IFERROR(INDEX('Tasas de Cambio'!$E$11:$E$15,MATCH(E25,'Tasas de Cambio'!$B$11:$B$15,0)),0)} -> 3788.4 | J25: 189420 | K25: =IFERROR(J25/'Tasas de Cambio'!$C$5,0) -> 63140 | L25: Estimado: Uber/taxi al aeropuerto (CDG/Orly), ~45-60 min, €45-60.
A26: Traslados | B26: España | C26: 6 May 2027 | D26: Traslado aeropuerto → hotel, Barcelona | E26: EUR | F26: 40 | G26: 1 | H26: 40 | I26: {=IFERROR(INDEX('Tasas de Cambio'!$E$11:$E$15,MATCH(E26,'Tasas de Cambio'!$B$11:$B$15,0)),0)} -> 3788.4 | J26: 151536 | K26: =IFERROR(J26/'Tasas de Cambio'!$C$5,0) -> 50512
A27: Alojamiento | B27: Barcelona, España | C27: 6 – 8 May (2 noches, pre-crucero) | D27: Hotel Barcelona — costo total (2 noches) | E27: COP | F27: 1900000 | G27: 1 | H27: =IFERROR(F27*G27,0) -> 1900000 | I27: {=IFERROR(INDEX('Tasas de Cambio'!$E$11:$E$15,MATCH(E27,'Tasas de Cambio'!$B$11:$B$15,0)),0)} -> 1 | J27: =IFERROR(H27*I27,0) -> 1900000 | K27: =IFERROR(J27/'Tasas de Cambio'!$C$5,0) -> 633333.33 | L27: Sagrada Familia, 2 noches (6-8 may). https://www.booking.com/hotel/es/sagradafamilia.es.html?aid=2311236&label=es-co-booking-desktop-vjGZbEFOhRc3a9njxeT3IwS652829002024%3Apl%3Ata%3Ap1%3Ap2%3Aac%3Aap%3Aneg%3Afi%3Atikwd-65526620%3Alp9246960%3Ali%3Adec%3Adm&sid=f6a1a9bb810c453f7b5f1225205f1f26&all_sr_blocks=9118812_91908190_0_2_0&checkin=2027-05-06&checkout=2027-05-08&dest_id=-372490&dest_type=city&dist=0&group_adults=3&group_children=0&hapos=1&highlighted_blocks=9118812_91908190_0_2_0&hpos=1&matching_block_id=9118812_91908190_0_2_0&no_rooms=1&req_adults=3&req_children=0&room1=A%2CA%2CA&sb_price_type=total&sr_order=popularity&sr_pri_blocks=9118812_91908190_0_2_0__37600&srepoch=1787875557&srpvid=a2d600b07c230149&type=total&ucfs=1 | M27: 27 ago 2026
A28: Comidas | B28: Barcelona | C28: 6 May 2027 | D28: cena | E28: EUR | F28: 15 | G28: 3 | H28: 45 | I28: {=IFERROR(INDEX('Tasas de Cambio'!$E$11:$E$15,MATCH(E28,'Tasas de Cambio'!$B$11:$B$15,0)),0)} -> 3788.4 | J28: 170478 | K28: =IFERROR(J28/'Tasas de Cambio'!$C$5,0) -> 56826
A29: Traslados | B29: Barcelona | C29: 7 May 2027 | D29: Bus, 4 trayectos | E29: EUR | F29: 12 | G29: 3 | H29: 36 | I29: {=IFERROR(INDEX('Tasas de Cambio'!$E$11:$E$15,MATCH(E29,'Tasas de Cambio'!$B$11:$B$15,0)),0)} -> 3788.4 | J29: 136382.4 | K29: =IFERROR(J29/'Tasas de Cambio'!$C$5,0) -> 45460.8
A30: Tours y Excursiones | B30: Barcelona | C30: 7 May 2027 | D30: Tour Barcelona Modernista | E30: USD | F30: 10 | G30: 3 | H30: =IFERROR(F30*G30,0) -> 30 | I30: {=IFERROR(INDEX('Tasas de Cambio'!$E$11:$E$15,MATCH(E30,'Tasas de Cambio'!$B$11:$B$15,0)),0)} -> 3263.4 | J30: =IFERROR(H30*I30,0) -> 97902 | K30: =IFERROR(J30/'Tasas de Cambio'!$C$5,0) -> 32634 | L30: Tour guiado por el Modernismo catalán en Barcelona. https://www.civitatis.com/es/barcelona/tour-barcelona-modernista/ | M30: 27 ago 2026
A31: Comidas | B31: Barcelona | C31: 7 May 2027 | D31: 3 comidas | E31: EUR | F31: 30 | G31: 3 | H31: 90 | I31: {=IFERROR(INDEX('Tasas de Cambio'!$E$11:$E$15,MATCH(E31,'Tasas de Cambio'!$B$11:$B$15,0)),0)} -> 3788.4 | J31: 340956 | K31: =IFERROR(J31/'Tasas de Cambio'!$C$5,0) -> 113652
A32: Traslados | B32: España | C32: 8 May 2027 | D32: Traslado hotel → puerto (embarque crucero), Barcelona | E32: EUR | F32: 30 | G32: 1 | H32: 30 | I32: {=IFERROR(INDEX('Tasas de Cambio'!$E$11:$E$15,MATCH(E32,'Tasas de Cambio'!$B$11:$B$15,0)),0)} -> 3788.4 | J32: 113652 | K32: =IFERROR(J32/'Tasas de Cambio'!$C$5,0) -> 37884
A33: Crucero | B33: Mediterráneo | C33: 8 – 15 May (7 noches) | D33: Crucero Barcelona → Ravena — tarifa por persona (cabina) | E33: USD | F33: 670 | G33: 3 | H33: =IFERROR(F33*G33,0) -> 2010 | I33: {=IFERROR(INDEX('Tasas de Cambio'!$E$11:$E$15,MATCH(E33,'Tasas de Cambio'!$B$11:$B$15,0)),0)} -> 3263.4 | J33: =IFERROR(H33*I33,0) -> 6559434 | K33: =IFERROR(J33/'Tasas de Cambio'!$C$5,0) -> 2186478 | L33: Crucero Barcelona-Ravena, 7 noches, incluye propinas. https://www.royalcaribbean.com/lac/es/itinerary/7-night-italy-croatia-cruise-from-barcelona-on-brilliance-BR07M885?sailDate=2027-05-08&packageCode=BR07M885&groupId=BR07BCN-1768961711&country=COL&search=startDate:2027-05-01~2027-05-31 | M33: 27 ago 2026
A34: Tours y Excursiones | B34: Barcelona | C34: 8 May 2027 | D34: N/A (día de embarque) | E34: EUR | F34: 0 | G34: 3 | H34: 0 | I34: {=IFERROR(INDEX('Tasas de Cambio'!$E$11:$E$15,MATCH(E34,'Tasas de Cambio'!$B$11:$B$15,0)),0)} -> 3788.4 | J34: 0 | K34: =IFERROR(J34/'Tasas de Cambio'!$C$5,0) -> 0
A35: Comidas | B35: Barcelona | C35: 8 May 2027 | D35: desayuno | E35: EUR | F35: 10 | G35: 3 | H35: 30 | I35: {=IFERROR(INDEX('Tasas de Cambio'!$E$11:$E$15,MATCH(E35,'Tasas de Cambio'!$B$11:$B$15,0)),0)} -> 3788.4 | J35: 113652 | K35: =IFERROR(J35/'Tasas de Cambio'!$C$5,0) -> 37884
A36: Traslados | B36: Venecia | C36: 15 May 2027 | D36: Vaporetti ACTV | E36: EUR | F36: 25 | G36: 3 | H36: =IFERROR(F36*G36,0) -> 75 | I36: {=IFERROR(INDEX('Tasas de Cambio'!$E$11:$E$15,MATCH(E36,'Tasas de Cambio'!$B$11:$B$15,0)),0)} -> 3788.4 | J36: =IFERROR(H36*I36,0) -> 284130 | K36: =IFERROR(J36/'Tasas de Cambio'!$C$5,0) -> 94710 | L36: Boletos de vaporetto (transporte acuático) por Venecia. https://book.tickets-venice.com/es/book/8748/select/?_gl=1%2A1073ils%2A_gcl_aw%2AR0NMLjE3ODc4NzgwODMuRUFJYUlRb2JDaE1JaFpPNjdZekNsZ01Wd1lSYUJSM2Y1U1JPRUFBWUF5QUFFZ0tjeFBEX0J3RQ..%2A_gcl_au%2ANzIxMTA1MTQ5LjE3ODc4NzgwODMuLS4tLjE3ODc4NzgwODMuMTE2MDU2ODc1MS4xNzg3ODc4MDg0LjE3ODc4NzgwODM.%2A_ga%2ANDcyOTU3MzYyLjE3ODc4NzgwODM.%2A_ga_Y45PC9R73C%2AczE3ODc4NzgwODMkbzEkZzAkdDE3ODc4NzgwODQkajU5JGwwJGgw&cookieBanner=false&date=2027-05-15&tourId=15560&variantId=15560 | M36: 27 ago 2026
A37: Tours y Excursiones | B37: La Spezia (Florencia/Pisa) | C37: 10 May 2027 | D37: Panoramic Pisa | E37: USD | F37: 70 | G37: 3 | H37: =IFERROR(F37*G37,0) -> 210 | I37: {=IFERROR(INDEX('Tasas de Cambio'!$E$11:$E$15,MATCH(E37,'Tasas de Cambio'!$B$11:$B$15,0)),0)} -> 3263.4 | J37: =IFERROR(H37*I37,0) -> 685314 | K37: =IFERROR(J37/'Tasas de Cambio'!$C$5,0) -> 228438 | L37: Excursión panorámica por Pisa desde el crucero. https://www.royalcaribbean.com/account/cruise-planner/category/shorex/product/Y8RO?bookingId=3113096&shipCode=BR&sailDate=20270508 | M37: 27 ago 2026
